Workbook
Name Customer_Name: OFFSET('Customer Name'!$D$2,,,COUNTIF('Customer Name'!$D:$D,"*?")-1)
Name d: OFFSET('[1]Customer Name'!$D$2,,,COUNTIF('[1]Customer Name'!$D:$D,"*?")-1)
Name Make: OFFSET(Make!$D$2,,,COUNTIF(Make!$D:$D,"*?")-1)
Name Products: OFFSET(Product!$D$2,,,COUNTIF(Product!$D:$D,"*?")-1)
Name Raw_Material: OFFSET('Raw material'!$D$2,,,COUNTIF('Raw material'!$D:$D,"*?")-1)
Name Supplier: OFFSET(Supplier!$D$2,,,COUNTIF(Supplier!$D:$D,"*?")-1)

Sheet Legend
A1: * Before editing, Latest file to be considered
A2: * Green Label Columns only Editable
A3: * Red Label Columns are not Editable
A4: * Fitting Ratio: First number indicates STRAIGHT & Second Number Indicates FITTINGS always.
A5: 70-30 ( Indicates 70% straight & 30% Fittings) same format to be used while writing
A6: Planning: If your using AMNS Make or 1250 Width Coil, Please mention make in Remarks Column (Consumption)

Sheet Purchase
K1: SUM(Rs) | N1: =SUM(N3:N1048576) -> 33293758 | O1: =SUM(O3:O1048576) -> 2915240.7 | P1: =SUM(P3:P1048576) -> 2915240.7 | Q1: =SUM(Q3:Q1048576) -> 178191.07 | R1: =SUM(R3:R1048576) -> 149916 | T1: =SUM(T3:T1048576) -> 39452347
A2: SI NO | B2: MONTH | C2: DATE | D2: PO NO | E2: PO DATE | F2: SUPPLIER | G2: MAKE | H2: INV NO | I2: IGR NO | J2: RAW MATERIAL | K2: UNIT | L2: QTY | M2: Rate | N2: BASIC | O2: CGST | P2: SGST | Q2: IGST | R2: TRANS. AS INVOICE | S2: TRANS./UNIT | T2: TOTAL
A3: =IF(C3="","",COUNT($C$3:C3)) -> 1 | B3: =IF(C3="","",TEXT(C3,"mmmm")) -> April | C3: 44652 | F3: Opening stock | G3: JSW | J3: 120gsm 26G | K3: =IF(ISNUMBER(SEARCH("gsm",J:J)),"Kg's",IF(ISNUMBER(SEARCH("Tape",J:J)),"Roll",IF(ISNUMBER(SEARCH("Thermal",J:J)),"Sqmt",IF(ISNUMBER(SEARCH("Acou",J:J)),"Sqmt",IF(ISNUMBER(SEARCH("ss",J:J)),"Kg's",IF(ISNUMBER(SEARCH("Alu",J:J)),"Kg's",IF(ISNUMBER(SEARCH("Gasket",J:J)),"Rmt",IF(ISNUMBER(SEARCH("Cleats",J:J)),"No's",IF(ISNUMBER(SEARCH("Tube",J:J)),"No's",IF(ISNUMBER(SEARCH("Bracket",J:J)),"No's",IF(ISNUMBER(SEARCH("Corner",J:J)),"No's",IF(ISNUMBER(SEARCH("MS",J:J)),"Kg's",IF(ISNUMBER(SEARCH("Bucket",J:J)),"Kg's",IF(ISNUMBER(SEARCH("stretch",J:J)),"Kg's",IF(ISNUMBER(SEARCH("Bubble",J:J)),"Roll",IF(ISNUMBER(SEARCH("JTR",J:J)),"Rmt",IF(ISNUMBER(SEARCH("Rod",J:J)),"Kg's",IF(ISNUMBER(SEARCH("Handle",J:J)),"No's",IF(ISNUMBER(SEARCH("Gear",J:J)),"No's",IF(ISNUMBER(SEARCH("Bush",J:J)),"No's","")))))))))))))))))))) -> Kg's | L3: 1835 | T3: =IF(N3="","",SUM(N3,O3,P3,Q3,R3))
A4: =IF(C4="","",COUNT($C$3:C4)) -> 2 | B4: =IF(C4="","",TEXT(C4,"mmmm")) -> April | C4: 44652 | F4: Opening stock | G4: JSW | J4: 120gsm 24G | K4: =IF(ISNUMBER(SEARCH("gsm",J:J)),"Kg's",IF(ISNUMBER(SEARCH("Tape",J:J)),"Roll",IF(ISNUMBER(SEARCH("Thermal",J:J)),"Sqmt",IF(ISNUMBER(SEARCH("Acou",J:J)),"Sqmt",IF(ISNUMBER(SEARCH("ss",J:J)),"Kg's",IF(ISNUMBER(SEARCH("Alu",J:J)),"Kg's",IF(ISNUMBER(SEARCH("Gasket",J:J)),"Rmt",IF(ISNUMBER(SEARCH("Cleats",J:J)),"No's",IF(ISNUMBER(SEARCH("Tube",J:J)),"No's",IF(ISNUMBER(SEARCH("Bracket",J:J)),"No's",IF(ISNUMBER(SEARCH("Corner",J:J)),"No's",IF(ISNUMBER(SEARCH("MS",J:J)),"Kg's",IF(ISNUMBER(SEARCH("Bucket",J:J)),"Kg's",IF(ISNUMBER(SEARCH("stretch",J:J)),"Kg's",IF(ISNUMBER(SEARCH("Bubble",J:J)),"Roll",IF(ISNUMBER(SEARCH("JTR",J:J)),"Rmt",IF(ISNUMBER(SEARCH("Rod",J:J)),"Kg's",IF(ISNUMBER(SEARCH("Handle",J:J)),"No's",IF(ISNUMBER(SEARCH("Gear",J:J)),"No's",IF(ISNUMBER(SEARCH("Bush",J:J)),"No's","")))))))))))))))))))) -> Kg's | L4: =12196+1241+1934+49.5+1412 -> 16832.5 | T4: =IF(N4="","",SUM(N4,O4,P4,Q4,R4))
A5: =IF(C5="","",COUNT($C$3:C5)) -> 3 | B5: =IF(C5="","",TEXT(C5,"mmmm")) -> April | C5: 44652 | F5: Opening stock | G5: JSW | J5: 120gsm 22G | K5: =IF(ISNUMBER(SEARCH("gsm",J:J)),"Kg's",IF(ISNUMBER(SEARCH("Tape",J:J)),"Roll",IF(ISNUMBER(SEARCH("Thermal",J:J)),"Sqmt",IF(ISNUMBER(SEARCH("Acou",J:J)),"Sqmt",IF(ISNUMBER(SEARCH("ss",J:J)),"Kg's",IF(ISNUMBER(SEARCH("Alu",J:J)),"Kg's",IF(ISNUMBER(SEARCH("Gasket",J:J)),"Rmt",IF(ISNUMBER(SEARCH("Cleats",J:J)),"No's",IF(ISNUMBER(SEARCH("Tube",J:J)),"No's",IF(ISNUMBER(SEARCH("Bracket",J:J)),"No's",IF(ISNUMBER(SEARCH("Corner",J:J)),"No's",IF(ISNUMBER(SEARCH("MS",J:J)),"Kg's",IF(ISNUMBER(SEARCH("Bucket",J:J)),"Kg's",IF(ISNUMBER(SEARCH("stretch",J:J)),"Kg's",IF(ISNUMBER(SEARCH("Bubble",J:J)),"Roll",IF(ISNUMBER(SEARCH("JTR",J:J)),"Rmt",IF(ISNUMBER(SEARCH("Rod",J:J)),"Kg's",IF(ISNUMBER(SEARCH("Handle",J:J)),"No's",IF(ISNUMBER(SEARCH("Gear",J:J)),"No's",IF(ISNUMBER(SEARCH("Bush",J:J)),"No's","")))))))))))))))))))) -> Kg's | L5: =5528+1228.4+99.2 -> 6855.6 | T5: =IF(N5="","",SUM(N5,O5,P5,Q5,R5))
A6: =IF(C6="","",COUNT($C$3:C6)) -> 4 | B6: =IF(C6="","",TEXT(C6,"mmmm")) -> April | C6: 44652 | F6: Opening stock | G6: JSW | J6: 120gsm 20G | K6: =IF(ISNUMBER(SEARCH("gsm",J:J)),"Kg's",IF(ISNUMBER(SEARCH("Tape",J:J)),"Roll",IF(ISNUMBER(SEARCH("Thermal",J:J)),"Sqmt",IF(ISNUMBER(SEARCH("Acou",J:J)),"Sqmt",IF(ISNUMBER(SEARCH("ss",J:J)),"Kg's",IF(ISNUMBER(SEARCH("Alu",J:J)),"Kg's",IF(ISNUMBER(SEARCH("Gasket",J:J)),"Rmt",IF(ISNUMBER(SEARCH("Cleats",J:J)),"No's",IF(ISNUMBER(SEARCH("Tube",J:J)),"No's",IF(ISNUMBER(SEARCH("Bracket",J:J)),"No's",IF(ISNUMBER(SEARCH("Corner",J:J)),"No's",IF(ISNUMBER(SEARCH("MS",J:J)),"Kg's",IF(ISNUMBER(SEARCH("Bucket",J:J)),"Kg's",IF(ISNUMBER(SEARCH("stretch",J:J)),"Kg's",IF(ISNUMBER(SEARCH("Bubble",J:J)),"Roll",IF(ISNUMBER(SEARCH("JTR",J:J)),"Rmt",IF(ISNUMBER(SEARCH("Rod",J:J)),"Kg's",IF(ISNUMBER(SEARCH("Handle",J:J)),"No's",IF(ISNUMBER(SEARCH("Gear",J:J)),"No's",IF(ISNUMBER(SEARCH("Bush",J:J)),"No's","")))))))))))))))))))) -> Kg's | L6: =2856+2189.9+503.2 -> 5549.1 | T6: =IF(N6="","",SUM(N6,O6,P6,Q6,R6))
A7: =IF(C7="","",COUNT($C$3:C7)) -> 5 | B7: =IF(C7="","",TEXT(C7,"mmmm")) -> April | C7: 44652 | F7: Opening stock | G7: JSW | J7: 120gsm 18G | K7: =IF(ISNUMBER(SEARCH("gsm",J:J)),"Kg's",IF(ISNUMBER(SEARCH("Tape",J:J)),"Roll",IF(ISNUMBER(SEARCH("Thermal",J:J)),"Sqmt",IF(ISNUMBER(SEARCH("Acou",J:J)),"Sqmt",IF(ISNUMBER(SEARCH("ss",J:J)),"Kg's",IF(ISNUMBER(SEARCH("Alu",J:J)),"Kg's",IF(ISNUMBER(SEARCH("Gasket",J:J)),"Rmt",IF(ISNUMBER(SEARCH("Cleats",J:J)),"No's",IF(ISNUMBER(SEARCH("Tube",J:J)),"No's",IF(ISNUMBER(SEARCH("Bracket",J:J)),"No's",IF(ISNUMBER(SEARCH("Corner",J:J)),"No's",IF(ISNUMBER(SEARCH("MS",J:J)),"Kg's",IF(ISNUMBER(SEARCH("Bucket",J:J)),"Kg's",IF(ISNUMBER(SEARCH("stretch",J:J)),"Kg's",IF(ISNUMBER(SEARCH("Bubble",J:J)),"Roll",IF(ISNUMBER(SEARCH("JTR",J:J)),"Rmt",IF(ISNUMBER(SEARCH("Rod",J:J)),"Kg's",IF(ISNUMBER(SEARCH("Handle",J:J)),"No's",IF(ISNUMBER(SEARCH("Gear",J:J)),"No's",IF(ISNUMBER(SEARCH("Bush",J:J)),"No's","")))))))))))))))))))) -> Kg's | L7: 6453 | T7: =IF(N7="","",SUM(N7,O7,P7,Q7,R7))
A8: =IF(C8="","",COUNT($C$3:C8)) -> 6 | B8: =IF(C8="","",TEXT(C8,"mmmm")) -> April | C8: 44652 | F8: Opening stock | G8: JSW | J8: 120gsm Slit 26G | K8: =IF(ISNUMBER(SEARCH("gsm",J:J)),"Kg's",IF(ISNUMBER(SEARCH("Tape",J:J)),"Roll",IF(ISNUMBER(SEARCH("Thermal",J:J)),"Sqmt",IF(ISNUMBER(SEARCH("Acou",J:J)),"Sqmt",IF(ISNUMBER(SEARCH("ss",J:J)),"Kg's",IF(ISNUMBER(SEARCH("Alu",J:J)),"Kg's",IF(ISNUMBER(SEARCH("Gasket",J:J)),"Rmt",IF(ISNUMBER(SEARCH("Cleats",J:J)),"No's",IF(ISNUMBER(SEARCH("Tube",J:J)),"No's",IF(ISNUMBER(SEARCH("Bracket",J:J)),"No's",IF(ISNUMBER(SEARCH("Corner",J:J)),"No's",IF(ISNUMBER(SEARCH("MS",J:J)),"Kg's",IF(ISNUMBER(SEARCH("Bucket",J:J)),"Kg's",IF(ISNUMBER(SEARCH("stretch",J:J)),"Kg's",IF(ISNUMBER(SEARCH("Bubble",J:J)),"Roll",IF(ISNUMBER(SEARCH("JTR",J:J)),"Rmt",IF(ISNUMBER(SEARCH("Rod",J:J)),"Kg's",IF(ISNUMBER(SEARCH("Handle",J:J)),"No's",IF(ISNUMBER(SEARCH("Gear",J:J)),"No's",IF(ISNUMBER(SEARCH("Bush",J:J)),"No's","")))))))))))))))))))) -> Kg's | L8: 2970 | T8: =IF(N8="","",SUM(N8,O8,P8,Q8,R8))
A9: =IF(C9="","",COUNT($C$3:C9)) -> 7 | B9: =IF(C9="","",TEXT(C9,"mmmm")) -> April | C9: 44652 | F9: Opening stock | G9: JSW | J9: 120gsm Slit 24G | K9: =IF(ISNUMBER(SEARCH("gsm",J:J)),"Kg's",IF(ISNUMBER(SEARCH("Tape",J:J)),"Roll",IF(ISNUMBER(SEARCH("Thermal",J:J)),"Sqmt",IF(ISNUMBER(SEARCH("Acou",J:J)),"Sqmt",IF(ISNUMBER(SEARCH("ss",J:J)),"Kg's",IF(ISNUMBER(SEARCH("Alu",J:J)),"Kg's",IF(ISNUMBER(SEARCH("Gasket",J:J)),"Rmt",IF(ISNUMBER(SEARCH("Cleats",J:J)),"No's",IF(ISNUMBER(SEARCH("Tube",J:J)),"No's",IF(ISNUMBER(SEARCH("Bracket",J:J)),"No's",IF(ISNUMBER(SEARCH("Corner",J:J)),"No's",IF(ISNUMBER(SEARCH("MS",J:J)),"Kg's",IF(ISNUMBER(SEARCH("Bucket",J:J)),"Kg's",IF(ISNUMBER(SEARCH("stretch",J:J)),"Kg's",IF(ISNUMBER(SEARCH("Bubble",J:J)),"Roll",IF(ISNUMBER(SEARCH("JTR",J:J)),"Rmt",IF(ISNUMBER(SEARCH("Rod",J:J)),"Kg's",IF(ISNUMBER(SEARCH("Handle",J:J)),"No's",IF(ISNUMBER(SEARCH("Gear",J:J)),"No's",IF(ISNUMBER(SEARCH("Bush",J:J)),"No's","")))))))))))))))))))) -> Kg's | L9: =13279+3307.6 -> 16586.6 | T9: =IF(N9="","",SUM(N9,O9,P9,Q9,R9))
A10: =IF(C10="","",COUNT($C$3:C10)) -> 8 | B10: =IF(C10="","",TEXT(C10,"mmmm")) -> April | C10: 44652 | F10: Opening stock | G10: JSW | J10: 120gsm Slit 22G | K10: =IF(ISNUMBER(SEARCH("gsm",J:J)),"Kg's",IF(ISNUMBER(SEARCH("Tape",J:J)),"Roll",IF(ISNUMBER(SEARCH("Thermal",J:J)),"Sqmt",IF(ISNUMBER(SEARCH("Acou",J:J)),"Sqmt",IF(ISNUMBER(SEARCH("ss",J:J)),"Kg's",IF(ISNUMBER(SEARCH("Alu",J:J)),"Kg's",IF(ISNUMBER(SEARCH("Gasket",J:J)),"Rmt",IF(ISNUMBER(SEARCH("Cleats",J:J)),"No's",IF(ISNUMBER(SEARCH("Tube",J:J)),"No's",IF(ISNUMBER(SEARCH("Bracket",J:J)),"No's",IF(ISNUMBER(SEARCH("Corner",J:J)),"No's",IF(ISNUMBER(SEARCH("MS",J:J)),"Kg's",IF(ISNUMBER(SEARCH("Bucket",J:J)),"Kg's",IF(ISNUMBER(SEARCH("stretch",J:J)),"Kg's",IF(ISNUMBER(SEARCH("Bubble",J:J)),"Roll",IF(ISNUMBER(SEARCH("JTR",J:J)),"Rmt",IF(ISNUMBER(SEARCH("Rod",J:J)),"Kg's",IF(ISNUMBER(SEARCH("Handle",J:J)),"No's",IF(ISNUMBER(SEARCH("Gear",J:J)),"No's",IF(ISNUMBER(SEARCH("Bush",J:J)),"No's","")))))))))))))))))))) -> Kg's | L10: =22155.4+5516.4+26.4 -> 27698.2 | T10: =IF(N10="","",SUM(N10,O10,P10,Q10,R10))
A11: =IF(C11="","",COUNT($C$3:C11)) -> 9 | B11: =IF(C11="","",TEXT(C11,"mmmm")) -> April | C11: 44652 | F11: Opening stock | G11: JSW | J11: 120gsm Slit 20G | K11: =IF(ISNUMBER(SEARCH("gsm",J:J)),"Kg's",IF(ISNUMBER(SEARCH("Tape",J:J)),"Roll",IF(ISNUMBER(SEARCH("Thermal",J:J)),"Sqmt",IF(ISNUMBER(SEARCH("Acou",J:J)),"Sqmt",IF(ISNUMBER(SEARCH("ss",J:J)),"Kg's",IF(ISNUMBER(SEARCH("Alu",J:J)),"Kg's",IF(ISNUMBER(SEARCH("Gasket",J:J)),"Rmt",IF(ISNUMBER(SEARCH("Cleats",J:J)),"No's",IF(ISNUMBER(SEARCH("Tube",J:J)),"No's",IF(ISNUMBER(SEARCH("Bracket",J:J)),"No's",IF(ISNUMBER(SEARCH("Corner",J:J)),"No's",IF(ISNUMBER(SEARCH("MS",J:J)),"Kg's",IF(ISNUMBER(SEARCH("Bucket",J:J)),"Kg's",IF(ISNUMBER(SEARCH("stretch",J:J)),"Kg's",IF(ISNUMBER(SEARCH("Bubble",J:J)),"Roll",IF(ISNUMBER(SEARCH("JTR",J:J)),"Rmt",IF(ISNUMBER(SEARCH("Rod",J:J)),"Kg's",IF(ISNUMBER(SEARCH("Handle",J:J)),"No's",IF(ISNUMBER(SEARCH("Gear",J:J)),"No's",IF(ISNUMBER(SEARCH("Bush",J:J)),"No's","")))))))))))))))))))) -> Kg's | L11: =1848+5655.5 -> 7503.5 | T11: =IF(N11="","",SUM(N11,O11,P11,Q11,R11))
A12: =IF(C12="","",COUNT($C$3:C12)) -> 10 | B12: =IF(C12="","",TEXT(C12,"mmmm")) -> April | C12: 44652 | F12: Opening stock | G12: JSW | J12: 120gsm Slit 18G | K12: =IF(ISNUMBER(SEARCH("gsm",J:J)),"Kg's",IF(ISNUMBER(SEARCH("Tape",J:J)),"Roll",IF(ISNUMBER(SEARCH("Thermal",J:J)),"Sqmt",IF(ISNUMBER(SEARCH("Acou",J:J)),"Sqmt",IF(ISNUMBER(SEARCH("ss",J:J)),"Kg's",IF(ISNUMBER(SEARCH("Alu",J:J)),"Kg's",IF(ISNUMBER(SEARCH("Gasket",J:J)),"Rmt",IF(ISNUMBER(SEARCH("Cleats",J:J)),"No's",IF(ISNUMBER(SEARCH("Tube",J:J)),"No's",IF(ISNUMBER(SEARCH("Bracket",J:J)),"No's",IF(ISNUMBER(SEARCH("Corner",J:J)),"No's",IF(ISNUMBER(SEARCH("MS",J:J)),"Kg's",IF(ISNUMBER(SEARCH("Bucket",J:J)),"Kg's",IF(ISNUMBER(SEARCH("stretch",J:J)),"Kg's",IF(ISNUMBER(SEARCH("Bubble",J:J)),"Roll",IF(ISNUMBER(SEARCH("JTR",J:J)),"Rmt",IF(ISNUMBER(SEARCH("Rod",J:J)),"Kg's",IF(ISNUMBER(SEARCH("Handle",J:J)),"No's",IF(ISNUMBER(SEARCH("Gear",J:J)),"No's",IF(ISNUMBER(SEARCH("Bush",J:J)),"No's","")))))))))))))))))))) -> Kg's | L12: =872+775.6+302.2 -> 1949.8 | T12: =IF(N12="","",SUM(N12,O12,P12,Q12,R12))
A13: =IF(C13="","",COUNT($C$3:C13)) -> 11 | B13: =IF(C13="","",TEXT(C13,"mmmm")) -> April | C13: 44652 | F13: Opening stock | G13: JSW | J13: 275gsm 24G | K13: =IF(ISNUMBER(SEARCH("gsm",J:J)),"Kg's",IF(ISNUMBER(SEARCH("Tape",J:J)),"Roll",IF(ISNUMBER(SEARCH("Thermal",J:J)),"Sqmt",IF(ISNUMBER(SEARCH("Acou",J:J)),"Sqmt",IF(ISNUMBER(SEARCH("ss",J:J)),"Kg's",IF(ISNUMBER(SEARCH("Alu",J:J)),"Kg's",IF(ISNUMBER(SEARCH("Gasket",J:J)),"Rmt",IF(ISNUMBER(SEARCH("Cleats",J:J)),"No's",IF(ISNUMBER(SEARCH("Tube",J:J)),"No's",IF(ISNUMBER(SEARCH("Bracket",J:J)),"No's",IF(ISNUMBER(SEARCH("Corner",J:J)),"No's",IF(ISNUMBER(SEARCH("MS",J:J)),"Kg's",IF(ISNUMBER(SEARCH("Bucket",J:J)),"Kg's",IF(ISNUMBER(SEARCH("stretch",J:J)),"Kg's",IF(ISNUMBER(SEARCH("Bubble",J:J)),"Roll",IF(ISNUMBER(SEARCH("JTR",J:J)),"Rmt",IF(ISNUMBER(SEARCH("Rod",J:J)),"Kg's",IF(ISNUMBER(SEARCH("Handle",J:J)),"No's",IF(ISNUMBER(SEARCH("Gear",J:J)),"No's",IF(ISNUMBER(SEARCH("Bush",J:J)),"No's","")))))))))))))))))))) -> Kg's | L13: 4183
A14: =IF(C14="","",COUNT($C$3:C14)) -> 12 | B14: =IF(C14="","",TEXT(C14,"mmmm")) -> April | C14: 44652 | F14: Opening stock | G14: JSW | J14: 275gsm 22G | K14: =IF(ISNUMBER(SEARCH("gsm",J:J)),"Kg's",IF(ISNUMBER(SEARCH("Tape",J:J)),"Roll",IF(ISNUMBER(SEARCH("Thermal",J:J)),"Sqmt",IF(ISNUMBER(SEARCH("Acou",J:J)),"Sqmt",IF(ISNUMBER(SEARCH("ss",J:J)),"Kg's",IF(ISNUMBER(SEARCH("Alu",J:J)),"Kg's",IF(ISNUMBER(SEARCH("Gasket",J:J)),"Rmt",IF(ISNUMBER(SEARCH("Cleats",J:J)),"No's",IF(ISNUMBER(SEARCH("Tube",J:J)),"No's",IF(ISNUMBER(SEARCH("Bracket",J:J)),"No's",IF(ISNUMBER(SEARCH("Corner",J:J)),"No's",IF(ISNUMBER(SEARCH("MS",J:J)),"Kg's",IF(ISNUMBER(SEARCH("Bucket",J:J)),"Kg's",IF(ISNUMBER(SEARCH("stretch",J:J)),"Kg's",IF(ISNUMBER(SEARCH("Bubble",J:J)),"Roll",IF(ISNUMBER(SEARCH("JTR",J:J)),"Rmt",IF(ISNUMBER(SEARCH("Rod",J:J)),"Kg's",IF(ISNUMBER(SEARCH("Handle",J:J)),"No's",IF(ISNUMBER(SEARCH("Gear",J:J)),"No's",IF(ISNUMBER(SEARCH("Bush",J:J)),"No's","")))))))))))))))))))) -> Kg's | L14: =9225+1381.4 -> 10606.4 | T14: =IF(N14="","",SUM(N14,O14,P14,Q14,R14))
A15: =IF(C15="","",COUNT($C$3:C15)) -> 13 | B15: =IF(C15="","",TEXT(C15,"mmmm")) -> April | C15: 44652 | F15: Opening stock | G15: JSW | J15: 275gsm 20G | K15: =IF(ISNUMBER(SEARCH("gsm",J:J)),"Kg's",IF(ISNUMBER(SEARCH("Tape",J:J)),"Roll",IF(ISNUMBER(SEARCH("Thermal",J:J)),"Sqmt",IF(ISNUMBER(SEARCH("Acou",J:J)),"Sqmt",IF(ISNUMBER(SEARCH("ss",J:J)),"Kg's",IF(ISNUMBER(SEARCH("Alu",J:J)),"Kg's",IF(ISNUMBER(SEARCH("Gasket",J:J)),"Rmt",IF(ISNUMBER(SEARCH("Cleats",J:J)),"No's",IF(ISNUMBER(SEARCH("Tube",J:J)),"No's",IF(ISNUMBER(SEARCH("Bracket",J:J)),"No's",IF(ISNUMBER(SEARCH("Corner",J:J)),"No's",IF(ISNUMBER(SEARCH("MS",J:J)),"Kg's",IF(ISNUMBER(SEARCH("Bucket",J:J)),"Kg's",IF(ISNUMBER(SEARCH("stretch",J:J)),"Kg's",IF(ISNUMBER(SEARCH("Bubble",J:J)),"Roll",IF(ISNUMBER(SEARCH("JTR",J:J)),"Rmt",IF(ISNUMBER(SEARCH("Rod",J:J)),"Kg's",IF(ISNUMBER(SEARCH("Handle",J:J)),"No's",IF(ISNUMBER(SEARCH("Gear",J:J)),"No's",IF(ISNUMBER(SEARCH("Bush",J:J)),"No's","")))))))))))))))))))) -> Kg's | L15: 299 | T15: =IF(N15="","",SUM(N15,O15,P15,Q15,R15))
A16: =IF(C16="","",COUNT($C$3:C16)) -> 14 | B16: =IF(C16="","",TEXT(C16,"mmmm")) -> April | C16: 44652 | F16: Opening stock | G16: JSW | J16: 275gsm 18G | K16: =IF(ISNUMBER(SEARCH("gsm",J:J)),"Kg's",IF(ISNUMBER(SEARCH("Tape",J:J)),"Roll",IF(ISNUMBER(SEARCH("Thermal",J:J)),"Sqmt",IF(ISNUMBER(SEARCH("Acou",J:J)),"Sqmt",IF(ISNUMBER(SEARCH("ss",J:J)),"Kg's",IF(ISNUMBER(SEARCH("Alu",J:J)),"Kg's",IF(ISNUMBER(SEARCH("Gasket",J:J)),"Rmt",IF(ISNUMBER(SEARCH("Cleats",J:J)),"No's",IF(ISNUMBER(SEARCH("Tube",J:J)),"No's",IF(ISNUMBER(SEARCH("Bracket",J:J)),"No's",IF(ISNUMBER(SEARCH("Corner",J:J)),"No's",IF(ISNUMBER(SEARCH("MS",J:J)),"Kg's",IF(ISNUMBER(SEARCH("Bucket",J:J)),"Kg's",IF(ISNUMBER(SEARCH("stretch",J:J)),"Kg's",IF(ISNUMBER(SEARCH("Bubble",J:J)),"Roll",IF(ISNUMBER(SEARCH("JTR",J:J)),"Rmt",IF(ISNUMBER(SEARCH("Rod",J:J)),"Kg's",IF(ISNUMBER(SEARCH("Handle",J:J)),"No's",IF(ISNUMBER(SEARCH("Gear",J:J)),"No's",IF(ISNUMBER(SEARCH("Bush",J:J)),"No's","")))))))))))))))))))) -> Kg's | L16: 1251 | T16: =IF(N16="","",SUM(N16,O16,P16,Q16,R16))
A17: =IF(C17="","",COUNT($C$3:C17)) -> 15 | B17: =IF(C17="","",TEXT(C17,"mmmm")) -> April | C17: 44652 | F17: Opening stock | G17: JSW | J17: 275gsm 16G | K17: =IF(ISNUMBER(SEARCH("gsm",J:J)),"Kg's",IF(ISNUMBER(SEARCH("Tape",J:J)),"Roll",IF(ISNUMBER(SEARCH("Thermal",J:J)),"Sqmt",IF(ISNUMBER(SEARCH("Acou",J:J)),"Sqmt",IF(ISNUMBER(SEARCH("ss",J:J)),"Kg's",IF(ISNUMBER(SEARCH("Alu",J:J)),"Kg's",IF(ISNUMBER(SEARCH("Gasket",J:J)),"Rmt",IF(ISNUMBER(SEARCH("Cleats",J:J)),"No's",IF(ISNUMBER(SEARCH("Tube",J:J)),"No's",IF(ISNUMBER(SEARCH("Bracket",J:J)),"No's",IF(ISNUMBER(SEARCH("Corner",J:J)),"No's",IF(ISNUMBER(SEARCH("MS",J:J)),"Kg's",IF(ISNUMBER(SEARCH("Bucket",J:J)),"Kg's",IF(ISNUMBER(SEARCH("stretch",J:J)),"Kg's",IF(ISNUMBER(SEARCH("Bubble",J:J)),"Roll",IF(ISNUMBER(SEARCH("JTR",J:J)),"Rmt",IF(ISNUMBER(SEARCH("Rod",J:J)),"Kg's",IF(ISNUMBER(SEARCH("Handle",J:J)),"No's",IF(ISNUMBER(SEARCH("Gear",J:J)),"No's",IF(ISNUMBER(SEARCH("Bush",J:J)),"No's","")))))))))))))))))))) -> Kg's | L17: 5919 | T17: =IF(N17="","",SUM(N17,O17,P17,Q17,R17))
A18: =IF(C18="","",COUNT($C$3:C18)) -> 16 | B18: =IF(C18="","",TEXT(C18,"mmmm")) -> April | C18: 44652 | F18: Opening stock | G18: JSW | J18: Alu. 1mm | K18: =IF(ISNUMBER(SEARCH("gsm",J:J)),"Kg's",IF(ISNUMBER(SEARCH("Tape",J:J)),"Roll",IF(ISNUMBER(SEARCH("Thermal",J:J)),"Sqmt",IF(ISNUMBER(SEARCH("Acou",J:J)),"Sqmt",IF(ISNUMBER(SEARCH("ss",J:J)),"Kg's",IF(ISNUMBER(SEARCH("Alu",J:J)),"Kg's",IF(ISNUMBER(SEARCH("Gasket",J:J)),"Rmt",IF(ISNUMBER(SEARCH("Cleats",J:J)),"No's",IF(ISNUMBER(SEARCH("Tube",J:J)),"No's",IF(ISNUMBER(SEARCH("Bracket",J:J)),"No's",IF(ISNUMBER(SEARCH("Corner",J:J)),"No's",IF(ISNUMBER(SEARCH("MS",J:J)),"Kg's",IF(ISNUMBER(SEARCH("Bucket",J:J)),"Kg's",IF(ISNUMBER(SEARCH("stretch",J:J)),"Kg's",IF(ISNUMBER(SEARCH("Bubble",J:J)),"Roll",IF(ISNUMBER(SEARCH("JTR",J:J)),"Rmt",IF(ISNUMBER(SEARCH("Rod",J:J)),"Kg's",IF(ISNUMBER(SEARCH("Handle",J:J)),"No's",IF(ISNUMBER(SEARCH("Gear",J:J)),"No's",IF(ISNUMBER(SEARCH("Bush",J:J)),"No's","")))))))))))))))))))) -> Kg's | L18: 170 | T18: =IF(N18="","",SUM(N18,O18,P18,Q18,R18))
A19: =IF(C19="","",COUNT($C$3:C19)) -> 17 | B19: =IF(C19="","",TEXT(C19,"mmmm")) -> April | C19: 44652 | F19: Opening stock | G19: JSW | J19: Alu. 0.8mm | K19: =IF(ISNUMBER(SEARCH("gsm",J:J)),"Kg's",IF(ISNUMBER(SEARCH("Tape",J:J)),"Roll",IF(ISNUMBER(SEARCH("Thermal",J:J)),"Sqmt",IF(ISNUMBER(SEARCH("Acou",J:J)),"Sqmt",IF(ISNUMBER(SEARCH("ss",J:J)),"Kg's",IF(ISNUMBER(SEARCH("Alu",J:J)),"Kg's",IF(ISNUMBER(SEARCH("Gasket",J:J)),"Rmt",IF(ISNUMBER(SEARCH("Cleats",J:J)),"No's",IF(ISNUMBER(SEARCH("Tube",J:J)),"No's",IF(ISNUMBER(SEARCH("Bracket",J:J)),"No's",IF(ISNUMBER(SEARCH("Corner",J:J)),"No's",IF(ISNUMBER(SEARCH("MS",J:J)),"Kg's",IF(ISNUMBER(SEARCH("Bucket",J:J)),"Kg's",IF(ISNUMBER(SEARCH("stretch",J:J)),"Kg's",IF(ISNUMBER(SEARCH("Bubble",J:J)),"Roll",IF(ISNUMBER(SEARCH("JTR",J:J)),"Rmt",IF(ISNUMBER(SEARCH("Rod",J:J)),"Kg's",IF(ISNUMBER(SEARCH("Handle",J:J)),"No's",IF(ISNUMBER(SEARCH("Gear",J:J)),"No's",IF(ISNUMBER(SEARCH("Bush",J:J)),"No's","")))))))))))))))))))) -> Kg's | L19: 33 | T19: =IF(N19="","",SUM(N19,O19,P19,Q19,R19))
A20: =IF(C20="","",COUNT($C$3:C20)) -> 18 | B20: =IF(C20="","",TEXT(C20,"mmmm")) -> April | C20: 44652 | F20: Opening stock | J20: Corner 32mm | K20: =IF(ISNUMBER(SEARCH("gsm",J:J)),"Kg's",IF(ISNUMBER(SEARCH("Tape",J:J)),"Roll",IF(ISNUMBER(SEARCH("Thermal",J:J)),"Sqmt",IF(ISNUMBER(SEARCH("Acou",J:J)),"Sqmt",IF(ISNUMBER(SEARCH("ss",J:J)),"Kg's",IF(ISNUMBER(SEARCH("Alu",J:J)),"Kg's",IF(ISNUMBER(SEARCH("Gasket",J:J)),"Rmt",IF(ISNUMBER(SEARCH("Cleats",J:J)),"No's",IF(ISNUMBER(SEARCH("Tube",J:J)),"No's",IF(ISNUMBER(SEARCH("Bracket",J:J)),"No's",IF(ISNUMBER(SEARCH("Corner",J:J)),"No's",IF(ISNUMBER(SEARCH("MS",J:J)),"Kg's",IF(ISNUMBER(SEARCH("Bucket",J:J)),"Kg's",IF(ISNUMBER(SEARCH("stretch",J:J)),"Kg's",IF(ISNUMBER(SEARCH("Bubble",J:J)),"Roll",IF(ISNUMBER(SEARCH("JTR",J:J)),"Rmt",IF(ISNUMBER(SEARCH("Rod",J:J)),"Kg's",IF(ISNUMBER(SEARCH("Handle",J:J)),"No's",IF(ISNUMBER(SEARCH("Gear",J:J)),"No's",IF(ISNUMBER(SEARCH("Bush",J:J)),"No's","")))))))))))))))))))) -> No's | L20: 59500 | T20: =IF(N20="","",SUM(N20,O20,P20,Q20,R20))
A21: =IF(C21="","",COUNT($C$3:C21)) -> 19 | B21: =IF(C21="","",TEXT(C21,"mmmm")) -> April | C21: 44652 | F21: Opening stock | J21: Corner 25mm | K21: =IF(ISNUMBER(SEARCH("gsm",J:J)),"Kg's",IF(ISNUMBER(SEARCH("Tape",J:J)),"Roll",IF(ISNUMBER(SEARCH("Thermal",J:J)),"Sqmt",IF(ISNUMBER(SEARCH("Acou",J:J)),"Sqmt",IF(ISNUMBER(SEARCH("ss",J:J)),"Kg's",IF(ISNUMBER(SEARCH("Alu",J:J)),"Kg's",IF(ISNUMBER(SEARCH("Gasket",J:J)),"Rmt",IF(ISNUMBER(SEARCH("Cleats",J:J)),"No's",IF(ISNUMBER(SEARCH("Tube",J:J)),"No's",IF(ISNUMBER(SEARCH("Bracket",J:J)),"No's",IF(ISNUMBER(SEARCH("Corner",J:J)),"No's",IF(ISNUMBER(SEARCH("MS",J:J)),"Kg's",IF(ISNUMBER(SEARCH("Bucket",J:J)),"Kg's",IF(ISNUMBER(SEARCH("stretch",J:J)),"Kg's",IF(ISNUMBER(SEARCH("Bubble",J:J)),"Roll",IF(ISNUMBER(SEARCH("JTR",J:J)),"Rmt",IF(ISNUMBER(SEARCH("Rod",J:J)),"Kg's",IF(ISNUMBER(SEARCH("Handle",J:J)),"No's",IF(ISNUMBER(SEARCH("Gear",J:J)),"No's",IF(ISNUMBER(SEARCH("Bush",J:J)),"No's","")))))))))))))))))))) -> No's | L21: 10000 | T21: =IF(N21="","",SUM(N21,O21,P21,Q21,R21))
A22: =IF(C22="","",COUNT($C$3:C22)) -> 20 | B22: =IF(C22="","",TEXT(C22,"mmmm")) -> April | C22: 44652 | F22: Opening stock | J22: XLPE Gasket | K22: =IF(ISNUMBER(SEARCH("gsm",J:J)),"Kg's",IF(ISNUMBER(SEARCH("Tape",J:J)),"Roll",IF(ISNUMBER(SEARCH("Thermal",J:J)),"Sqmt",IF(ISNUMBER(SEARCH("Acou",J:J)),"Sqmt",IF(ISNUMBER(SEARCH("ss",J:J)),"Kg's",IF(ISNUMBER(SEARCH("Alu",J:J)),"Kg's",IF(ISNUMBER(SEARCH("Gasket",J:J)),"Rmt",IF(ISNUMBER(SEARCH("Cleats",J:J)),"No's",IF(ISNUMBER(SEARCH("Tube",J:J)),"No's",IF(ISNUMBER(SEARCH("Bracket",J:J)),"No's",IF(ISNUMBER(SEARCH("Corner",J:J)),"No's",IF(ISNUMBER(SEARCH("MS",J:J)),"Kg's",IF(ISNUMBER(SEARCH("Bucket",J:J)),"Kg's",IF(ISNUMBER(SEARCH("stretch",J:J)),"Kg's",IF(ISNUMBER(SEARCH("Bubble",J:J)),"Roll",IF(ISNUMBER(SEARCH("JTR",J:J)),"Rmt",IF(ISNUMBER(SEARCH("Rod",J:J)),"Kg's",IF(ISNUMBER(SEARCH("Handle",J:J)),"No's",IF(ISNUMBER(SEARCH("Gear",J:J)),"No's",IF(ISNUMBER(SEARCH("Bush",J:J)),"No's","")))))))))))))))))))) -> Rmt | L22: 30210 | T22: =IF(N22="","",SUM(N22,O22,P22,Q22,R22))
A23: =IF(C23="","",COUNT($C$3:C23)) -> 21 | B23: =IF(C23="","",TEXT(C23,"mmmm")) -> April | C23: 44652 | F23: Opening stock | G23: Urja | J23: Sealant Tube | K23: =IF(ISNUMBER(SEARCH("gsm",J:J)),"Kg's",IF(ISNUMBER(SEARCH("Tape",J:J)),"Roll",IF(ISNUMBER(SEARCH("Thermal",J:J)),"Sqmt",IF(ISNUMBER(SEARCH("Acou",J:J)),"Sqmt",IF(ISNUMBER(SEARCH("ss",J:J)),"Kg's",IF(ISNUMBER(SEARCH("Alu",J:J)),"Kg's",IF(ISNUMBER(SEARCH("Gasket",J:J)),"Rmt",IF(ISNUMBER(SEARCH("Cleats",J:J)),"No's",IF(ISNUMBER(SEARCH("Tube",J:J)),"No's",IF(ISNUMBER(SEARCH("Bracket",J:J)),"No's",IF(ISNUMBER(SEARCH("Corner",J:J)),"No's",IF(ISNUMBER(SEARCH("MS",J:J)),"Kg's",IF(ISNUMBER(SEARCH("Bucket",J:J)),"Kg's",IF(ISNUMBER(SEARCH("stretch",J:J)),"Kg's",IF(ISNUMBER(SEARCH("Bubble",J:J)),"Roll",IF(ISNUMBER(SEARCH("JTR",J:J)),"Rmt",IF(ISNUMBER(SEARCH("Rod",J:J)),"Kg's",IF(ISNUMBER(SEARCH("Handle",J:J)),"No's",IF(ISNUMBER(SEARCH("Gear",J:J)),"No's",IF(ISNUMBER(SEARCH("Bush",J:J)),"No's","")))))))))))))))))))) -> No's | L23: 357 | T23: =IF(N23="","",SUM(N23,O23,P23,Q23,R23))
A24: =IF(C24="","",COUNT($C$3:C24)) -> 22 | B24: =IF(C24="","",TEXT(C24,"mmmm")) -> April | C24: 44652 | F24: Opening stock | G24: Urja | J24: Sealant Bucket | K24: =IF(ISNUMBER(SEARCH("gsm",J:J)),"Kg's",IF(ISNUMBER(SEARCH("Tape",J:J)),"Roll",IF(ISNUMBER(SEARCH("Thermal",J:J)),"Sqmt",IF(ISNUMBER(SEARCH("Acou",J:J)),"Sqmt",IF(ISNUMBER(SEARCH("ss",J:J)),"Kg's",IF(ISNUMBER(SEARCH("Alu",J:J)),"Kg's",IF(ISNUMBER(SEARCH("Gasket",J:J)),"Rmt",IF(ISNUMBER(SEARCH("Cleats",J:J)),"No's",IF(ISNUMBER(SEARCH("Tube",J:J)),"No's",IF(ISNUMBER(SEARCH("Bracket",J:J)),"No's",IF(ISNUMBER(SEARCH("Corner",J:J)),"No's",IF(ISNUMBER(SEARCH("MS",J:J)),"Kg's",IF(ISNUMBER(SEARCH("Bucket",J:J)),"Kg's",IF(ISNUMBER(SEARCH("stretch",J:J)),"Kg's",IF(ISNUMBER(SEARCH("Bubble",J:J)),"Roll",IF(ISNUMBER(SEARCH("JTR",J:J)),"Rmt",IF(ISNUMBER(SEARCH("Rod",J:J)),"Kg's",IF(ISNUMBER(SEARCH("Handle",J:J)),"No's",IF(ISNUMBER(SEARCH("Gear",J:J)),"No's",IF(ISNUMBER(SEARCH("Bush",J:J)),"No's","")))))))))))))))))))) -> Kg's | L24: 100 | T24: =IF(N24="","",SUM(N24,O24,P24,Q24,R24))
A25: =IF(C25="","",COUNT($C$3:C25)) -> 23 | B25: =IF(C25="","",TEXT(C25,"mmmm")) -> December | C25: 44926 | F25: Opening stock | G25: K Flex | J25: Insu Kflex Thermal 6mm | K25: =IF(ISNUMBER(SEARCH("gsm",J:J)),"Kg's",IF(ISNUMBER(SEARCH("Tape",J:J)),"Roll",IF(ISNUMBER(SEARCH("Thermal",J:J)),"Sqmt",IF(ISNUMBER(SEARCH("Acou",J:J)),"Sqmt",IF(ISNUMBER(SEARCH("ss",J:J)),"Kg's",IF(ISNUMBER(SEARCH("Alu",J:J)),"Kg's",IF(ISNUMBER(SEARCH("Gasket",J:J)),"Rmt",IF(ISNUMBER(SEARCH("Cleats",J:J)),"No's",IF(ISNUMBER(SEARCH("Tube",J:J)),"No's",IF(ISNUMBER(SEARCH("Bracket",J:J)),"No's",IF(ISNUMBER(SEARCH("Corner",J:J)),"No's",IF(ISNUMBER(SEARCH("MS",J:J)),"Kg's",IF(ISNUMBER(SEARCH("Bucket",J:J)),"Kg's",IF(ISNUMBER(SEARCH("stretch",J:J)),"Kg's",IF(ISNUMBER(SEARCH("Bubble",J:J)),"Roll",IF(ISNUMBER(SEARCH("JTR",J:J)),"Rmt",IF(ISNUMBER(SEARCH("Rod",J:J)),"Kg's",IF(ISNUMBER(SEARCH("Handle",J:J)),"No's",IF(ISNUMBER(SEARCH("Gear",J:J)),"No's",IF(ISNUMBER(SEARCH("Bush",J:J)),"No's","")))))))))))))))))))) -> Sqmt | L25: 396
A26: =IF(C26="","",COUNT($C$3:C26)) -> 24 | B26: =IF(C26="","",TEXT(C26,"mmmm")) -> December | C26: 44926 | F26: Opening stock | G26: K Flex | J26: Insu Kflex Thermal 9mm | K26: =IF(ISNUMBER(SEARCH("gsm",J:J)),"Kg's",IF(ISNUMBER(SEARCH("Tape",J:J)),"Roll",IF(ISNUMBER(SEARCH("Thermal",J:J)),"Sqmt",IF(ISNUMBER(SEARCH("Acou",J:J)),"Sqmt",IF(ISNUMBER(SEARCH("ss",J:J)),"Kg's",IF(ISNUMBER(SEARCH("Alu",J:J)),"Kg's",IF(ISNUMBER(SEARCH("Gasket",J:J)),"Rmt",IF(ISNUMBER(SEARCH("Cleats",J:J)),"No's",IF(ISNUMBER(SEARCH("Tube",J:J)),"No's",IF(ISNUMBER(SEARCH("Bracket",J:J)),"No's",IF(ISNUMBER(SEARCH("Corner",J:J)),"No's",IF(ISNUMBER(SEARCH("MS",J:J)),"Kg's",IF(ISNUMBER(SEARCH("Bucket",J:J)),"Kg's",IF(ISNUMBER(SEARCH("stretch",J:J)),"Kg's",IF(ISNUMBER(SEARCH("Bubble",J:J)),"Roll",IF(ISNUMBER(SEARCH("JTR",J:J)),"Rmt",IF(ISNUMBER(SEARCH("Rod",J:J)),"Kg's",IF(ISNUMBER(SEARCH("Handle",J:J)),"No's",IF(ISNUMBER(SEARCH("Gear",J:J)),"No's",IF(ISNUMBER(SEARCH("Bush",J:J)),"No's","")))))))))))))))))))) -> Sqmt | L26: 144 | T26: =IF(N26="","",SUM(N26,O26,P26,Q26,R26))
A27: =IF(C27="","",COUNT($C$3:C27)) -> 25 | B27: =IF(C27="","",TEXT(C27,"mmmm")) -> December | C27: 44926 | F27: Opening stock | G27: K Flex | J27: Insu Kflex Thermal 13mm | K27: =IF(ISNUMBER(SEARCH("gsm",J:J)),"Kg's",IF(ISNUMBER(SEARCH("Tape",J:J)),"Roll",IF(ISNUMBER(SEARCH("Thermal",J:J)),"Sqmt",IF(ISNUMBER(SEARCH("Acou",J:J)),"Sqmt",IF(ISNUMBER(SEARCH("ss",J:J)),"Kg's",IF(ISNUMBER(SEARCH("Alu",J:J)),"Kg's",IF(ISNUMBER(SEARCH("Gasket",J:J)),"Rmt",IF(ISNUMBER(SEARCH("Cleats",J:J)),"No's",IF(ISNUMBER(SEARCH("Tube",J:J)),"No's",IF(ISNUMBER(SEARCH("Bracket",J:J)),"No's",IF(ISNUMBER(SEARCH("Corner",J:J)),"No's",IF(ISNUMBER(SEARCH("MS",J:J)),"Kg's",IF(ISNUMBER(SEARCH("Bucket",J:J)),"Kg's",IF(ISNUMBER(SEARCH("stretch",J:J)),"Kg's",IF(ISNUMBER(SEARCH("Bubble",J:J)),"Roll",IF(ISNUMBER(SEARCH("JTR",J:J)),"Rmt",IF(ISNUMBER(SEARCH("Rod",J:J)),"Kg's",IF(ISNUMBER(SEARCH("Handle",J:J)),"No's",IF(ISNUMBER(SEARCH("Gear",J:J)),"No's",IF(ISNUMBER(SEARCH("Bush",J:J)),"No's","")))))))))))))))))))) -> Sqmt | L27: 33.6 | T27: =IF(N27="","",SUM(N27,O27,P27,Q27,R27))
A28: =IF(C28="","",COUNT($C$3:C28)) -> 26 | B28: =IF(C28="","",TEXT(C28,"mmmm")) -> December | C28: 44926 | F28: Opening stock | G28: K Flex | J28: Insu Kflex Thermal 25mm | K28: =IF(ISNUMBER(SEARCH("gsm",J:J)),"Kg's",IF(ISNUMBER(SEARCH("Tape",J:J)),"Roll",IF(ISNUMBER(SEARCH("Thermal",J:J)),"Sqmt",IF(ISNUMBER(SEARCH("Acou",J:J)),"Sqmt",IF(ISNUMBER(SEARCH("ss",J:J)),"Kg's",IF(ISNUMBER(SEARCH("Alu",J:J)),"Kg's",IF(ISNUMBER(SEARCH("Gasket",J:J)),"Rmt",IF(ISNUMBER(SEARCH("Cleats",J:J)),"No's",IF(ISNUMBER(SEARCH("Tube",J:J)),"No's",IF(ISNUMBER(SEARCH("Bracket",J:J)),"No's",IF(ISNUMBER(SEARCH("Corner",J:J)),"No's",IF(ISNUMBER(SEARCH("MS",J:J)),"Kg's",IF(ISNUMBER(SEARCH("Bucket",J:J)),"Kg's",IF(ISNUMBER(SEARCH("stretch",J:J)),"Kg's",IF(ISNUMBER(SEARCH("Bubble",J:J)),"Roll",IF(ISNUMBER(SEARCH("JTR",J:J)),"Rmt",IF(ISNUMBER(SEARCH("Rod",J:J)),"Kg's",IF(ISNUMBER(SEARCH("Handle",J:J)),"No's",IF(ISNUMBER(SEARCH("Gear",J:J)),"No's",IF(ISNUMBER(SEARCH("Bush",J:J)),"No's","")))))))))))))))))))) -> Sqmt | L28: 38.4
A29: =IF(C29="","",COUNT($C$3:C29)) -> 27 | B29: =IF(C29="","",TEXT(C29,"mmmm")) -> December | C29: 44926 | F29: Opening stock | G29: K Flex | J29: Insu Kflex Thermal 32mm | K29: =IF(ISNUMBER(SEARCH("gsm",J:J)),"Kg's",IF(ISNUMBER(SEARCH("Tape",J:J)),"Roll",IF(ISNUMBER(SEARCH("Thermal",J:J)),"Sqmt",IF(ISNUMBER(SEARCH("Acou",J:J)),"Sqmt",IF(ISNUMBER(SEARCH("ss",J:J)),"Kg's",IF(ISNUMBER(SEARCH("Alu",J:J)),"Kg's",IF(ISNUMBER(SEARCH("Gasket",J:J)),"Rmt",IF(ISNUMBER(SEARCH("Cleats",J:J)),"No's",IF(ISNUMBER(SEARCH("Tube",J:J)),"No's",IF(ISNUMBER(SEARCH("Bracket",J:J)),"No's",IF(ISNUMBER(SEARCH("Corner",J:J)),"No's",IF(ISNUMBER(SEARCH("MS",J:J)),"Kg's",IF(ISNUMBER(SEARCH("Bucket",J:J)),"Kg's",IF(ISNUMBER(SEARCH("stretch",J:J)),"Kg's",IF(ISNUMBER(SEARCH("Bubble",J:J)),"Roll",IF(ISNUMBER(SEARCH("JTR",J:J)),"Rmt",IF(ISNUMBER(SEARCH("Rod",J:J)),"Kg's",IF(ISNUMBER(SEARCH("Handle",J:J)),"No's",IF(ISNUMBER(SEARCH("Gear",J:J)),"No's",IF(ISNUMBER(SEARCH("Bush",J:J)),"No's","")))))))))))))))))))) -> Sqmt | L29: 93.6 | T29: =IF(N29="","",SUM(N29,O29,P29,Q29,R29))
A30: =IF(C30="","",COUNT($C$3:C30)) -> 28 | B30: =IF(C30="","",TEXT(C30,"mmmm")) -> December | C30: 44926 | F30: Opening stock | G30: K Flex | J30: Insu Kflex Thermal 9mm Al. Foil | K30: =IF(ISNUMBER(SEARCH("gsm",J:J)),"Kg's",IF(ISNUMBER(SEARCH("Tape",J:J)),"Roll",IF(ISNUMBER(SEARCH("Thermal",J:J)),"Sqmt",IF(ISNUMBER(SEARCH("Acou",J:J)),"Sqmt",IF(ISNUMBER(SEARCH("ss",J:J)),"Kg's",IF(ISNUMBER(SEARCH("Alu",J:J)),"Kg's",IF(ISNUMBER(SEARCH("Gasket",J:J)),"Rmt",IF(ISNUMBER(SEARCH("Cleats",J:J)),"No's",IF(ISNUMBER(SEARCH("Tube",J:J)),"No's",IF(ISNUMBER(SEARCH("Bracket",J:J)),"No's",IF(ISNUMBER(SEARCH("Corner",J:J)),"No's",IF(ISNUMBER(SEARCH("MS",J:J)),"Kg's",IF(ISNUMBER(SEARCH("Bucket",J:J)),"Kg's",IF(ISNUMBER(SEARCH("stretch",J:J)),"Kg's",IF(ISNUMBER(SEARCH("Bubble",J:J)),"Roll",IF(ISNUMBER(SEARCH("JTR",J:J)),"Rmt",IF(ISNUMBER(SEARCH("Rod",J:J)),"Kg's",IF(ISNUMBER(SEARCH("Handle",J:J)),"No's",IF(ISNUMBER(SEARCH("Gear",J:J)),"No's",IF(ISNUMBER(SEARCH("Bush",J:J)),"No's","")))))))))))))))))))) -> Sqmt | L30: 24
A31: =IF(C31="","",COUNT($C$3:C31)) -> 29 | B31: =IF(C31="","",TEXT(C31,"mmmm")) -> December | C31: 44926 | F31: Opening stock | G31: K Flex | J31: Insu Kflex Thermal 13mm Al. Foil | K31: =IF(ISNUMBER(SEARCH("gsm",J:J)),"Kg's",IF(ISNUMBER(SEARCH("Tape",J:J)),"Roll",IF(ISNUMBER(SEARCH("Thermal",J:J)),"Sqmt",IF(ISNUMBER(SEARCH("Acou",J:J)),"Sqmt",IF(ISNUMBER(SEARCH("ss",J:J)),"Kg's",IF(ISNUMBER(SEARCH("Alu",J:J)),"Kg's",IF(ISNUMBER(SEARCH("Gasket",J:J)),"Rmt",IF(ISNUMBER(SEARCH("Cleats",J:J)),"No's",IF(ISNUMBER(SEARCH("Tube",J:J)),"No's",IF(ISNUMBER(SEARCH("Bracket",J:J)),"No's",IF(ISNUMBER(SEARCH("Corner",J:J)),"No's",IF(ISNUMBER(SEARCH("MS",J:J)),"Kg's",IF(ISNUMBER(SEARCH("Bucket",J:J)),"Kg's",IF(ISNUMBER(SEARCH("stretch",J:J)),"Kg's",IF(ISNUMBER(SEARCH("Bubble",J:J)),"Roll",IF(ISNUMBER(SEARCH("JTR",J:J)),"Rmt",IF(ISNUMBER(SEARCH("Rod",J:J)),"Kg's",IF(ISNUMBER(SEARCH("Handle",J:J)),"No's",IF(ISNUMBER(SEARCH("Gear",J:J)),"No's",IF(ISNUMBER(SEARCH("Bush",J:J)),"No's","")))))))))))))))))))) -> Sqmt | L31: 67.2 | T31: =IF(N31="","",SUM(N31,O31,P31,Q31,R31))
A32: =IF(C32="","",COUNT($C$3:C32)) -> 30 | B32: =IF(C32="","",TEXT(C32,"mmmm")) -> December | C32: 44926 | F32: Opening stock | G32: K Flex | J32: Insu Kflex Thermal 19mm Al. Foil | K32: =IF(ISNUMBER(SEARCH("gsm",J:J)),"Kg's",IF(ISNUMBER(SEARCH("Tape",J:J)),"Roll",IF(ISNUMBER(SEARCH("Thermal",J:J)),"Sqmt",IF(ISNUMBER(SEARCH("Acou",J:J)),"Sqmt",IF(ISNUMBER(SEARCH("ss",J:J)),"Kg's",IF(ISNUMBER(SEARCH("Alu",J:J)),"Kg's",IF(ISNUMBER(SEARCH("Gasket",J:J)),"Rmt",IF(ISNUMBER(SEARCH("Cleats",J:J)),"No's",IF(ISNUMBER(SEARCH("Tube",J:J)),"No's",IF(ISNUMBER(SEARCH("Bracket",J:J)),"No's",IF(ISNUMBER(SEARCH("Corner",J:J)),"No's",IF(ISNUMBER(SEARCH("MS",J:J)),"Kg's",IF(ISNUMBER(SEARCH("Bucket",J:J)),"Kg's",IF(ISNUMBER(SEARCH("stretch",J:J)),"Kg's",IF(ISNUMBER(SEARCH("Bubble",J:J)),"Roll",IF(ISNUMBER(SEARCH("JTR",J:J)),"Rmt",IF(ISNUMBER(SEARCH("Rod",J:J)),"Kg's",IF(ISNUMBER(SEARCH("Handle",J:J)),"No's",IF(ISNUMBER(SEARCH("Gear",J:J)),"No's",IF(ISNUMBER(SEARCH("Bush",J:J)),"No's","")))))))))))))))))))) -> Sqmt | L32: 24
A33: =IF(C33="","",COUNT($C$3:C33)) -> 31 | B33: =IF(C33="","",TEXT(C33,"mmmm")) -> December | C33: 44926 | F33: Opening stock | G33: K Flex | J33: Insu Kflex Thermal 9mm (IC-Clad Black) | K33: =IF(ISNUMBER(SEARCH("gsm",J:J)),"Kg's",IF(ISNUMBER(SEARCH("Tape",J:J)),"Roll",IF(ISNUMBER(SEARCH("Thermal",J:J)),"Sqmt",IF(ISNUMBER(SEARCH("Acou",J:J)),"Sqmt",IF(ISNUMBER(SEARCH("ss",J:J)),"Kg's",IF(ISNUMBER(SEARCH("Alu",J:J)),"Kg's",IF(ISNUMBER(SEARCH("Gasket",J:J)),"Rmt",IF(ISNUMBER(SEARCH("Cleats",J:J)),"No's",IF(ISNUMBER(SEARCH("Tube",J:J)),"No's",IF(ISNUMBER(SEARCH("Bracket",J:J)),"No's",IF(ISNUMBER(SEARCH("Corner",J:J)),"No's",IF(ISNUMBER(SEARCH("MS",J:J)),"Kg's",IF(ISNUMBER(SEARCH("Bucket",J:J)),"Kg's",IF(ISNUMBER(SEARCH("stretch",J:J)),"Kg's",IF(ISNUMBER(SEARCH("Bubble",J:J)),"Roll",IF(ISNUMBER(SEARCH("JTR",J:J)),"Rmt",IF(ISNUMBER(SEARCH("Rod",J:J)),"Kg's",IF(ISNUMBER(SEARCH("Handle",J:J)),"No's",IF(ISNUMBER(SEARCH("Gear",J:J)),"No's",IF(ISNUMBER(SEARCH("Bush",J:J)),"No's","")))))))))))))))))))) -> Sqmt | L33: 120 | T33: =IF(N33="","",SUM(N33,O33,P33,Q33,R33))
A34: =IF(C34="","",COUNT($C$3:C34)) -> 32 | B34: =IF(C34="","",TEXT(C34,"mmmm")) -> December | C34: 44926 | F34: Opening stock | G34: K Flex | J34: Insu Kflex Thermal 13mm (IC-Clad Black) | K34: =IF(ISNUMBER(SEARCH("gsm",J:J)),"Kg's",IF(ISNUMBER(SEARCH("Tape",J:J)),"Roll",IF(ISNUMBER(SEARCH("Thermal",J:J)),"Sqmt",IF(ISNUMBER(SEARCH("Acou",J:J)),"Sqmt",IF(ISNUMBER(SEARCH("ss",J:J)),"Kg's",IF(ISNUMBER(SEARCH("Alu",J:J)),"Kg's",IF(ISNUMBER(SEARCH("Gasket",J:J)),"Rmt",IF(ISNUMBER(SEARCH("Cleats",J:J)),"No's",IF(ISNUMBER(SEARCH("Tube",J:J)),"No's",IF(ISNUMBER(SEARCH("Bracket",J:J)),"No's",IF(ISNUMBER(SEARCH("Corner",J:J)),"No's",IF(ISNUMBER(SEARCH("MS",J:J)),"Kg's",IF(ISNUMBER(SEARCH("Bucket",J:J)),"Kg's",IF(ISNUMBER(SEARCH("stretch",J:J)),"Kg's",IF(ISNUMBER(SEARCH("Bubble",J:J)),"Roll",IF(ISNUMBER(SEARCH("JTR",J:J)),"Rmt",IF(ISNUMBER(SEARCH("Rod",J:J)),"Kg's",IF(ISNUMBER(SEARCH("Handle",J:J)),"No's",IF(ISNUMBER(SEARCH("Gear",J:J)),"No's",IF(ISNUMBER(SEARCH("Bush",J:J)),"No's","")))))))))))))))))))) -> Sqmt | L34: 16.8
A35: =IF(C35="","",COUNT($C$3:C35)) -> 33 | B35: =IF(C35="","",TEXT(C35,"mmmm")) -> December | C35: 44926 | F35: Opening stock | G35: K Flex | J35: Insu Kflex Thermal 9mm (Clad Grey) | K35: =IF(ISNUMBER(SEARCH("gsm",J:J)),"Kg's",IF(ISNUMBER(SEARCH("Tape",J:J)),"Roll",IF(ISNUMBER(SEARCH("Thermal",J:J)),"Sqmt",IF(ISNUMBER(SEARCH("Acou",J:J)),"Sqmt",IF(ISNUMBER(SEARCH("ss",J:J)),"Kg's",IF(ISNUMBER(SEARCH("Alu",J:J)),"Kg's",IF(ISNUMBER(SEARCH("Gasket",J:J)),"Rmt",IF(ISNUMBER(SEARCH("Cleats",J:J)),"No's",IF(ISNUMBER(SEARCH("Tube",J:J)),"No's",IF(ISNUMBER(SEARCH("Bracket",J:J)),"No's",IF(ISNUMBER(SEARCH("Corner",J:J)),"No's",IF(ISNUMBER(SEARCH("MS",J:J)),"Kg's",IF(ISNUMBER(SEARCH("Bucket",J:J)),"Kg's",IF(ISNUMBER(SEARCH("stretch",J:J)),"Kg's",IF(ISNUMBER(SEARCH("Bubble",J:J)),"Roll",IF(ISNUMBER(SEARCH("JTR",J:J)),"Rmt",IF(ISNUMBER(SEARCH("Rod",J:J)),"Kg's",IF(ISNUMBER(SEARCH("Handle",J:J)),"No's",IF(ISNUMBER(SEARCH("Gear",J:J)),"No's",IF(ISNUMBER(SEARCH("Bush",J:J)),"No's","")))))))))))))))))))) -> Sqmt | L35: 24 | T35: =IF(N35="","",SUM(N35,O35,P35,Q35,R35))
A36: =IF(C36="","",COUNT($C$3:C36)) -> 34 | B36: =IF(C36="","",TEXT(C36,"mmmm")) -> December | C36: 44926 | F36: Opening stock | G36: K Flex | J36: Insu Kflex 10mm Acou. | K36: =IF(ISNUMBER(SEARCH("gsm",J:J)),"Kg's",IF(ISNUMBER(SEARCH("Tape",J:J)),"Roll",IF(ISNUMBER(SEARCH("Thermal",J:J)),"Sqmt",IF(ISNUMBER(SEARCH("Acou",J:J)),"Sqmt",IF(ISNUMBER(SEARCH("ss",J:J)),"Kg's",IF(ISNUMBER(SEARCH("Alu",J:J)),"Kg's",IF(ISNUMBER(SEARCH("Gasket",J:J)),"Rmt",IF(ISNUMBER(SEARCH("Cleats",J:J)),"No's",IF(ISNUMBER(SEARCH("Tube",J:J)),"No's",IF(ISNUMBER(SEARCH("Bracket",J:J)),"No's",IF(ISNUMBER(SEARCH("Corner",J:J)),"No's",IF(ISNUMBER(SEARCH("MS",J:J)),"Kg's",IF(ISNUMBER(SEARCH("Bucket",J:J)),"Kg's",IF(ISNUMBER(SEARCH("stretch",J:J)),"Kg's",IF(ISNUMBER(SEARCH("Bubble",J:J)),"Roll",IF(ISNUMBER(SEARCH("JTR",J:J)),"Rmt",IF(ISNUMBER(SEARCH("Rod",J:J)),"Kg's",IF(ISNUMBER(SEARCH("Handle",J:J)),"No's",IF(ISNUMBER(SEARCH("Gear",J:J)),"No's",IF(ISNUMBER(SEARCH("Bush",J:J)),"No's","")))))))))))))))))))) -> Sqmt | L36: 160 | T36: =IF(N36="","",SUM(N36,O36,P36,Q36,R36))
A37: =IF(C37="","",COUNT($C$3:C37)) -> 35 | B37: =IF(C37="","",TEXT(C37,"mmmm")) -> December | C37: 44926 | F37: Opening stock | G37: K Flex | J37: Insu Kflex 15mm Acou. | K37: =IF(ISNUMBER(SEARCH("gsm",J:J)),"Kg's",IF(ISNUMBER(SEARCH("Tape",J:J)),"Roll",IF(ISNUMBER(SEARCH("Thermal",J:J)),"Sqmt",IF(ISNUMBER(SEARCH("Acou",J:J)),"Sqmt",IF(ISNUMBER(SEARCH("ss",J:J)),"Kg's",IF(ISNUMBER(SEARCH("Alu",J:J)),"Kg's",IF(ISNUMBER(SEARCH("Gasket",J:J)),"Rmt",IF(ISNUMBER(SEARCH("Cleats",J:J)),"No's",IF(ISNUMBER(SEARCH("Tube",J:J)),"No's",IF(ISNUMBER(SEARCH("Bracket",J:J)),"No's",IF(ISNUMBER(SEARCH("Corner",J:J)),"No's",IF(ISNUMBER(SEARCH("MS",J:J)),"Kg's",IF(ISNUMBER(SEARCH("Bucket",J:J)),"Kg's",IF(ISNUMBER(SEARCH("stretch",J:J)),"Kg's",IF(ISNUMBER(SEARCH("Bubble",J:J)),"Roll",IF(ISNUMBER(SEARCH("JTR",J:J)),"Rmt",IF(ISNUMBER(SEARCH("Rod",J:J)),"Kg's",IF(ISNUMBER(SEARCH("Handle",J:J)),"No's",IF(ISNUMBER(SEARCH("Gear",J:J)),"No's",IF(ISNUMBER(SEARCH("Bush",J:J)),"No's","")))))))))))))))))))) -> Sqmt | L37: 185 | T37: =IF(N37="","",SUM(N37,O37,P37,Q37,R37))
A38: =IF(C38="","",COUNT($C$3:C38)) -> 36 | B38: =IF(C38="","",TEXT(C38,"mmmm")) -> December | C38: 44926 | F38: Opening stock | G38: K Flex | J38: Insu Thermal Tape | K38: =IF(ISNUMBER(SEARCH("gsm",J:J)),"Kg's",IF(ISNUMBER(SEARCH("Tape",J:J)),"Roll",IF(ISNUMBER(SEARCH("Thermal",J:J)),"Sqmt",IF(ISNUMBER(SEARCH("Acou",J:J)),"Sqmt",IF(ISNUMBER(SEARCH("ss",J:J)),"Kg's",IF(ISNUMBER(SEARCH("Alu",J:J)),"Kg's",IF(ISNUMBER(SEARCH("Gasket",J:J)),"Rmt",IF(ISNUMBER(SEARCH("Cleats",J:J)),"No's",IF(ISNUMBER(SEARCH("Tube",J:J)),"No's",IF(ISNUMBER(SEARCH("Bracket",J:J)),"No's",IF(ISNUMBER(SEARCH("Corner",J:J)),"No's",IF(ISNUMBER(SEARCH("MS",J:J)),"Kg's",IF(ISNUMBER(SEARCH("Bucket",J:J)),"Kg's",IF(ISNUMBER(SEARCH("stretch",J:J)),"Kg's",IF(ISNUMBER(SEARCH("Bubble",J:J)),"Roll",IF(ISNUMBER(SEARCH("JTR",J:J)),"Rmt",IF(ISNUMBER(SEARCH("Rod",J:J)),"Kg's",IF(ISNUMBER(SEARCH("Handle",J:J)),"No's",IF(ISNUMBER(SEARCH("Gear",J:J)),"No's",IF(ISNUMBER(SEARCH("Bush",J:J)),"No's","")))))))))))))))))))) -> Roll | L38: 277 | T38: =IF(N38="","",SUM(N38,O38,P38,Q38,R38))
A39: =IF(C39="","",COUNT($C$3:C39)) -> 37 | B39: =IF(C39="","",TEXT(C39,"mmmm")) -> December | C39: 44926 | F39: Opening stock | G39: K Flex | J39: Insu Thermal IC Clad Tape | K39: =IF(ISNUMBER(SEARCH("gsm",J:J)),"Kg's",IF(ISNUMBER(SEARCH("Tape",J:J)),"Roll",IF(ISNUMBER(SEARCH("Thermal",J:J)),"Sqmt",IF(ISNUMBER(SEARCH("Acou",J:J)),"Sqmt",IF(ISNUMBER(SEARCH("ss",J:J)),"Kg's",IF(ISNUMBER(SEARCH("Alu",J:J)),"Kg's",IF(ISNUMBER(SEARCH("Gasket",J:J)),"Rmt",IF(ISNUMBER(SEARCH("Cleats",J:J)),"No's",IF(ISNUMBER(SEARCH("Tube",J:J)),"No's",IF(ISNUMBER(SEARCH("Bracket",J:J)),"No's",IF(ISNUMBER(SEARCH("Corner",J:J)),"No's",IF(ISNUMBER(SEARCH("MS",J:J)),"Kg's",IF(ISNUMBER(SEARCH("Bucket",J:J)),"Kg's",IF(ISNUMBER(SEARCH("stretch",J:J)),"Kg's",IF(ISNUMBER(SEARCH("Bubble",J:J)),"Roll",IF(ISNUMBER(SEARCH("JTR",J:J)),"Rmt",IF(ISNUMBER(SEARCH("Rod",J:J)),"Kg's",IF(ISNUMBER(SEARCH("Handle",J:J)),"No's",IF(ISNUMBER(SEARCH("Gear",J:J)),"No's",IF(ISNUMBER(SEARCH("Bush",J:J)),"No's","")))))))))))))))))))) -> Roll | L39: 102 | T39: =IF(N39="","",SUM(N39,O39,P39,Q39,R39))
A40: =IF(C40="","",COUNT($C$3:C40)) -> 38 | B40: =IF(C40="","",TEXT(C40,"mmmm")) -> December | C40: 44926 | F40: Opening stock | G40: Superlon | J40: Insu Superlon Thermal 25mm | K40: =IF(ISNUMBER(SEARCH("gsm",J:J)),"Kg's",IF(ISNUMBER(SEARCH("Tape",J:J)),"Roll",IF(ISNUMBER(SEARCH("Thermal",J:J)),"Sqmt",IF(ISNUMBER(SEARCH("Acou",J:J)),"Sqmt",IF(ISNUMBER(SEARCH("ss",J:J)),"Kg's",IF(ISNUMBER(SEARCH("Alu",J:J)),"Kg's",IF(ISNUMBER(SEARCH("Gasket",J:J)),"Rmt",IF(ISNUMBER(SEARCH("Cleats",J:J)),"No's",IF(ISNUMBER(SEARCH("Tube",J:J)),"No's",IF(ISNUMBER(SEARCH("Bracket",J:J)),"No's",IF(ISNUMBER(SEARCH("Corner",J:J)),"No's",IF(ISNUMBER(SEARCH("MS",J:J)),"Kg's",IF(ISNUMBER(SEARCH("Bucket",J:J)),"Kg's",IF(ISNUMBER(SEARCH("stretch",J:J)),"Kg's",IF(ISNUMBER(SEARCH("Bubble",J:J)),"Roll",IF(ISNUMBER(SEARCH("JTR",J:J)),"Rmt",IF(ISNUMBER(SEARCH("Rod",J:J)),"Kg's",IF(ISNUMBER(SEARCH("Handle",J:J)),"No's",IF(ISNUMBER(SEARCH("Gear",J:J)),"No's",IF(ISNUMBER(SEARCH("Bush",J:J)),"No's","")))))))))))))))))))) -> Sqmt | L40: 11.15 | T40: =IF(N40="","",SUM(N40,O40,P40,Q40,R40))
A41: =IF(C41="","",COUNT($C$3:C41)) -> 39 | B41: =IF(C41="","",TEXT(C41,"mmmm")) -> December | C41: 44926 | F41: Opening stock | G41: Superlon | J41: Insu Superlon Thermal 25mm Al. Foil | K41: =IF(ISNUMBER(SEARCH("gsm",J:J)),"Kg's",IF(ISNUMBER(SEARCH("Tape",J:J)),"Roll",IF(ISNUMBER(SEARCH("Thermal",J:J)),"Sqmt",IF(ISNUMBER(SEARCH("Acou",J:J)),"Sqmt",IF(ISNUMBER(SEARCH("ss",J:J)),"Kg's",IF(ISNUMBER(SEARCH("Alu",J:J)),"Kg's",IF(ISNUMBER(SEARCH("Gasket",J:J)),"Rmt",IF(ISNUMBER(SEARCH("Cleats",J:J)),"No's",IF(ISNUMBER(SEARCH("Tube",J:J)),"No's",IF(ISNUMBER(SEARCH("Bracket",J:J)),"No's",IF(ISNUMBER(SEARCH("Corner",J:J)),"No's",IF(ISNUMBER(SEARCH("MS",J:J)),"Kg's",IF(ISNUMBER(SEARCH("Bucket",J:J)),"Kg's",IF(ISNUMBER(SEARCH("stretch",J:J)),"Kg's",IF(ISNUMBER(SEARCH("Bubble",J:J)),"Roll",IF(ISNUMBER(SEARCH("JTR",J:J)),"Rmt",IF(ISNUMBER(SEARCH("Rod",J:J)),"Kg's",IF(ISNUMBER(SEARCH("Handle",J:J)),"No's",IF(ISNUMBER(SEARCH("Gear",J:J)),"No's",IF(ISNUMBER(SEARCH("Bush",J:J)),"No's","")))))))))))))))))))) -> Sqmt | L41: 22.3 | T41: =IF(N41="","",SUM(N41,O41,P41,Q41,R41))
A42: =IF(C42="","",COUNT($C$3:C42)) -> 40 | B42: =IF(C42="","",TEXT(C42,"mmmm")) -> December | C42: 44926 | F42: Opening stock | G42: Thermobreak | J42: Insu TB Thermal 13mm Al. Foil | K42: =IF(ISNUMBER(SEARCH("gsm",J:J)),"Kg's",IF(ISNUMBER(SEARCH("Tape",J:J)),"Roll",IF(ISNUMBER(SEARCH("Thermal",J:J)),"Sqmt",IF(ISNUMBER(SEARCH("Acou",J:J)),"Sqmt",IF(ISNUMBER(SEARCH("ss",J:J)),"Kg's",IF(ISNUMBER(SEARCH("Alu",J:J)),"Kg's",IF(ISNUMBER(SEARCH("Gasket",J:J)),"Rmt",IF(ISNUMBER(SEARCH("Cleats",J:J)),"No's",IF(ISNUMBER(SEARCH("Tube",J:J)),"No's",IF(ISNUMBER(SEARCH("Bracket",J:J)),"No's",IF(ISNUMBER(SEARCH("Corner",J:J)),"No's",IF(ISNUMBER(SEARCH("MS",J:J)),"Kg's",IF(ISNUMBER(SEARCH("Bucket",J:J)),"Kg's",IF(ISNUMBER(SEARCH("stretch",J:J)),"Kg's",IF(ISNUMBER(SEARCH("Bubble",J:J)),"Roll",IF(ISNUMBER(SEARCH("JTR",J:J)),"Rmt",IF(ISNUMBER(SEARCH("Rod",J:J)),"Kg's",IF(ISNUMBER(SEARCH("Handle",J:J)),"No's",IF(ISNUMBER(SEARCH("Gear",J:J)),"No's",IF(ISNUMBER(SEARCH("Bush",J:J)),"No's","")))))))))))))))))))) -> Sqmt | L42: 384 | T42: =IF(N42="","",SUM(N42,O42,P42,Q42,R42))
A43: =IF(C43="","",COUNT($C$3:C43)) -> 41 | B43: =IF(C43="","",TEXT(C43,"mmmm")) -> December | C43: 44926 | F43: Opening stock | G43: Thermobreak | J43: Insu TB Thermal 19mm Al. Foil | K43: =IF(ISNUMBER(SEARCH("gsm",J:J)),"Kg's",IF(ISNUMBER(SEARCH("Tape",J:J)),"Roll",IF(ISNUMBER(SEARCH("Thermal",J:J)),"Sqmt",IF(ISNUMBER(SEARCH("Acou",J:J)),"Sqmt",IF(ISNUMBER(SEARCH("ss",J:J)),"Kg's",IF(ISNUMBER(SEARCH("Alu",J:J)),"Kg's",IF(ISNUMBER(SEARCH("Gasket",J:J)),"Rmt",IF(ISNUMBER(SEARCH("Cleats",J:J)),"No's",IF(ISNUMBER(SEARCH("Tube",J:J)),"No's",IF(ISNUMBER(SEARCH("Bracket",J:J)),"No's",IF(ISNUMBER(SEARCH("Corner",J:J)),"No's",IF(ISNUMBER(SEARCH("MS",J:J)),"Kg's",IF(ISNUMBER(SEARCH("Bucket",J:J)),"Kg's",IF(ISNUMBER(SEARCH("stretch",J:J)),"Kg's",IF(ISNUMBER(SEARCH("Bubble",J:J)),"Roll",IF(ISNUMBER(SEARCH("JTR",J:J)),"Rmt",IF(ISNUMBER(SEARCH("Rod",J:J)),"Kg's",IF(ISNUMBER(SEARCH("Handle",J:J)),"No's",IF(ISNUMBER(SEARCH("Gear",J:J)),"No's",IF(ISNUMBER(SEARCH("Bush",J:J)),"No's","")))))))))))))))))))) -> Sqmt | L43: 912 | T43: =IF(N43="","",SUM(N43,O43,P43,Q43,R43))
A44: =IF(C44="","",COUNT($C$3:C44)) -> 42 | B44: =IF(C44="","",TEXT(C44,"mmmm")) -> December | C44: 44926 | F44: Opening stock | G44: Thermobreak | J44: Insu TB Thermal 25mm Al. Foil | K44: =IF(ISNUMBER(SEARCH("gsm",J:J)),"Kg's",IF(ISNUMBER(SEARCH("Tape",J:J)),"Roll",IF(ISNUMBER(SEARCH("Thermal",J:J)),"Sqmt",IF(ISNUMBER(SEARCH("Acou",J:J)),"Sqmt",IF(ISNUMBER(SEARCH("ss",J:J)),"Kg's",IF(ISNUMBER(SEARCH("Alu",J:J)),"Kg's",IF(ISNUMBER(SEARCH("Gasket",J:J)),"Rmt",IF(ISNUMBER(SEARCH("Cleats",J:J)),"No's",IF(ISNUMBER(SEARCH("Tube",J:J)),"No's",IF(ISNUMBER(SEARCH("Bracket",J:J)),"No's",IF(ISNUMBER(SEARCH("Corner",J:J)),"No's",IF(ISNUMBER(SEARCH("MS",J:J)),"Kg's",IF(ISNUMBER(SEARCH("Bucket",J:J)),"Kg's",IF(ISNUMBER(SEARCH("stretch",J:J)),"Kg's",IF(ISNUMBER(SEARCH("Bubble",J:J)),"Roll",IF(ISNUMBER(SEARCH("JTR",J:J)),"Rmt",IF(ISNUMBER(SEARCH("Rod",J:J)),"Kg's",IF(ISNUMBER(SEARCH("Handle",J:J)),"No's",IF(ISNUMBER(SEARCH("Gear",J:J)),"No's",IF(ISNUMBER(SEARCH("Bush",J:J)),"No's","")))))))))))))))))))) -> Sqmt | L44: 33.12 | T44: =IF(N44="","",SUM(N44,O44,P44,Q44,R44))
A45: =IF(C45="","",COUNT($C$3:C45)) -> 43 | B45: =IF(C45="","",TEXT(C45,"mmmm")) -> December | C45: 44926 | F45: Opening stock | G45: Thermobreak | J45: Insu TB Acou 10mm Al. Foil | K45: =IF(ISNUMBER(SEARCH("gsm",J:J)),"Kg's",IF(ISNUMBER(SEARCH("Tape",J:J)),"Roll",IF(ISNUMBER(SEARCH("Thermal",J:J)),"Sqmt",IF(ISNUMBER(SEARCH("Acou",J:J)),"Sqmt",IF(ISNUMBER(SEARCH("ss",J:J)),"Kg's",IF(ISNUMBER(SEARCH("Alu",J:J)),"Kg's",IF(ISNUMBER(SEARCH("Gasket",J:J)),"Rmt",IF(ISNUMBER(SEARCH("Cleats",J:J)),"No's",IF(ISNUMBER(SEARCH("Tube",J:J)),"No's",IF(ISNUMBER(SEARCH("Bracket",J:J)),"No's",IF(ISNUMBER(SEARCH("Corner",J:J)),"No's",IF(ISNUMBER(SEARCH("MS",J:J)),"Kg's",IF(ISNUMBER(SEARCH("Bucket",J:J)),"Kg's",IF(ISNUMBER(SEARCH("stretch",J:J)),"Kg's",IF(ISNUMBER(SEARCH("Bubble",J:J)),"Roll",IF(ISNUMBER(SEARCH("JTR",J:J)),"Rmt",IF(ISNUMBER(SEARCH("Rod",J:J)),"Kg's",IF(ISNUMBER(SEARCH("Handle",J:J)),"No's",IF(ISNUMBER(SEARCH("Gear",J:J)),"No's",IF(ISNUMBER(SEARCH("Bush",J:J)),"No's","")))))))))))))))))))) -> Sqmt | L45: 336 | T45: =IF(N45="","",SUM(N45,O45,P45,Q45,R45))
A46: =IF(C46="","",COUNT($C$3:C46)) -> 44 | B46: =IF(C46="","",TEXT(C46,"mmmm")) -> December | C46: 44926 | F46: Opening stock | G46: Thermobreak | J46: Insu TB Acou 15mm Al. Foil | K46: =IF(ISNUMBER(SEARCH("gsm",J:J)),"Kg's",IF(ISNUMBER(SEARCH("Tape",J:J)),"Roll",IF(ISNUMBER(SEARCH("Thermal",J:J)),"Sqmt",IF(ISNUMBER(SEARCH("Acou",J:J)),"Sqmt",IF(ISNUMBER(SEARCH("ss",J:J)),"Kg's",IF(ISNUMBER(SEARCH("Alu",J:J)),"Kg's",IF(ISNUMBER(SEARCH("Gasket",J:J)),"Rmt",IF(ISNUMBER(SEARCH("Cleats",J:J)),"No's",IF(ISNUMBER(SEARCH("Tube",J:J)),"No's",IF(ISNUMBER(SEARCH("Bracket",J:J)),"No's",IF(ISNUMBER(SEARCH("Corner",J:J)),"No's",IF(ISNUMBER(SEARCH("MS",J:J)),"Kg's",IF(ISNUMBER(SEARCH("Bucket",J:J)),"Kg's",IF(ISNUMBER(SEARCH("stretch",J:J)),"Kg's",IF(ISNUMBER(SEARCH("Bubble",J:J)),"Roll",IF(ISNUMBER(SEARCH("JTR",J:J)),"Rmt",IF(ISNUMBER(SEARCH("Rod",J:J)),"Kg's",IF(ISNUMBER(SEARCH("Handle",J:J)),"No's",IF(ISNUMBER(SEARCH("Gear",J:J)),"No's",IF(ISNUMBER(SEARCH("Bush",J:J)),"No's","")))))))))))))))))))) -> Sqmt | L46: 331.2 | T46: =IF(N46="","",SUM(N46,O46,P46,Q46,R46))
A47: =IF(C47="","",COUNT($C$3:C47)) -> 45 | B47: =IF(C47="","",TEXT(C47,"mmmm")) -> December | C47: 44926 | F47: Opening stock | G47: Thermobreak | J47: Insu TB Acou 24mm Al. Foil | K47: =IF(ISNUMBER(SEARCH("gsm",J:J)),"Kg's",IF(ISNUMBER(SEARCH("Tape",J:J)),"Roll",IF(ISNUMBER(SEARCH("Thermal",J:J)),"Sqmt",IF(ISNUMBER(SEARCH("Acou",J:J)),"Sqmt",IF(ISNUMBER(SEARCH("ss",J:J)),"Kg's",IF(ISNUMBER(SEARCH("Alu",J:J)),"Kg's",IF(ISNUMBER(SEARCH("Gasket",J:J)),"Rmt",IF(ISNUMBER(SEARCH("Cleats",J:J)),"No's",IF(ISNUMBER(SEARCH("Tube",J:J)),"No's",IF(ISNUMBER(SEARCH("Bracket",J:J)),"No's",IF(ISNUMBER(SEARCH("Corner",J:J)),"No's",IF(ISNUMBER(SEARCH("MS",J:J)),"Kg's",IF(ISNUMBER(SEARCH("Bucket",J:J)),"Kg's",IF(ISNUMBER(SEARCH("stretch",J:J)),"Kg's",IF(ISNUMBER(SEARCH("Bubble",J:J)),"Roll",IF(ISNUMBER(SEARCH("JTR",J:J)),"Rmt",IF(ISNUMBER(SEARCH("Rod",J:J)),"Kg's",IF(ISNUMBER(SEARCH("Handle",J:J)),"No's",IF(ISNUMBER(SEARCH("Gear",J:J)),"No's",IF(ISNUMBER(SEARCH("Bush",J:J)),"No's","")))))))))))))))))))) -> Sqmt | L47: 110.4 | T47: =IF(N47="","",SUM(N47,O47,P47,Q47,R47))
A48: =IF(C48="","",COUNT($C$3:C48)) -> 46 | B48: =IF(C48="","",TEXT(C48,"mmmm")) -> December | C48: 44926 | F48: Opening stock | G48: Thermobreak | J48: Tape THBR 50mm x 50Mtr Alumn | K48: =IF(ISNUMBER(SEARCH("gsm",J:J)),"Kg's",IF(ISNUMBER(SEARCH("Tape",J:J)),"Roll",IF(ISNUMBER(SEARCH("Thermal",J:J)),"Sqmt",IF(ISNUMBER(SEARCH("Acou",J:J)),"Sqmt",IF(ISNUMBER(SEARCH("ss",J:J)),"Kg's",IF(ISNUMBER(SEARCH("Alu",J:J)),"Kg's",IF(ISNUMBER(SEARCH("Gasket",J:J)),"Rmt",IF(ISNUMBER(SEARCH("Cleats",J:J)),"No's",IF(ISNUMBER(SEARCH("Tube",J:J)),"No's",IF(ISNUMBER(SEARCH("Bracket",J:J)),"No's",IF(ISNUMBER(SEARCH("Corner",J:J)),"No's",IF(ISNUMBER(SEARCH("MS",J:J)),"Kg's",IF(ISNUMBER(SEARCH("Bucket",J:J)),"Kg's",IF(ISNUMBER(SEARCH("stretch",J:J)),"Kg's",IF(ISNUMBER(SEARCH("Bubble",J:J)),"Roll",IF(ISNUMBER(SEARCH("JTR",J:J)),"Rmt",IF(ISNUMBER(SEARCH("Rod",J:J)),"Kg's",IF(ISNUMBER(SEARCH("Handle",J:J)),"No's",IF(ISNUMBER(SEARCH("Gear",J:J)),"No's",IF(ISNUMBER(SEARCH("Bush",J:J)),"No's","")))))))))))))))))))) -> Roll | L48: 27
A49: =IF(C49="","",COUNT($C$3:C49)) -> 47 | B49: =IF(C49="","",TEXT(C49,"mmmm")) -> December | C49: 44926 | F49: Opening stock | G49: Supreme | J49: Insu Supreme Thermal 9mm | K49: =IF(ISNUMBER(SEARCH("gsm",J:J)),"Kg's",IF(ISNUMBER(SEARCH("Tape",J:J)),"Roll",IF(ISNUMBER(SEARCH("Thermal",J:J)),"Sqmt",IF(ISNUMBER(SEARCH("Acou",J:J)),"Sqmt",IF(ISNUMBER(SEARCH("ss",J:J)),"Kg's",IF(ISNUMBER(SEARCH("Alu",J:J)),"Kg's",IF(ISNUMBER(SEARCH("Gasket",J:J)),"Rmt",IF(ISNUMBER(SEARCH("Cleats",J:J)),"No's",IF(ISNUMBER(SEARCH("Tube",J:J)),"No's",IF(ISNUMBER(SEARCH("Bracket",J:J)),"No's",IF(ISNUMBER(SEARCH("Corner",J:J)),"No's",IF(ISNUMBER(SEARCH("MS",J:J)),"Kg's",IF(ISNUMBER(SEARCH("Bucket",J:J)),"Kg's",IF(ISNUMBER(SEARCH("stretch",J:J)),"Kg's",IF(ISNUMBER(SEARCH("Bubble",J:J)),"Roll",IF(ISNUMBER(SEARCH("JTR",J:J)),"Rmt",IF(ISNUMBER(SEARCH("Rod",J:J)),"Kg's",IF(ISNUMBER(SEARCH("Handle",J:J)),"No's",IF(ISNUMBER(SEARCH("Gear",J:J)),"No's",IF(ISNUMBER(SEARCH("Bush",J:J)),"No's","")))))))))))))))))))) -> Sqmt | L49: 504 | T49: =IF(N49="","",SUM(N49,O49,P49,Q49,R49))
A50: =IF(C50="","",COUNT($C$3:C50)) -> 48 | B50: =IF(C50="","",TEXT(C50,"mmmm")) -> December | C50: 44926 | F50: Opening stock | G50: Supreme | J50: Insu Supreme Thermal 13mm | K50: =IF(ISNUMBER(SEARCH("gsm",J:J)),"Kg's",IF(ISNUMBER(SEARCH("Tape",J:J)),"Roll",IF(ISNUMBER(SEARCH("Thermal",J:J)),"Sqmt",IF(ISNUMBER(SEARCH("Acou",J:J)),"Sqmt",IF(ISNUMBER(SEARCH("ss",J:J)),"Kg's",IF(ISNUMBER(SEARCH("Alu",J:J)),"Kg's",IF(ISNUMBER(SEARCH("Gasket",J:J)),"Rmt",IF(ISNUMBER(SEARCH("Cleats",J:J)),"No's",IF(ISNUMBER(SEARCH("Tube",J:J)),"No's",IF(ISNUMBER(SEARCH("Bracket",J:J)),"No's",IF(ISNUMBER(SEARCH("Corner",J:J)),"No's",IF(ISNUMBER(SEARCH("MS",J:J)),"Kg's",IF(ISNUMBER(SEARCH("Bucket",J:J)),"Kg's",IF(ISNUMBER(SEARCH("stretch",J:J)),"Kg's",IF(ISNUMBER(SEARCH("Bubble",J:J)),"Roll",IF(ISNUMBER(SEARCH("JTR",J:J)),"Rmt",IF(ISNUMBER(SEARCH("Rod",J:J)),"Kg's",IF(ISNUMBER(SEARCH("Handle",J:J)),"No's",IF(ISNUMBER(SEARCH("Gear",J:J)),"No's",IF(ISNUMBER(SEARCH("Bush",J:J)),"No's","")))))))))))))))))))) -> Sqmt | L50: 1142.4 | T50: =IF(N50="","",SUM(N50,O50,P50,Q50,R50))
A51: =IF(C51="","",COUNT($C$3:C51)) -> 49 | B51: =IF(C51="","",TEXT(C51,"mmmm")) -> December | C51: 44926 | F51: Opening stock | G51: Supreme | J51: Insu Supreme Thermal 16mm | K51: =IF(ISNUMBER(SEARCH("gsm",J:J)),"Kg's",IF(ISNUMBER(SEARCH("Tape",J:J)),"Roll",IF(ISNUMBER(SEARCH("Thermal",J:J)),"Sqmt",IF(ISNUMBER(SEARCH("Acou",J:J)),"Sqmt",IF(ISNUMBER(SEARCH("ss",J:J)),"Kg's",IF(ISNUMBER(SEARCH("Alu",J:J)),"Kg's",IF(ISNUMBER(SEARCH("Gasket",J:J)),"Rmt",IF(ISNUMBER(SEARCH("Cleats",J:J)),"No's",IF(ISNUMBER(SEARCH("Tube",J:J)),"No's",IF(ISNUMBER(SEARCH("Bracket",J:J)),"No's",IF(ISNUMBER(SEARCH("Corner",J:J)),"No's",IF(ISNUMBER(SEARCH("MS",J:J)),"Kg's",IF(ISNUMBER(SEARCH("Bucket",J:J)),"Kg's",IF(ISNUMBER(SEARCH("stretch",J:J)),"Kg's",IF(ISNUMBER(SEARCH("Bubble",J:J)),"Roll",IF(ISNUMBER(SEARCH("JTR",J:J)),"Rmt",IF(ISNUMBER(SEARCH("Rod",J:J)),"Kg's",IF(ISNUMBER(SEARCH("Handle",J:J)),"No's",IF(ISNUMBER(SEARCH("Gear",J:J)),"No's",IF(ISNUMBER(SEARCH("Bush",J:J)),"No's","")))))))))))))))))))) -> Sqmt | L51: 1008
A52: =IF(C52="","",COUNT($C$3:C52)) -> 50 | B52: =IF(C52="","",TEXT(C52,"mmmm")) -> December | C52: 44926 | F52: Opening stock | G52: Supreme | J52: Insu Supreme Thermal 13mm Al. Foil | K52: =IF(ISNUMBER(SEARCH("gsm",J:J)),"Kg's",IF(ISNUMBER(SEARCH("Tape",J:J)),"Roll",IF(ISNUMBER(SEARCH("Thermal",J:J)),"Sqmt",IF(ISNUMBER(SEARCH("Acou",J:J)),"Sqmt",IF(ISNUMBER(SEARCH("ss",J:J)),"Kg's",IF(ISNUMBER(SEARCH("Alu",J:J)),"Kg's",IF(ISNUMBER(SEARCH("Gasket",J:J)),"Rmt",IF(ISNUMBER(SEARCH("Cleats",J:J)),"No's",IF(ISNUMBER(SEARCH("Tube",J:J)),"No's",IF(ISNUMBER(SEARCH("Bracket",J:J)),"No's",IF(ISNUMBER(SEARCH("Corner",J:J)),"No's",IF(ISNUMBER(SEARCH("MS",J:J)),"Kg's",IF(ISNUMBER(SEARCH("Bucket",J:J)),"Kg's",IF(ISNUMBER(SEARCH("stretch",J:J)),"Kg's",IF(ISNUMBER(SEARCH("Bubble",J:J)),"Roll",IF(ISNUMBER(SEARCH("JTR",J:J)),"Rmt",IF(ISNUMBER(SEARCH("Rod",J:J)),"Kg's",IF(ISNUMBER(SEARCH("Handle",J:J)),"No's",IF(ISNUMBER(SEARCH("Gear",J:J)),"No's",IF(ISNUMBER(SEARCH("Bush",J:J)),"No's","")))))))))))))))))))) -> Sqmt | L52: 93.75 | T52: =IF(N52="","",SUM(N52,O52,P52,Q52,R52))
A53: =IF(C53="","",COUNT($C$3:C53)) -> 51 | B53: =IF(C53="","",TEXT(C53,"mmmm")) -> December | C53: 44926 | F53: Opening stock | G53: Supreme | J53: Insu Supreme Thermal 19mm Al. Foil | K53: =IF(ISNUMBER(SEARCH("gsm",J:J)),"Kg's",IF(ISNUMBER(SEARCH("Tape",J:J)),"Roll",IF(ISNUMBER(SEARCH("Thermal",J:J)),"Sqmt",IF(ISNUMBER(SEARCH("Acou",J:J)),"Sqmt",IF(ISNUMBER(SEARCH("ss",J:J)),"Kg's",IF(ISNUMBER(SEARCH("Alu",J:J)),"Kg's",IF(ISNUMBER(SEARCH("Gasket",J:J)),"Rmt",IF(ISNUMBER(SEARCH("Cleats",J:J)),"No's",IF(ISNUMBER(SEARCH("Tube",J:J)),"No's",IF(ISNUMBER(SEARCH("Bracket",J:J)),"No's",IF(ISNUMBER(SEARCH("Corner",J:J)),"No's",IF(ISNUMBER(SEARCH("MS",J:J)),"Kg's",IF(ISNUMBER(SEARCH("Bucket",J:J)),"Kg's",IF(ISNUMBER(SEARCH("stretch",J:J)),"Kg's",IF(ISNUMBER(SEARCH("Bubble",J:J)),"Roll",IF(ISNUMBER(SEARCH("JTR",J:J)),"Rmt",IF(ISNUMBER(SEARCH("Rod",J:J)),"Kg's",IF(ISNUMBER(SEARCH("Handle",J:J)),"No's",IF(ISNUMBER(SEARCH("Gear",J:J)),"No's",IF(ISNUMBER(SEARCH("Bush",J:J)),"No's","")))))))))))))))))))) -> Sqmt | L53: 48.8 | T53: =IF(N53="","",SUM(N53,O53,P53,Q53,R53))
A54: =IF(C54="","",COUNT($C$3:C54)) -> 52 | B54: =IF(C54="","",TEXT(C54,"mmmm")) -> December | C54: 44926 | F54: Opening stock | G54: Supreme | J54: Insu Supreme Thermal 25mm Al. Foil | K54: =IF(ISNUMBER(SEARCH("gsm",J:J)),"Kg's",IF(ISNUMBER(SEARCH("Tape",J:J)),"Roll",IF(ISNUMBER(SEARCH("Thermal",J:J)),"Sqmt",IF(ISNUMBER(SEARCH("Acou",J:J)),"Sqmt",IF(ISNUMBER(SEARCH("ss",J:J)),"Kg's",IF(ISNUMBER(SEARCH("Alu",J:J)),"Kg's",IF(ISNUMBER(SEARCH("Gasket",J:J)),"Rmt",IF(ISNUMBER(SEARCH("Cleats",J:J)),"No's",IF(ISNUMBER(SEARCH("Tube",J:J)),"No's",IF(ISNUMBER(SEARCH("Bracket",J:J)),"No's",IF(ISNUMBER(SEARCH("Corner",J:J)),"No's",IF(ISNUMBER(SEARCH("MS",J:J)),"Kg's",IF(ISNUMBER(SEARCH("Bucket",J:J)),"Kg's",IF(ISNUMBER(SEARCH("stretch",J:J)),"Kg's",IF(ISNUMBER(SEARCH("Bubble",J:J)),"Roll",IF(ISNUMBER(SEARCH("JTR",J:J)),"Rmt",IF(ISNUMBER(SEARCH("Rod",J:J)),"Kg's",IF(ISNUMBER(SEARCH("Handle",J:J)),"No's",IF(ISNUMBER(SEARCH("Gear",J:J)),"No's",IF(ISNUMBER(SEARCH("Bush",J:J)),"No's","")))))))))))))))))))) -> Sqmt | L54: 54.9 | T54: =IF(N54="","",SUM(N54,O54,P54,Q54,R54))
A55: =IF(C55="","",COUNT($C$3:C55)) -> 53 | B55: =IF(C55="","",TEXT(C55,"mmmm")) -> December | C55: 44926 | F55: Opening stock | G55: Supreme | J55: Insu Supreme 10mm Acou. | K55: =IF(ISNUMBER(SEARCH("gsm",J:J)),"Kg's",IF(ISNUMBER(SEARCH("Tape",J:J)),"Roll",IF(ISNUMBER(SEARCH("Thermal",J:J)),"Sqmt",IF(ISNUMBER(SEARCH("Acou",J:J)),"Sqmt",IF(ISNUMBER(SEARCH("ss",J:J)),"Kg's",IF(ISNUMBER(SEARCH("Alu",J:J)),"Kg's",IF(ISNUMBER(SEARCH("Gasket",J:J)),"Rmt",IF(ISNUMBER(SEARCH("Cleats",J:J)),"No's",IF(ISNUMBER(SEARCH("Tube",J:J)),"No's",IF(ISNUMBER(SEARCH("Bracket",J:J)),"No's",IF(ISNUMBER(SEARCH("Corner",J:J)),"No's",IF(ISNUMBER(SEARCH("MS",J:J)),"Kg's",IF(ISNUMBER(SEARCH("Bucket",J:J)),"Kg's",IF(ISNUMBER(SEARCH("stretch",J:J)),"Kg's",IF(ISNUMBER(SEARCH("Bubble",J:J)),"Roll",IF(ISNUMBER(SEARCH("JTR",J:J)),"Rmt",IF(ISNUMBER(SEARCH("Rod",J:J)),"Kg's",IF(ISNUMBER(SEARCH("Handle",J:J)),"No's",IF(ISNUMBER(SEARCH("Gear",J:J)),"No's",IF(ISNUMBER(SEARCH("Bush",J:J)),"No's","")))))))))))))))))))) -> Sqmt | L55: 192
A56: =IF(C56="","",COUNT($C$3:C56)) -> 54 | B56: =IF(C56="","",TEXT(C56,"mmmm")) -> December | C56: 44926 | F56: Opening stock | G56: Supreme | J56: Insu Supreme 15mm Acou. | K56: =IF(ISNUMBER(SEARCH("gsm",J:J)),"Kg's",IF(ISNUMBER(SEARCH("Tape",J:J)),"Roll",IF(ISNUMBER(SEARCH("Thermal",J:J)),"Sqmt",IF(ISNUMBER(SEARCH("Acou",J:J)),"Sqmt",IF(ISNUMBER(SEARCH("ss",J:J)),"Kg's",IF(ISNUMBER(SEARCH("Alu",J:J)),"Kg's",IF(ISNUMBER(SEARCH("Gasket",J:J)),"Rmt",IF(ISNUMBER(SEARCH("Cleats",J:J)),"No's",IF(ISNUMBER(SEARCH("Tube",J:J)),"No's",IF(ISNUMBER(SEARCH("Bracket",J:J)),"No's",IF(ISNUMBER(SEARCH("Corner",J:J)),"No's",IF(ISNUMBER(SEARCH("MS",J:J)),"Kg's",IF(ISNUMBER(SEARCH("Bucket",J:J)),"Kg's",IF(ISNUMBER(SEARCH("stretch",J:J)),"Kg's",IF(ISNUMBER(SEARCH("Bubble",J:J)),"Roll",IF(ISNUMBER(SEARCH("JTR",J:J)),"Rmt",IF(ISNUMBER(SEARCH("Rod",J:J)),"Kg's",IF(ISNUMBER(SEARCH("Handle",J:J)),"No's",IF(ISNUMBER(SEARCH("Gear",J:J)),"No's",IF(ISNUMBER(SEARCH("Bush",J:J)),"No's","")))))))))))))))))))) -> Sqmt | L56: 888 | T56: =IF(N56="","",SUM(N56,O56,P56,Q56,R56))
A57: =IF(C57="","",COUNT($C$3:C57)) -> 55 | B57: =IF(C57="","",TEXT(C57,"mmmm")) -> December | C57: 44926 | F57: Opening stock | G57: Airofoam | J57: Insu Airofoam Thermal 19mm Al. Foil | K57: =IF(ISNUMBER(SEARCH("gsm",J:J)),"Kg's",IF(ISNUMBER(SEARCH("Tape",J:J)),"Roll",IF(ISNUMBER(SEARCH("Thermal",J:J)),"Sqmt",IF(ISNUMBER(SEARCH("Acou",J:J)),"Sqmt",IF(ISNUMBER(SEARCH("ss",J:J)),"Kg's",IF(ISNUMBER(SEARCH("Alu",J:J)),"Kg's",IF(ISNUMBER(SEARCH("Gasket",J:J)),"Rmt",IF(ISNUMBER(SEARCH("Cleats",J:J)),"No's",IF(ISNUMBER(SEARCH("Tube",J:J)),"No's",IF(ISNUMBER(SEARCH("Bracket",J:J)),"No's",IF(ISNUMBER(SEARCH("Corner",J:J)),"No's",IF(ISNUMBER(SEARCH("MS",J:J)),"Kg's",IF(ISNUMBER(SEARCH("Bucket",J:J)),"Kg's",IF(ISNUMBER(SEARCH("stretch",J:J)),"Kg's",IF(ISNUMBER(SEARCH("Bubble",J:J)),"Roll",IF(ISNUMBER(SEARCH("JTR",J:J)),"Rmt",IF(ISNUMBER(SEARCH("Rod",J:J)),"Kg's",IF(ISNUMBER(SEARCH("Handle",J:J)),"No's",IF(ISNUMBER(SEARCH("Gear",J:J)),"No's",IF(ISNUMBER(SEARCH("Bush",J:J)),"No's","")))))))))))))))))))) -> Sqmt | L57: 96 | T57: =IF(N57="","",SUM(N57,O57,P57,Q57,R57))
A58: =IF(C58="","",COUNT($C$3:C58)) -> 56 | B58: =IF(C58="","",TEXT(C58,"mmmm")) -> December | C58: 44926 | F58: Opening stock | G58: Armaflex | J58: Insu Armaflex Thermal 6mm | K58: =IF(ISNUMBER(SEARCH("gsm",J:J)),"Kg's",IF(ISNUMBER(SEARCH("Tape",J:J)),"Roll",IF(ISNUMBER(SEARCH("Thermal",J:J)),"Sqmt",IF(ISNUMBER(SEARCH("Acou",J:J)),"Sqmt",IF(ISNUMBER(SEARCH("ss",J:J)),"Kg's",IF(ISNUMBER(SEARCH("Alu",J:J)),"Kg's",IF(ISNUMBER(SEARCH("Gasket",J:J)),"Rmt",IF(ISNUMBER(SEARCH("Cleats",J:J)),"No's",IF(ISNUMBER(SEARCH("Tube",J:J)),"No's",IF(ISNUMBER(SEARCH("Bracket",J:J)),"No's",IF(ISNUMBER(SEARCH("Corner",J:J)),"No's",IF(ISNUMBER(SEARCH("MS",J:J)),"Kg's",IF(ISNUMBER(SEARCH("Bucket",J:J)),"Kg's",IF(ISNUMBER(SEARCH("stretch",J:J)),"Kg's",IF(ISNUMBER(SEARCH("Bubble",J:J)),"Roll",IF(ISNUMBER(SEARCH("JTR",J:J)),"Rmt",IF(ISNUMBER(SEARCH("Rod",J:J)),"Kg's",IF(ISNUMBER(SEARCH("Handle",J:J)),"No's",IF(ISNUMBER(SEARCH("Gear",J:J)),"No's",IF(ISNUMBER(SEARCH("Bush",J:J)),"No's","")))))))))))))))))))) -> Sqmt | L58: 136 | T58: =IF(N58="","",SUM(N58,O58,P58,Q58,R58))
A59: =IF(C59="","",COUNT($C$3:C59)) -> 57 | B59: =IF(C59="","",TEXT(C59,"mmmm")) -> December | C59: 44926 | F59: Opening stock | G59: Armaflex | J59: Insu Armaflex Thermal 25mm | K59: =IF(ISNUMBER(SEARCH("gsm",J:J)),"Kg's",IF(ISNUMBER(SEARCH("Tape",J:J)),"Roll",IF(ISNUMBER(SEARCH("Thermal",J:J)),"Sqmt",IF(ISNUMBER(SEARCH("Acou",J:J)),"Sqmt",IF(ISNUMBER(SEARCH("ss",J:J)),"Kg's",IF(ISNUMBER(SEARCH("Alu",J:J)),"Kg's",IF(ISNUMBER(SEARCH("Gasket",J:J)),"Rmt",IF(ISNUMBER(SEARCH("Cleats",J:J)),"No's",IF(ISNUMBER(SEARCH("Tube",J:J)),"No's",IF(ISNUMBER(SEARCH("Bracket",J:J)),"No's",IF(ISNUMBER(SEARCH("Corner",J:J)),"No's",IF(ISNUMBER(SEARCH("MS",J:J)),"Kg's",IF(ISNUMBER(SEARCH("Bucket",J:J)),"Kg's",IF(ISNUMBER(SEARCH("stretch",J:J)),"Kg's",IF(ISNUMBER(SEARCH("Bubble",J:J)),"Roll",IF(ISNUMBER(SEARCH("JTR",J:J)),"Rmt",IF(ISNUMBER(SEARCH("Rod",J:J)),"Kg's",IF(ISNUMBER(SEARCH("Handle",J:J)),"No's",IF(ISNUMBER(SEARCH("Gear",J:J)),"No's",IF(ISNUMBER(SEARCH("Bush",J:J)),"No's","")))))))))))))))))))) -> Sqmt | L59: 162 | T59: =IF(N59="","",SUM(N59,O59,P59,Q59,R59))
A60: =IF(C60="","",COUNT($C$3:C60)) -> 58 | B60: =IF(C60="","",TEXT(C60,"mmmm")) -> December | C60: 44926 | F60: Opening stock | G60: Armaflex | J60: Insu Armaflex Thermal 19mm Al. Foil | K60: =IF(ISNUMBER(SEARCH("gsm",J:J)),"Kg's",IF(ISNUMBER(SEARCH("Tape",J:J)),"Roll",IF(ISNUMBER(SEARCH("Thermal",J:J)),"Sqmt",IF(ISNUMBER(SEARCH("Acou",J:J)),"Sqmt",IF(ISNUMBER(SEARCH("ss",J:J)),"Kg's",IF(ISNUMBER(SEARCH("Alu",J:J)),"Kg's",IF(ISNUMBER(SEARCH("Gasket",J:J)),"Rmt",IF(ISNUMBER(SEARCH("Cleats",J:J)),"No's",IF(ISNUMBER(SEARCH("Tube",J:J)),"No's",IF(ISNUMBER(SEARCH("Bracket",J:J)),"No's",IF(ISNUMBER(SEARCH("Corner",J:J)),"No's",IF(ISNUMBER(SEARCH("MS",J:J)),"Kg's",IF(ISNUMBER(SEARCH("Bucket",J:J)),"Kg's",IF(ISNUMBER(SEARCH("stretch",J:J)),"Kg's",IF(ISNUMBER(SEARCH("Bubble",J:J)),"Roll",IF(ISNUMBER(SEARCH("JTR",J:J)),"Rmt",IF(ISNUMBER(SEARCH("Rod",J:J)),"Kg's",IF(ISNUMBER(SEARCH("Handle",J:J)),"No's",IF(ISNUMBER(SEARCH("Gear",J:J)),"No's",IF(ISNUMBER(SEARCH("Bush",J:J)),"No's","")))))))))))))))))))) -> Sqmt | L60: 60 | T60: =IF(N60="","",SUM(N60,O60,P60,Q60,R60))
A61: =IF(C61="","",COUNT($C$3:C61)) -> 59 | B61: =IF(C61="","",TEXT(C61,"mmmm")) -> December | C61: 44926 | F61: Opening stock | G61: Armaflex | J61: Insu Armaflex Thermal 25mm Al. Foil | K61: =IF(ISNUMBER(SEARCH("gsm",J:J)),"Kg's",IF(ISNUMBER(SEARCH("Tape",J:J)),"Roll",IF(ISNUMBER(SEARCH("Thermal",J:J)),"Sqmt",IF(ISNUMBER(SEARCH("Acou",J:J)),"Sqmt",IF(ISNUMBER(SEARCH("ss",J:J)),"Kg's",IF(ISNUMBER(SEARCH("Alu",J:J)),"Kg's",IF(ISNUMBER(SEARCH("Gasket",J:J)),"Rmt",IF(ISNUMBER(SEARCH("Cleats",J:J)),"No's",IF(ISNUMBER(SEARCH("Tube",J:J)),"No's",IF(ISNUMBER(SEARCH("Bracket",J:J)),"No's",IF(ISNUMBER(SEARCH("Corner",J:J)),"No's",IF(ISNUMBER(SEARCH("MS",J:J)),"Kg's",IF(ISNUMBER(SEARCH("Bucket",J:J)),"Kg's",IF(ISNUMBER(SEARCH("stretch",J:J)),"Kg's",IF(ISNUMBER(SEARCH("Bubble",J:J)),"Roll",IF(ISNUMBER(SEARCH("JTR",J:J)),"Rmt",IF(ISNUMBER(SEARCH("Rod",J:J)),"Kg's",IF(ISNUMBER(SEARCH("Handle",J:J)),"No's",IF(ISNUMBER(SEARCH("Gear",J:J)),"No's",IF(ISNUMBER(SEARCH("Bush",J:J)),"No's","")))))))))))))))))))) -> Sqmt | L61: 36 | T61: =IF(N61="","",SUM(N61,O61,P61,Q61,R61))
A62: =IF(C62="","",COUNT($C$3:C62)) -> 60 | B62: =IF(C62="","",TEXT(C62,"mmmm")) -> December | C62: 44926 | F62: Opening stock | G62: Armasound | J62: Insu Armasound Acou. 10mm | K62: =IF(ISNUMBER(SEARCH("gsm",J:J)),"Kg's",IF(ISNUMBER(SEARCH("Tape",J:J)),"Roll",IF(ISNUMBER(SEARCH("Thermal",J:J)),"Sqmt",IF(ISNUMBER(SEARCH("Acou",J:J)),"Sqmt",IF(ISNUMBER(SEARCH("ss",J:J)),"Kg's",IF(ISNUMBER(SEARCH("Alu",J:J)),"Kg's",IF(ISNUMBER(SEARCH("Gasket",J:J)),"Rmt",IF(ISNUMBER(SEARCH("Cleats",J:J)),"No's",IF(ISNUMBER(SEARCH("Tube",J:J)),"No's",IF(ISNUMBER(SEARCH("Bracket",J:J)),"No's",IF(ISNUMBER(SEARCH("Corner",J:J)),"No's",IF(ISNUMBER(SEARCH("MS",J:J)),"Kg's",IF(ISNUMBER(SEARCH("Bucket",J:J)),"Kg's",IF(ISNUMBER(SEARCH("stretch",J:J)),"Kg's",IF(ISNUMBER(SEARCH("Bubble",J:J)),"Roll",IF(ISNUMBER(SEARCH("JTR",J:J)),"Rmt",IF(ISNUMBER(SEARCH("Rod",J:J)),"Kg's",IF(ISNUMBER(SEARCH("Handle",J:J)),"No's",IF(ISNUMBER(SEARCH("Gear",J:J)),"No's",IF(ISNUMBER(SEARCH("Bush",J:J)),"No's","")))))))))))))))))))) -> Sqmt | L62: 51 | T62: =IF(N62="","",SUM(N62,O62,P62,Q62,R62))
A63: =IF(C63="","",COUNT($C$3:C63)) -> 61 | B63: =IF(C63="","",TEXT(C63,"mmmm")) -> December | C63: 44926 | F63: Opening stock | G63: Armasound | J63: Insu Armasound Acou. 15mm | K63: =IF(ISNUMBER(SEARCH("gsm",J:J)),"Kg's",IF(ISNUMBER(SEARCH("Tape",J:J)),"Roll",IF(ISNUMBER(SEARCH("Thermal",J:J)),"Sqmt",IF(ISNUMBER(SEARCH("Acou",J:J)),"Sqmt",IF(ISNUMBER(SEARCH("ss",J:J)),"Kg's",IF(ISNUMBER(SEARCH("Alu",J:J)),"Kg's",IF(ISNUMBER(SEARCH("Gasket",J:J)),"Rmt",IF(ISNUMBER(SEARCH("Cleats",J:J)),"No's",IF(ISNUMBER(SEARCH("Tube",J:J)),"No's",IF(ISNUMBER(SEARCH("Bracket",J:J)),"No's",IF(ISNUMBER(SEARCH("Corner",J:J)),"No's",IF(ISNUMBER(SEARCH("MS",J:J)),"Kg's",IF(ISNUMBER(SEARCH("Bucket",J:J)),"Kg's",IF(ISNUMBER(SEARCH("stretch",J:J)),"Kg's",IF(ISNUMBER(SEARCH("Bubble",J:J)),"Roll",IF(ISNUMBER(SEARCH("JTR",J:J)),"Rmt",IF(ISNUMBER(SEARCH("Rod",J:J)),"Kg's",IF(ISNUMBER(SEARCH("Handle",J:J)),"No's",IF(ISNUMBER(SEARCH("Gear",J:J)),"No's",IF(ISNUMBER(SEARCH("Bush",J:J)),"No's","")))))))))))))))))))) -> Sqmt | L63: 528 | T63: =IF(N63="","",SUM(N63,O63,P63,Q63,R63))
A64: =IF(C64="","",COUNT($C$3:C64)) -> 62 | B64: =IF(C64="","",TEXT(C64,"mmmm")) -> December | C64: 44926 | F64: Opening stock | G64: Armasound | J64: Insu Armasound Acou. 25mm | K64: =IF(ISNUMBER(SEARCH("gsm",J:J)),"Kg's",IF(ISNUMBER(SEARCH("Tape",J:J)),"Roll",IF(ISNUMBER(SEARCH("Thermal",J:J)),"Sqmt",IF(ISNUMBER(SEARCH("Acou",J:J)),"Sqmt",IF(ISNUMBER(SEARCH("ss",J:J)),"Kg's",IF(ISNUMBER(SEARCH("Alu",J:J)),"Kg's",IF(ISNUMBER(SEARCH("Gasket",J:J)),"Rmt",IF(ISNUMBER(SEARCH("Cleats",J:J)),"No's",IF(ISNUMBER(SEARCH("Tube",J:J)),"No's",IF(ISNUMBER(SEARCH("Bracket",J:J)),"No's",IF(ISNUMBER(SEARCH("Corner",J:J)),"No's",IF(ISNUMBER(SEARCH("MS",J:J)),"Kg's",IF(ISNUMBER(SEARCH("Bucket",J:J)),"Kg's",IF(ISNUMBER(SEARCH("stretch",J:J)),"Kg's",IF(ISNUMBER(SEARCH("Bubble",J:J)),"Roll",IF(ISNUMBER(SEARCH("JTR",J:J)),"Rmt",IF(ISNUMBER(SEARCH("Rod",J:J)),"Kg's",IF(ISNUMBER(SEARCH("Handle",J:J)),"No's",IF(ISNUMBER(SEARCH("Gear",J:J)),"No's",IF(ISNUMBER(SEARCH("Bush",J:J)),"No's","")))))))))))))))))))) -> Sqmt | L64: 68 | T64: =IF(N64="","",SUM(N64,O64,P64,Q64,R64))
A65: =IF(C65="","",COUNT($C$3:C65)) -> 63 | B65: =IF(C65="","",TEXT(C65,"mmmm")) -> December | C65: 44926 | F65: Opening stock | G65: Aerocell | J65: Insu Aerocell Thermal 16mm | K65: =IF(ISNUMBER(SEARCH("gsm",J:J)),"Kg's",IF(ISNUMBER(SEARCH("Tape",J:J)),"Roll",IF(ISNUMBER(SEARCH("Thermal",J:J)),"Sqmt",IF(ISNUMBER(SEARCH("Acou",J:J)),"Sqmt",IF(ISNUMBER(SEARCH("ss",J:J)),"Kg's",IF(ISNUMBER(SEARCH("Alu",J:J)),"Kg's",IF(ISNUMBER(SEARCH("Gasket",J:J)),"Rmt",IF(ISNUMBER(SEARCH("Cleats",J:J)),"No's",IF(ISNUMBER(SEARCH("Tube",J:J)),"No's",IF(ISNUMBER(SEARCH("Bracket",J:J)),"No's",IF(ISNUMBER(SEARCH("Corner",J:J)),"No's",IF(ISNUMBER(SEARCH("MS",J:J)),"Kg's",IF(ISNUMBER(SEARCH("Bucket",J:J)),"Kg's",IF(ISNUMBER(SEARCH("stretch",J:J)),"Kg's",IF(ISNUMBER(SEARCH("Bubble",J:J)),"Roll",IF(ISNUMBER(SEARCH("JTR",J:J)),"Rmt",IF(ISNUMBER(SEARCH("Rod",J:J)),"Kg's",IF(ISNUMBER(SEARCH("Handle",J:J)),"No's",IF(ISNUMBER(SEARCH("Gear",J:J)),"No's",IF(ISNUMBER(SEARCH("Bush",J:J)),"No's","")))))))))))))))))))) -> Sqmt | L65: 60
A66: =IF(C66="","",COUNT($C$3:C66)) -> 64 | B66: =IF(C66="","",TEXT(C66,"mmmm")) -> December | C66: 44926 | F66: Opening stock | G66: Aerocell | J66: Insu Aerocell Thermal 32mm (GC-CLOTH) | K66: =IF(ISNUMBER(SEARCH("gsm",J:J)),"Kg's",IF(ISNUMBER(SEARCH("Tape",J:J)),"Roll",IF(ISNUMBER(SEARCH("Thermal",J:J)),"Sqmt",IF(ISNUMBER(SEARCH("Acou",J:J)),"Sqmt",IF(ISNUMBER(SEARCH("ss",J:J)),"Kg's",IF(ISNUMBER(SEARCH("Alu",J:J)),"Kg's",IF(ISNUMBER(SEARCH("Gasket",J:J)),"Rmt",IF(ISNUMBER(SEARCH("Cleats",J:J)),"No's",IF(ISNUMBER(SEARCH("Tube",J:J)),"No's",IF(ISNUMBER(SEARCH("Bracket",J:J)),"No's",IF(ISNUMBER(SEARCH("Corner",J:J)),"No's",IF(ISNUMBER(SEARCH("MS",J:J)),"Kg's",IF(ISNUMBER(SEARCH("Bucket",J:J)),"Kg's",IF(ISNUMBER(SEARCH("stretch",J:J)),"Kg's",IF(ISNUMBER(SEARCH("Bubble",J:J)),"Roll",IF(ISNUMBER(SEARCH("JTR",J:J)),"Rmt",IF(ISNUMBER(SEARCH("Rod",J:J)),"Kg's",IF(ISNUMBER(SEARCH("Handle",J:J)),"No's",IF(ISNUMBER(SEARCH("Gear",J:J)),"No's",IF(ISNUMBER(SEARCH("Bush",J:J)),"No's","")))))))))))))))))))) -> Sqmt | L66: 496 | T66: =IF(N66="","",SUM(N66,O66,P66,Q66,R66))
A67: =IF(C67="","",COUNT($C$3:C67)) -> 65 | B67: =IF(C67="","",TEXT(C67,"mmmm")) -> December | C67: 44926 | F67: Opening stock | G67: Aerocell | J67: Insu Aerocell Acou. 15mm | K67: =IF(ISNUMBER(SEARCH("gsm",J:J)),"Kg's",IF(ISNUMBER(SEARCH("Tape",J:J)),"Roll",IF(ISNUMBER(SEARCH("Thermal",J:J)),"Sqmt",IF(ISNUMBER(SEARCH("Acou",J:J)),"Sqmt",IF(ISNUMBER(SEARCH("ss",J:J)),"Kg's",IF(ISNUMBER(SEARCH("Alu",J:J)),"Kg's",IF(ISNUMBER(SEARCH("Gasket",J:J)),"Rmt",IF(ISNUMBER(SEARCH("Cleats",J:J)),"No's",IF(ISNUMBER(SEARCH("Tube",J:J)),"No's",IF(ISNUMBER(SEARCH("Bracket",J:J)),"No's",IF(ISNUMBER(SEARCH("Corner",J:J)),"No's",IF(ISNUMBER(SEARCH("MS",J:J)),"Kg's",IF(ISNUMBER(SEARCH("Bucket",J:J)),"Kg's",IF(ISNUMBER(SEARCH("stretch",J:J)),"Kg's",IF(ISNUMBER(SEARCH("Bubble",J:J)),"Roll",IF(ISNUMBER(SEARCH("JTR",J:J)),"Rmt",IF(ISNUMBER(SEARCH("Rod",J:J)),"Kg's",IF(ISNUMBER(SEARCH("Handle",J:J)),"No's",IF(ISNUMBER(SEARCH("Gear",J:J)),"No's",IF(ISNUMBER(SEARCH("Bush",J:J)),"No's","")))))))))))))))))))) -> Sqmt | L67: 19
A68: =IF(C68="","",COUNT($C$3:C68)) -> 66 | B68: =IF(C68="","",TEXT(C68,"mmmm")) -> April | C68: 44652 | F68: Opening stock | G68: Paramount | J68: Insu Paramount Thermal 13mm Al. Foil | K68: =IF(ISNUMBER(SEARCH("gsm",J:J)),"Kg's",IF(ISNUMBER(SEARCH("Tape",J:J)),"Roll",IF(ISNUMBER(SEARCH("Thermal",J:J)),"Sqmt",IF(ISNUMBER(SEARCH("Acou",J:J)),"Sqmt",IF(ISNUMBER(SEARCH("ss",J:J)),"Kg's",IF(ISNUMBER(SEARCH("Alu",J:J)),"Kg's",IF(ISNUMBER(SEARCH("Gasket",J:J)),"Rmt",IF(ISNUMBER(SEARCH("Cleats",J:J)),"No's",IF(ISNUMBER(SEARCH("Tube",J:J)),"No's",IF(ISNUMBER(SEARCH("Bracket",J:J)),"No's",IF(ISNUMBER(SEARCH("Corner",J:J)),"No's",IF(ISNUMBER(SEARCH("MS",J:J)),"Kg's",IF(ISNUMBER(SEARCH("Bucket",J:J)),"Kg's",IF(ISNUMBER(SEARCH("stretch",J:J)),"Kg's",IF(ISNUMBER(SEARCH("Bubble",J:J)),"Roll",IF(ISNUMBER(SEARCH("JTR",J:J)),"Rmt",IF(ISNUMBER(SEARCH("Rod",J:J)),"Kg's",IF(ISNUMBER(SEARCH("Handle",J:J)),"No's",IF(ISNUMBER(SEARCH("Gear",J:J)),"No's",IF(ISNUMBER(SEARCH("Bush",J:J)),"No's","")))))))))))))))))))) -> Sqmt | L68: 412.5 | T68: =IF(N68="","",SUM(N68,O68,P68,Q68,R68))
A69: =IF(C69="","",COUNT($C$3:C69)) -> 67 | B69: =IF(C69="","",TEXT(C69,"mmmm")) -> April | C69: 44652 | F69: Opening stock | G69: Paramount | J69: Insu Paramount Acou 10mm Al. Foil | K69: =IF(ISNUMBER(SEARCH("gsm",J:J)),"Kg's",IF(ISNUMBER(SEARCH("Tape",J:J)),"Roll",IF(ISNUMBER(SEARCH("Thermal",J:J)),"Sqmt",IF(ISNUMBER(SEARCH("Acou",J:J)),"Sqmt",IF(ISNUMBER(SEARCH("ss",J:J)),"Kg's",IF(ISNUMBER(SEARCH("Alu",J:J)),"Kg's",IF(ISNUMBER(SEARCH("Gasket",J:J)),"Rmt",IF(ISNUMBER(SEARCH("Cleats",J:J)),"No's",IF(ISNUMBER(SEARCH("Tube",J:J)),"No's",IF(ISNUMBER(SEARCH("Bracket",J:J)),"No's",IF(ISNUMBER(SEARCH("Corner",J:J)),"No's",IF(ISNUMBER(SEARCH("MS",J:J)),"Kg's",IF(ISNUMBER(SEARCH("Bucket",J:J)),"Kg's",IF(ISNUMBER(SEARCH("stretch",J:J)),"Kg's",IF(ISNUMBER(SEARCH("Bubble",J:J)),"Roll",IF(ISNUMBER(SEARCH("JTR",J:J)),"Rmt",IF(ISNUMBER(SEARCH("Rod",J:J)),"Kg's",IF(ISNUMBER(SEARCH("Handle",J:J)),"No's",IF(ISNUMBER(SEARCH("Gear",J:J)),"No's",IF(ISNUMBER(SEARCH("Bush",J:J)),"No's","")))))))))))))))))))) -> Sqmt | L69: 350 | T69: =IF(N69="","",SUM(N69,O69,P69,Q69,R69))
A70: =IF(C70="","",COUNT($C$3:C70)) -> 68 | B70: =IF(C70="","",TEXT(C70,"mmmm")) -> April | C70: 44652 | F70: Opening stock | J70: Bubble Wrap | K70: =IF(ISNUMBER(SEARCH("gsm",J:J)),"Kg's",IF(ISNUMBER(SEARCH("Tape",J:J)),"Roll",IF(ISNUMBER(SEARCH("Thermal",J:J)),"Sqmt",IF(ISNUMBER(SEARCH("Acou",J:J)),"Sqmt",IF(ISNUMBER(SEARCH("ss",J:J)),"Kg's",IF(ISNUMBER(SEARCH("Alu",J:J)),"Kg's",IF(ISNUMBER(SEARCH("Gasket",J:J)),"Rmt",IF(ISNUMBER(SEARCH("Cleats",J:J)),"No's",IF(ISNUMBER(SEARCH("Tube",J:J)),"No's",IF(ISNUMBER(SEARCH("Bracket",J:J)),"No's",IF(ISNUMBER(SEARCH("Corner",J:J)),"No's",IF(ISNUMBER(SEARCH("MS",J:J)),"Kg's",IF(ISNUMBER(SEARCH("Bucket",J:J)),"Kg's",IF(ISNUMBER(SEARCH("stretch",J:J)),"Kg's",IF(ISNUMBER(SEARCH("Bubble",J:J)),"Roll",IF(ISNUMBER(SEARCH("JTR",J:J)),"Rmt",IF(ISNUMBER(SEARCH("Rod",J:J)),"Kg's",IF(ISNUMBER(SEARCH("Handle",J:J)),"No's",IF(ISNUMBER(SEARCH("Gear",J:J)),"No's",IF(ISNUMBER(SEARCH("Bush",J:J)),"No's","")))))))))))))))))))) -> Roll | L70: 21 | T70: =IF(N70="","",SUM(N70,O70,P70,Q70,R70))
A71: =IF(C71="","",COUNT($C$3:C71)) -> 69 | B71: =IF(C71="","",TEXT(C71,"mmmm")) -> April | C71: 44652 | F71: Opening stock | J71: Stretch Film | K71: =IF(ISNUMBER(SEARCH("gsm",J:J)),"Kg's",IF(ISNUMBER(SEARCH("Tape",J:J)),"Roll",IF(ISNUMBER(SEARCH("Thermal",J:J)),"Sqmt",IF(ISNUMBER(SEARCH("Acou",J:J)),"Sqmt",IF(ISNUMBER(SEARCH("ss",J:J)),"Kg's",IF(ISNUMBER(SEARCH("Alu",J:J)),"Kg's",IF(ISNUMBER(SEARCH("Gasket",J:J)),"Rmt",IF(ISNUMBER(SEARCH("Cleats",J:J)),"No's",IF(ISNUMBER(SEARCH("Tube",J:J)),"No's",IF(ISNUMBER(SEARCH("Bracket",J:J)),"No's",IF(ISNUMBER(SEARCH("Corner",J:J)),"No's",IF(ISNUMBER(SEARCH("MS",J:J)),"Kg's",IF(ISNUMBER(SEARCH("Bucket",J:J)),"Kg's",IF(ISNUMBER(SEARCH("stretch",J:J)),"Kg's",IF(ISNUMBER(SEARCH("Bubble",J:J)),"Roll",IF(ISNUMBER(SEARCH("JTR",J:J)),"Rmt",IF(ISNUMBER(SEARCH("Rod",J:J)),"Kg's",IF(ISNUMBER(SEARCH("Handle",J:J)),"No's",IF(ISNUMBER(SEARCH("Gear",J:J)),"No's",IF(ISNUMBER(SEARCH("Bush",J:J)),"No's","")))))))))))))))))))) -> Kg's | L71: 91.8 | T71: =IF(N71="","",SUM(N71,O71,P71,Q71,R71))
A72: =IF(C72="","",COUNT($C$3:C72)) -> 70 | B72: =IF(C72="","",TEXT(C72,"mmmm")) -> April | C72: 44659 | F72: Lunia Exim Pvt Ltd | H72: 00013037 | J72: MS Angle 25x25x5mm | K72: =IF(ISNUMBER(SEARCH("gsm",J:J)),"Kg's",IF(ISNUMBER(SEARCH("Tape",J:J)),"Roll",IF(ISNUMBER(SEARCH("Thermal",J:J)),"Sqmt",IF(ISNUMBER(SEARCH("Acou",J:J)),"Sqmt",IF(ISNUMBER(SEARCH("ss",J:J)),"Kg's",IF(ISNUMBER(SEARCH("Alu",J:J)),"Kg's",IF(ISNUMBER(SEARCH("Gasket",J:J)),"Rmt",IF(ISNUMBER(SEARCH("Cleats",J:J)),"No's",IF(ISNUMBER(SEARCH("Tube",J:J)),"No's",IF(ISNUMBER(SEARCH("Bracket",J:J)),"No's",IF(ISNUMBER(SEARCH("Corner",J:J)),"No's",IF(ISNUMBER(SEARCH("MS",J:J)),"Kg's",IF(ISNUMBER(SEARCH("Bucket",J:J)),"Kg's",IF(ISNUMBER(SEARCH("stretch",J:J)),"Kg's",IF(ISNUMBER(SEARCH("Bubble",J:J)),"Roll",IF(ISNUMBER(SEARCH("JTR",J:J)),"Rmt",IF(ISNUMBER(SEARCH("Rod",J:J)),"Kg's",IF(ISNUMBER(SEARCH("Handle",J:J)),"No's",IF(ISNUMBER(SEARCH("Gear",J:J)),"No's",IF(ISNUMBER(SEARCH("Bush",J:J)),"No's","")))))))))))))))))))) -> Kg's | L72: 1000 | M72: 77 | N72: =L72*M72 -> 77000 | O72: =(N72+R72)*9% -> 7245 | P72: =(N72+R72)*9% -> 7245 | R72: 3500 | S72: =IF(R72="","",R72/(L72+L73)) -> 2.346159 | T72: =IF(N72="","",SUM(N72,O72,P72,Q72,R72)) -> 94990
A73: =IF(C73="","",COUNT($C$3:C73)) -> 71 | B73: =IF(C73="","",TEXT(C73,"mmmm")) -> April | C73: 44664 | F73: LR Multi Speciality Products | H73: 0036/22-23 | J73: Stretch Film | K73: =IF(ISNUMBER(SEARCH("gsm",J:J)),"Kg's",IF(ISNUMBER(SEARCH("Tape",J:J)),"Roll",IF(ISNUMBER(SEARCH("Thermal",J:J)),"Sqmt",IF(ISNUMBER(SEARCH("Acou",J:J)),"Sqmt",IF(ISNUMBER(SEARCH("ss",J:J)),"Kg's",IF(ISNUMBER(SEARCH("Alu",J:J)),"Kg's",IF(ISNUMBER(SEARCH("Gasket",J:J)),"Rmt",IF(ISNUMBER(SEARCH("Cleats",J:J)),"No's",IF(ISNUMBER(SEARCH("Tube",J:J)),"No's",IF(ISNUMBER(SEARCH("Bracket",J:J)),"No's",IF(ISNUMBER(SEARCH("Corner",J:J)),"No's",IF(ISNUMBER(SEARCH("MS",J:J)),"Kg's",IF(ISNUMBER(SEARCH("Bucket",J:J)),"Kg's",IF(ISNUMBER(SEARCH("stretch",J:J)),"Kg's",IF(ISNUMBER(SEARCH("Bubble",J:J)),"Roll",IF(ISNUMBER(SEARCH("JTR",J:J)),"Rmt",IF(ISNUMBER(SEARCH("Rod",J:J)),"Kg's",IF(ISNUMBER(SEARCH("Handle",J:J)),"No's",IF(ISNUMBER(SEARCH("Gear",J:J)),"No's",IF(ISNUMBER(SEARCH("Bush",J:J)),"No's","")))))))))))))))))))) -> Kg's | L73: 491.8 | M73: 155 | N73: =L73*M73 -> 76229 | O73: =(N73+R73)*9% -> 6860.61 | P73: =(N73+R73)*9% -> 6860.61 | T73: =IF(N73="","",SUM(N73,O73,P73,Q73,R73)) -> 89950.22
A74: =IF(C74="","",COUNT($C$3:C74)) -> 72 | B74: =IF(C74="","",TEXT(C74,"mmmm")) -> April | C74: 44671 | F74: Kothari Metals | G74: JSW | H74: KM/02309/2022-23 | J74: 120gsm 22G | K74: =IF(ISNUMBER(SEARCH("gsm",J:J)),"Kg's",IF(ISNUMBER(SEARCH("Tape",J:J)),"Roll",IF(ISNUMBER(SEARCH("Thermal",J:J)),"Sqmt",IF(ISNUMBER(SEARCH("Acou",J:J)),"Sqmt",IF(ISNUMBER(SEARCH("ss",J:J)),"Kg's",IF(ISNUMBER(SEARCH("Alu",J:J)),"Kg's",IF(ISNUMBER(SEARCH("Gasket",J:J)),"Rmt",IF(ISNUMBER(SEARCH("Cleats",J:J)),"No's",IF(ISNUMBER(SEARCH("Tube",J:J)),"No's",IF(ISNUMBER(SEARCH("Bracket",J:J)),"No's",IF(ISNUMBER(SEARCH("Corner",J:J)),"No's",IF(ISNUMBER(SEARCH("MS",J:J)),"Kg's",IF(ISNUMBER(SEARCH("Bucket",J:J)),"Kg's",IF(ISNUMBER(SEARCH("stretch",J:J)),"Kg's",IF(ISNUMBER(SEARCH("Bubble",J:J)),"Roll",IF(ISNUMBER(SEARCH("JTR",J:J)),"Rmt",IF(ISNUMBER(SEARCH("Rod",J:J)),"Kg's",IF(ISNUMBER(SEARCH("Handle",J:J)),"No's",IF(ISNUMBER(SEARCH("Gear",J:J)),"No's",IF(ISNUMBER(SEARCH("Bush",J:J)),"No's","")))))))))))))))))))) -> Kg's | L74: 5200 | M74: 104.75057 | N74: =L74*M74 -> 544702.96 | O74: =(N74+R74)*9% -> 49023.267 | P74: =(N74+R74)*9% -> 49023.267 | S74: =IF(R74="","",R74/(L74+L75)) | T74: =IF(N74="","",SUM(N74,O74,P74,Q74,R74)) -> 642749.5
A75: =IF(C75="","",COUNT($C$3:C75)) -> 73 | B75: =IF(C75="","",TEXT(C75,"mmmm")) -> April | C75: 44676 | F75: Kothari Metals | G75: JSW | H75: KM/02317/2022-23 | J75: 120gsm 22G | K75: =IF(ISNUMBER(SEARCH("gsm",J:J)),"Kg's",IF(ISNUMBER(SEARCH("Tape",J:J)),"Roll",IF(ISNUMBER(SEARCH("Thermal",J:J)),"Sqmt",IF(ISNUMBER(SEARCH("Acou",J:J)),"Sqmt",IF(ISNUMBER(SEARCH("ss",J:J)),"Kg's",IF(ISNUMBER(SEARCH("Alu",J:J)),"Kg's",IF(ISNUMBER(SEARCH("Gasket",J:J)),"Rmt",IF(ISNUMBER(SEARCH("Cleats",J:J)),"No's",IF(ISNUMBER(SEARCH("Tube",J:J)),"No's",IF(ISNUMBER(SEARCH("Bracket",J:J)),"No's",IF(ISNUMBER(SEARCH("Corner",J:J)),"No's",IF(ISNUMBER(SEARCH("MS",J:J)),"Kg's",IF(ISNUMBER(SEARCH("Bucket",J:J)),"Kg's",IF(ISNUMBER(SEARCH("stretch",J:J)),"Kg's",IF(ISNUMBER(SEARCH("Bubble",J:J)),"Roll",IF(ISNUMBER(SEARCH("JTR",J:J)),"Rmt",IF(ISNUMBER(SEARCH("Rod",J:J)),"Kg's",IF(ISNUMBER(SEARCH("Handle",J:J)),"No's",IF(ISNUMBER(SEARCH("Gear",J:J)),"No's",IF(ISNUMBER(SEARCH("Bush",J:J)),"No's","")))))))))))))))))))) -> Kg's | L75: 5050 | M75: 104.75057 | N75: =L75*M75 -> 528990.38 | O75: =(N75+R75)*9% -> 47609.134 | P75: =(N75+R75)*9% -> 47609.134 | S75: =IF(R75="","",R75/(L75+#REF!)) | T75: =IF(N75="","",SUM(N75,O75,P75,Q75,R75)) -> 624208.65
A76: =IF(C76="","",COUNT($C$3:C76)) -> 74 | B76: =IF(C76="","",TEXT(C76,"mmmm")) -> July | C76: 44764 | F76: Kothari Metals | G76: JSW | H76: KM/02552/2022-23 | I76: 012/22-23 | J76: 120gsm 22G | K76: =IF(ISNUMBER(SEARCH("gsm",J:J)),"Kg's",IF(ISNUMBER(SEARCH("Tape",J:J)),"Roll",IF(ISNUMBER(SEARCH("Thermal",J:J)),"Sqmt",IF(ISNUMBER(SEARCH("Acou",J:J)),"Sqmt",IF(ISNUMBER(SEARCH("ss",J:J)),"Kg's",IF(ISNUMBER(SEARCH("Alu",J:J)),"Kg's",IF(ISNUMBER(SEARCH("Gasket",J:J)),"Rmt",IF(ISNUMBER(SEARCH("Cleats",J:J)),"No's",IF(ISNUMBER(SEARCH("Tube",J:J)),"No's",IF(ISNUMBER(SEARCH("Bracket",J:J)),"No's",IF(ISNUMBER(SEARCH("Corner",J:J)),"No's",IF(ISNUMBER(SEARCH("MS",J:J)),"Kg's",IF(ISNUMBER(SEARCH("Bucket",J:J)),"Kg's",IF(ISNUMBER(SEARCH("stretch",J:J)),"Kg's",IF(ISNUMBER(SEARCH("Bubble",J:J)),"Roll",IF(ISNUMBER(SEARCH("JTR",J:J)),"Rmt",IF(ISNUMBER(SEARCH("Rod",J:J)),"Kg's",IF(ISNUMBER(SEARCH("Handle",J:J)),"No's",IF(ISNUMBER(SEARCH("Gear",J:J)),"No's",IF(ISNUMBER(SEARCH("Bush",J:J)),"No's","")))))))))))))))))))) -> Kg's | L76: 9770 | M76: 81 | N76: =L76*M76 -> 791370 | O76: =(N76+R76)*9% -> 71855.1 | P76: =(N76+R76)*9% -> 71855.1 | R76: 7020 | S76: =IF(R76="","",R76/(L76+L77)) -> 0.51110302 | T76: =IF(N76="","",SUM(N76,O76,P76,Q76,R76)) -> 942100.2
A77: =IF(C77="","",COUNT($C$3:C77)) -> 75 | B77: =IF(C77="","",TEXT(C77,"mmmm")) -> August | C77: 44778 | F77: Kothari Metals | G77: JSW | H77: KM/02595/2022-23 | I77: 016/22-23 | J77: 120gsm 24G | K77: =IF(ISNUMBER(SEARCH("gsm",J:J)),"Kg's",IF(ISNUMBER(SEARCH("Tape",J:J)),"Roll",IF(ISNUMBER(SEARCH("Thermal",J:J)),"Sqmt",IF(ISNUMBER(SEARCH("Acou",J:J)),"Sqmt",IF(ISNUMBER(SEARCH("ss",J:J)),"Kg's",IF(ISNUMBER(SEARCH("Alu",J:J)),"Kg's",IF(ISNUMBER(SEARCH("Gasket",J:J)),"Rmt",IF(ISNUMBER(SEARCH("Cleats",J:J)),"No's",IF(ISNUMBER(SEARCH("Tube",J:J)),"No's",IF(ISNUMBER(SEARCH("Bracket",J:J)),"No's",IF(ISNUMBER(SEARCH("Corner",J:J)),"No's",IF(ISNUMBER(SEARCH("MS",J:J)),"Kg's",IF(ISNUMBER(SEARCH("Bucket",J:J)),"Kg's",IF(ISNUMBER(SEARCH("stretch",J:J)),"Kg's",IF(ISNUMBER(SEARCH("Bubble",J:J)),"Roll",IF(ISNUMBER(SEARCH("JTR",J:J)),"Rmt",IF(ISNUMBER(SEARCH("Rod",J:J)),"Kg's",IF(ISNUMBER(SEARCH("Handle",J:J)),"No's",IF(ISNUMBER(SEARCH("Gear",J:J)),"No's",IF(ISNUMBER(SEARCH("Bush",J:J)),"No's","")))))))))))))))))))) -> Kg's | L77: 3965 | M77: 79 | N77: =L77*M77 -> 313235 | O77: =(N77+R77)*9% -> 28191.15 | P77: =(N77+R77)*9% -> 28191.15 | S77: =IF(R77="","",R77/(L77+L78)) | T77: =IF(N77="","",SUM(N77,O77,P77,Q77,R77)) -> 369617.3
A78: =IF(C78="","",COUNT($C$3:C78)) -> 76 | B78: =IF(C78="","",TEXT(C78,"mmmm")) -> August | C78: 44778 | F78: Kothari Metals | G78: JSW | H78: KM/02595/2022-23 | I78: 016/22-23 | J78: 120gsm 22G | K78: =IF(ISNUMBER(SEARCH("gsm",J:J)),"Kg's",IF(ISNUMBER(SEARCH("Tape",J:J)),"Roll",IF(ISNUMBER(SEARCH("Thermal",J:J)),"Sqmt",IF(ISNUMBER(SEARCH("Acou",J:J)),"Sqmt",IF(ISNUMBER(SEARCH("ss",J:J)),"Kg's",IF(ISNUMBER(SEARCH("Alu",J:J)),"Kg's",IF(ISNUMBER(SEARCH("Gasket",J:J)),"Rmt",IF(ISNUMBER(SEARCH("Cleats",J:J)),"No's",IF(ISNUMBER(SEARCH("Tube",J:J)),"No's",IF(ISNUMBER(SEARCH("Bracket",J:J)),"No's",IF(ISNUMBER(SEARCH("Corner",J:J)),"No's",IF(ISNUMBER(SEARCH("MS",J:J)),"Kg's",IF(ISNUMBER(SEARCH("Bucket",J:J)),"Kg's",IF(ISNUMBER(SEARCH("stretch",J:J)),"Kg's",IF(ISNUMBER(SEARCH("Bubble",J:J)),"Roll",IF(ISNUMBER(SEARCH("JTR",J:J)),"Rmt",IF(ISNUMBER(SEARCH("Rod",J:J)),"Kg's",IF(ISNUMBER(SEARCH("Handle",J:J)),"No's",IF(ISNUMBER(SEARCH("Gear",J:J)),"No's",IF(ISNUMBER(SEARCH("Bush",J:J)),"No's","")))))))))))))))))))) -> Kg's | L78: 25402 | M78: 78 | N78: =L78*M78 -> 1981356 | O78: =(N78+R78)*9% -> 178322.04 | P78: =(N78+R78)*9% -> 178322.04 | S78: =IF(R78="","",R78/(L78+L79)) | T78: =IF(N78="","",SUM(N78,O78,P78,Q78,R78)) -> 2338000.1
A79: =IF(C79="","",COUNT($C$3:C79)) -> 77 | B79: =IF(C79="","",TEXT(C79,"mmmm")) -> August | C79: 44778 | F79: Kothari Metals | G79: JSW | H79: KM/02595/2022-23 | I79: 016/22-23 | J79: 120gsm 20G | K79: =IF(ISNUMBER(SEARCH("gsm",J:J)),"Kg's",IF(ISNUMBER(SEARCH("Tape",J:J)),"Roll",IF(ISNUMBER(SEARCH("Thermal",J:J)),"Sqmt",IF(ISNUMBER(SEARCH("Acou",J:J)),"Sqmt",IF(ISNUMBER(SEARCH("ss",J:J)),"Kg's",IF(ISNUMBER(SEARCH("Alu",J:J)),"Kg's",IF(ISNUMBER(SEARCH("Gasket",J:J)),"Rmt",IF(ISNUMBER(SEARCH("Cleats",J:J)),"No's",IF(ISNUMBER(SEARCH("Tube",J:J)),"No's",IF(ISNUMBER(SEARCH("Bracket",J:J)),"No's",IF(ISNUMBER(SEARCH("Corner",J:J)),"No's",IF(ISNUMBER(SEARCH("MS",J:J)),"Kg's",IF(ISNUMBER(SEARCH("Bucket",J:J)),"Kg's",IF(ISNUMBER(SEARCH("stretch",J:J)),"Kg's",IF(ISNUMBER(SEARCH("Bubble",J:J)),"Roll",IF(ISNUMBER(SEARCH("JTR",J:J)),"Rmt",IF(ISNUMBER(SEARCH("Rod",J:J)),"Kg's",IF(ISNUMBER(SEARCH("Handle",J:J)),"No's",IF(ISNUMBER(SEARCH("Gear",J:J)),"No's",IF(ISNUMBER(SEARCH("Bush",J:J)),"No's","")))))))))))))))))))) -> Kg's | L79: 4520 | M79: 78 | N79: =L79*M79 -> 352560 | O79: =(N79+R79)*9% -> 31730.4 | P79: =(N79+R79)*9% -> 31730.4 | S79: =IF(R79="","",R79/(L79+L80)) | T79: =IF(N79="","",SUM(N79,O79,P79,Q79,R79)) -> 416020.8
A80: =IF(C80="","",COUNT($C$3:C80)) -> 78 | B80: =IF(C80="","",TEXT(C80,"mmmm")) -> August | C80: 44778 | F80: Kothari Metals | G80: JSW | H80: KM/02595/2022-23 | I80: 016/22-23 | J80: 120gsm 18G | K80: =IF(ISNUMBER(SEARCH("gsm",J:J)),"Kg's",IF(ISNUMBER(SEARCH("Tape",J:J)),"Roll",IF(ISNUMBER(SEARCH("Thermal",J:J)),"Sqmt",IF(ISNUMBER(SEARCH("Acou",J:J)),"Sqmt",IF(ISNUMBER(SEARCH("ss",J:J)),"Kg's",IF(ISNUMBER(SEARCH("Alu",J:J)),"Kg's",IF(ISNUMBER(SEARCH("Gasket",J:J)),"Rmt",IF(ISNUMBER(SEARCH("Cleats",J:J)),"No's",IF(ISNUMBER(SEARCH("Tube",J:J)),"No's",IF(ISNUMBER(SEARCH("Bracket",J:J)),"No's",IF(ISNUMBER(SEARCH("Corner",J:J)),"No's",IF(ISNUMBER(SEARCH("MS",J:J)),"Kg's",IF(ISNUMBER(SEARCH("Bucket",J:J)),"Kg's",IF(ISNUMBER(SEARCH("stretch",J:J)),"Kg's",IF(ISNUMBER(SEARCH("Bubble",J:J)),"Roll",IF(ISNUMBER(SEARCH("JTR",J:J)),"Rmt",IF(ISNUMBER(SEARCH("Rod",J:J)),"Kg's",IF(ISNUMBER(SEARCH("Handle",J:J)),"No's",IF(ISNUMBER(SEARCH("Gear",J:J)),"No's",IF(ISNUMBER(SEARCH("Bush",J:J)),"No's","")))))))))))))))))))) -> Kg's | L80: 5195 | M80: 78 | N80: =L80*M80 -> 405210 | O80: =(N80+R80)*9% -> 36468.9 | P80: =(N80+R80)*9% -> 36468.9 | S80: =IF(R80="","",R80/(L80+L81)) | T80: =IF(N80="","",SUM(N80,O80,P80,Q80,R80)) -> 478147.8
A81: =IF(C81="","",COUNT($C$3:C81)) -> 79 | B81: =IF(C81="","",TEXT(C81,"mmmm")) -> August | C81: 44781 | F81: Kothari Metals | G81: JSW | H81: KM/02609/2022-23 | I81: 017/22-23 | J81: 120gsm 24G | K81: =IF(ISNUMBER(SEARCH("gsm",J:J)),"Kg's",IF(ISNUMBER(SEARCH("Tape",J:J)),"Roll",IF(ISNUMBER(SEARCH("Thermal",J:J)),"Sqmt",IF(ISNUMBER(SEARCH("Acou",J:J)),"Sqmt",IF(ISNUMBER(SEARCH("ss",J:J)),"Kg's",IF(ISNUMBER(SEARCH("Alu",J:J)),"Kg's",IF(ISNUMBER(SEARCH("Gasket",J:J)),"Rmt",IF(ISNUMBER(SEARCH("Cleats",J:J)),"No's",IF(ISNUMBER(SEARCH("Tube",J:J)),"No's",IF(ISNUMBER(SEARCH("Bracket",J:J)),"No's",IF(ISNUMBER(SEARCH("Corner",J:J)),"No's",IF(ISNUMBER(SEARCH("MS",J:J)),"Kg's",IF(ISNUMBER(SEARCH("Bucket",J:J)),"Kg's",IF(ISNUMBER(SEARCH("stretch",J:J)),"Kg's",IF(ISNUMBER(SEARCH("Bubble",J:J)),"Roll",IF(ISNUMBER(SEARCH("JTR",J:J)),"Rmt",IF(ISNUMBER(SEARCH("Rod",J:J)),"Kg's",IF(ISNUMBER(SEARCH("Handle",J:J)),"No's",IF(ISNUMBER(SEARCH("Gear",J:J)),"No's",IF(ISNUMBER(SEARCH("Bush",J:J)),"No's","")))))))))))))))))))) -> Kg's | L81: 26104 | M81: 79 | N81: =L81*M81 -> 2062216 | O81: =(N81+R81)*9% -> 185599.44 | P81: =(N81+R81)*9% -> 185599.44 | S81: =IF(R81="","",R81/(L81+L82)) | T81: =IF(N81="","",SUM(N81,O81,P81,Q81,R81)) -> 2433414.9
A82: =IF(C82="","",COUNT($C$3:C82)) -> 80 | B82: =IF(C82="","",TEXT(C82,"mmmm")) -> August | C82: 44781 | F82: Kothari Metals | G82: JSW | H82: KM/02609/2022-23 | I82: 017/22-23 | J82: 120gsm 20G | K82: =IF(ISNUMBER(SEARCH("gsm",J:J)),"Kg's",IF(ISNUMBER(SEARCH("Tape",J:J)),"Roll",IF(ISNUMBER(SEARCH("Thermal",J:J)),"Sqmt",IF(ISNUMBER(SEARCH("Acou",J:J)),"Sqmt",IF(ISNUMBER(SEARCH("ss",J:J)),"Kg's",IF(ISNUMBER(SEARCH("Alu",J:J)),"Kg's",IF(ISNUMBER(SEARCH("Gasket",J:J)),"Rmt",IF(ISNUMBER(SEARCH("Cleats",J:J)),"No's",IF(ISNUMBER(SEARCH("Tube",J:J)),"No's",IF(ISNUMBER(SEARCH("Bracket",J:J)),"No's",IF(ISNUMBER(SEARCH("Corner",J:J)),"No's",IF(ISNUMBER(SEARCH("MS",J:J)),"Kg's",IF(ISNUMBER(SEARCH("Bucket",J:J)),"Kg's",IF(ISNUMBER(SEARCH("stretch",J:J)),"Kg's",IF(ISNUMBER(SEARCH("Bubble",J:J)),"Roll",IF(ISNUMBER(SEARCH("JTR",J:J)),"Rmt",IF(ISNUMBER(SEARCH("Rod",J:J)),"Kg's",IF(ISNUMBER(SEARCH("Handle",J:J)),"No's",IF(ISNUMBER(SEARCH("Gear",J:J)),"No's",IF(ISNUMBER(SEARCH("Bush",J:J)),"No's","")))))))))))))))))))) -> Kg's | L82: 4076 | M82: 78 | N82: =L82*M82 -> 317928 | O82: =(N82+R82)*9% -> 28613.52 | P82: =(N82+R82)*9% -> 28613.52 | S82: =IF(R82="","",R82/(L82)) | T82: =IF(N82="","",SUM(N82,O82,P82,Q82,R82)) -> 375155.04
A83: =IF(C83="","",COUNT($C$3:C83)) -> 81 | B83: =IF(C83="","",TEXT(C83,"mmmm")) -> August | C83: 44781 | F83: Kothari Metals | G83: JSW | H83: KM/02610/2022-23 | I83: 018/22-23 | J83: 120gsm 24G | K83: =IF(ISNUMBER(SEARCH("gsm",J:J)),"Kg's",IF(ISNUMBER(SEARCH("Tape",J:J)),"Roll",IF(ISNUMBER(SEARCH("Thermal",J:J)),"Sqmt",IF(ISNUMBER(SEARCH("Acou",J:J)),"Sqmt",IF(ISNUMBER(SEARCH("ss",J:J)),"Kg's",IF(ISNUMBER(SEARCH("Alu",J:J)),"Kg's",IF(ISNUMBER(SEARCH("Gasket",J:J)),"Rmt",IF(ISNUMBER(SEARCH("Cleats",J:J)),"No's",IF(ISNUMBER(SEARCH("Tube",J:J)),"No's",IF(ISNUMBER(SEARCH("Bracket",J:J)),"No's",IF(ISNUMBER(SEARCH("Corner",J:J)),"No's",IF(ISNUMBER(SEARCH("MS",J:J)),"Kg's",IF(ISNUMBER(SEARCH("Bucket",J:J)),"Kg's",IF(ISNUMBER(SEARCH("stretch",J:J)),"Kg's",IF(ISNUMBER(SEARCH("Bubble",J:J)),"Roll",IF(ISNUMBER(SEARCH("JTR",J:J)),"Rmt",IF(ISNUMBER(SEARCH("Rod",J:J)),"Kg's",IF(ISNUMBER(SEARCH("Handle",J:J)),"No's",IF(ISNUMBER(SEARCH("Gear",J:J)),"No's",IF(ISNUMBER(SEARCH("Bush",J:J)),"No's","")))))))))))))))))))) -> Kg's | L83: 19716 | M83: 79 | N83: =L83*M83 -> 1557564 | O83: =(N83+R83)*9% -> 140180.76 | P83: =(N83+R83)*9% -> 140180.76 | S83: =IF(R83="","",R83/(L83)) | T83: =IF(N83="","",SUM(N83,O83,P83,Q83,R83)) -> 1837925.5
A84: =IF(C84="","",COUNT($C$3:C84)) -> 82 | B84: =IF(C84="","",TEXT(C84,"mmmm")) -> August | C84: 44781 | F84: Kothari Metals | G84: JSW | H84: KM/02610/2022-23 | I84: 018/22-23 | J84: 120gsm Slit 20G | K84: =IF(ISNUMBER(SEARCH("gsm",J:J)),"Kg's",IF(ISNUMBER(SEARCH("Tape",J:J)),"Roll",IF(ISNUMBER(SEARCH("Thermal",J:J)),"Sqmt",IF(ISNUMBER(SEARCH("Acou",J:J)),"Sqmt",IF(ISNUMBER(SEARCH("ss",J:J)),"Kg's",IF(ISNUMBER(SEARCH("Alu",J:J)),"Kg's",IF(ISNUMBER(SEARCH("Gasket",J:J)),"Rmt",IF(ISNUMBER(SEARCH("Cleats",J:J)),"No's",IF(ISNUMBER(SEARCH("Tube",J:J)),"No's",IF(ISNUMBER(SEARCH("Bracket",J:J)),"No's",IF(ISNUMBER(SEARCH("Corner",J:J)),"No's",IF(ISNUMBER(SEARCH("MS",J:J)),"Kg's",IF(ISNUMBER(SEARCH("Bucket",J:J)),"Kg's",IF(ISNUMBER(SEARCH("stretch",J:J)),"Kg's",IF(ISNUMBER(SEARCH("Bubble",J:J)),"Roll",IF(ISNUMBER(SEARCH("JTR",J:J)),"Rmt",IF(ISNUMBER(SEARCH("Rod",J:J)),"Kg's",IF(ISNUMBER(SEARCH("Handle",J:J)),"No's",IF(ISNUMBER(SEARCH("Gear",J:J)),"No's",IF(ISNUMBER(SEARCH("Bush",J:J)),"No's","")))))))))))))))))))) -> Kg's | L84: 4984 | M84: 79 | N84: =L84*M84 -> 393736 | O84: =(N84+R84)*9% -> 35436.24 | P84: =(N84+R84)*9% -> 35436.24 | S84: =IF(R84="","",R84/(L84+L85)) | T84: =IF(N84="","",SUM(N84,O84,P84,Q84,R84)) -> 464608.48
A85: =IF(C85="","",COUNT($C$3:C85)) -> 83 | B85: =IF(C85="","",TEXT(C85,"mmmm")) -> August | C85: 44785 | F85: LR Multi Speciality Products | H85: LRM/0442/22-23 | I85: 019/22-23 | J85: Stretch Film | K85: =IF(ISNUMBER(SEARCH("gsm",J:J)),"Kg's",IF(ISNUMBER(SEARCH("Tape",J:J)),"Roll",IF(ISNUMBER(SEARCH("Thermal",J:J)),"Sqmt",IF(ISNUMBER(SEARCH("Acou",J:J)),"Sqmt",IF(ISNUMBER(SEARCH("ss",J:J)),"Kg's",IF(ISNUMBER(SEARCH("Alu",J:J)),"Kg's",IF(ISNUMBER(SEARCH("Gasket",J:J)),"Rmt",IF(ISNUMBER(SEARCH("Cleats",J:J)),"No's",IF(ISNUMBER(SEARCH("Tube",J:J)),"No's",IF(ISNUMBER(SEARCH("Bracket",J:J)),"No's",IF(ISNUMBER(SEARCH("Corner",J:J)),"No's",IF(ISNUMBER(SEARCH("MS",J:J)),"Kg's",IF(ISNUMBER(SEARCH("Bucket",J:J)),"Kg's",IF(ISNUMBER(SEARCH("stretch",J:J)),"Kg's",IF(ISNUMBER(SEARCH("Bubble",J:J)),"Roll",IF(ISNUMBER(SEARCH("JTR",J:J)),"Rmt",IF(ISNUMBER(SEARCH("Rod",J:J)),"Kg's",IF(ISNUMBER(SEARCH("Handle",J:J)),"No's",IF(ISNUMBER(SEARCH("Gear",J:J)),"No's",IF(ISNUMBER(SEARCH("Bush",J:J)),"No's","")))))))))))))))))))) -> Kg's | L85: 304.54 | M85: 145 | N85: =L85*M85 -> 44158.3 | O85: =(N85+R85)*9% -> 3974.247 | P85: =(N85+R85)*9% -> 3974.247 | S85: =IF(R85="","",R85/(L85+L86)) | T85: =IF(N85="","",SUM(N85,O85,P85,Q85,R85)) -> 52106.794
A86: =IF(C86="","",COUNT($C$3:C86)) -> 84 | B86: =IF(C86="","",TEXT(C86,"mmmm")) -> August | C86: 44786 | F86: Kothari Metals | H86: KM/02626/2022-23 | I86: 020/22-23 | J86: MS Angle 25x25x5mm | K86: =IF(ISNUMBER(SEARCH("gsm",J:J)),"Kg's",IF(ISNUMBER(SEARCH("Tape",J:J)),"Roll",IF(ISNUMBER(SEARCH("Thermal",J:J)),"Sqmt",IF(ISNUMBER(SEARCH("Acou",J:J)),"Sqmt",IF(ISNUMBER(SEARCH("ss",J:J)),"Kg's",IF(ISNUMBER(SEARCH("Alu",J:J)),"Kg's",IF(ISNUMBER(SEARCH("Gasket",J:J)),"Rmt",IF(ISNUMBER(SEARCH("Cleats",J:J)),"No's",IF(ISNUMBER(SEARCH("Tube",J:J)),"No's",IF(ISNUMBER(SEARCH("Bracket",J:J)),"No's",IF(ISNUMBER(SEARCH("Corner",J:J)),"No's",IF(ISNUMBER(SEARCH("MS",J:J)),"Kg's",IF(ISNUMBER(SEARCH("Bucket",J:J)),"Kg's",IF(ISNUMBER(SEARCH("stretch",J:J)),"Kg's",IF(ISNUMBER(SEARCH("Bubble",J:J)),"Roll",IF(ISNUMBER(SEARCH("JTR",J:J)),"Rmt",IF(ISNUMBER(SEARCH("Rod",J:J)),"Kg's",IF(ISNUMBER(SEARCH("Handle",J:J)),"No's",IF(ISNUMBER(SEARCH("Gear",J:J)),"No's",IF(ISNUMBER(SEARCH("Bush",J:J)),"No's","")))))))))))))))))))) -> Kg's | L86: 2003 | M86: 67 | N86: =L86*M86 -> 134201 | O86: =(N86+R86)*9% -> 12628.62 | P86: =(N86+R86)*9% -> 12628.62 | R86: 6117 | S86: =IF(R86="","",R86/(L86+L87)) -> 0.22653039 | T86: =IF(N86="","",SUM(N86,O86,P86,Q86,R86)) -> 165575.24
A87: =IF(C87="","",COUNT($C$3:C87)) -> 85 | B87: =IF(C87="","",TEXT(C87,"mmmm")) -> August | C87: 44781 | F87: HR Precisoins | H87: HRP/0187/22-23 | I87: 021/22-23 | J87: Corner 32mm | K87: =IF(ISNUMBER(SEARCH("gsm",J:J)),"Kg's",IF(ISNUMBER(SEARCH("Tape",J:J)),"Roll",IF(ISNUMBER(SEARCH("Thermal",J:J)),"Sqmt",IF(ISNUMBER(SEARCH("Acou",J:J)),"Sqmt",IF(ISNUMBER(SEARCH("ss",J:J)),"Kg's",IF(ISNUMBER(SEARCH("Alu",J:J)),"Kg's",IF(ISNUMBER(SEARCH("Gasket",J:J)),"Rmt",IF(ISNUMBER(SEARCH("Cleats",J:J)),"No's",IF(ISNUMBER(SEARCH("Tube",J:J)),"No's",IF(ISNUMBER(SEARCH("Bracket",J:J)),"No's",IF(ISNUMBER(SEARCH("Corner",J:J)),"No's",IF(ISNUMBER(SEARCH("MS",J:J)),"Kg's",IF(ISNUMBER(SEARCH("Bucket",J:J)),"Kg's",IF(ISNUMBER(SEARCH("stretch",J:J)),"Kg's",IF(ISNUMBER(SEARCH("Bubble",J:J)),"Roll",IF(ISNUMBER(SEARCH("JTR",J:J)),"Rmt",IF(ISNUMBER(SEARCH("Rod",J:J)),"Kg's",IF(ISNUMBER(SEARCH("Handle",J:J)),"No's",IF(ISNUMBER(SEARCH("Gear",J:J)),"No's",IF(ISNUMBER(SEARCH("Bush",J:J)),"No's","")))))))))))))))))))) -> No's | L87: 25000 | M87: 8 | N87: =L87*M87 -> 200000 | O87: =(N87+R87)*9% -> 18000 | P87: =(N87+R87)*9% -> 18000 | S87: =IF(R87="","",R87/(L87+#REF!)) | T87: =IF(N87="","",SUM(N87,O87,P87,Q87,R87)) -> 236000
A88: =IF(C88="","",COUNT($C$3:C88)) -> 86 | B88: =IF(C88="","",TEXT(C88,"mmmm")) -> August | C88: 44802 | F88: HR Precisoins | H88: HRP/0227/22-23 | I88: 031/22-23 | J88: Corner 32mm | K88: =IF(ISNUMBER(SEARCH("gsm",J:J)),"Kg's",IF(ISNUMBER(SEARCH("Tape",J:J)),"Roll",IF(ISNUMBER(SEARCH("Thermal",J:J)),"Sqmt",IF(ISNUMBER(SEARCH("Acou",J:J)),"Sqmt",IF(ISNUMBER(SEARCH("ss",J:J)),"Kg's",IF(ISNUMBER(SEARCH("Alu",J:J)),"Kg's",IF(ISNUMBER(SEARCH("Gasket",J:J)),"Rmt",IF(ISNUMBER(SEARCH("Cleats",J:J)),"No's",IF(ISNUMBER(SEARCH("Tube",J:J)),"No's",IF(ISNUMBER(SEARCH("Bracket",J:J)),"No's",IF(ISNUMBER(SEARCH("Corner",J:J)),"No's",IF(ISNUMBER(SEARCH("MS",J:J)),"Kg's",IF(ISNUMBER(SEARCH("Bucket",J:J)),"Kg's",IF(ISNUMBER(SEARCH("stretch",J:J)),"Kg's",IF(ISNUMBER(SEARCH("Bubble",J:J)),"Roll",IF(ISNUMBER(SEARCH("JTR",J:J)),"Rmt",IF(ISNUMBER(SEARCH("Rod",J:J)),"Kg's",IF(ISNUMBER(SEARCH("Handle",J:J)),"No's",IF(ISNUMBER(SEARCH("Gear",J:J)),"No's",IF(ISNUMBER(SEARCH("Bush",J:J)),"No's","")))))))))))))))))))) -> No's | L88: 25000 | M88: 8 | N88: =L88*M88 -> 200000 | O88: =(N88+R88)*9% -> 18000 | P88: =(N88+R88)*9% -> 18000 | S88: =IF(R88="","",R88/(L88+L89)) | T88: =IF(N88="","",SUM(N88,O88,P88,Q88,R88)) -> 236000
A89: =IF(C89="","",COUNT($C$3:C89)) -> 87 | B89: =IF(C89="","",TEXT(C89,"mmmm")) -> September | C89: 44821 | D89: 925 | E89: 44814 | F89: JR & Co | G89: JSW | H89: 41530 | I89: 042/22-23 | J89: 120gsm 24G | K89: =IF(ISNUMBER(SEARCH("gsm",J:J)),"Kg's",IF(ISNUMBER(SEARCH("Tape",J:J)),"Roll",IF(ISNUMBER(SEARCH("Thermal",J:J)),"Sqmt",IF(ISNUMBER(SEARCH("Acou",J:J)),"Sqmt",IF(ISNUMBER(SEARCH("ss",J:J)),"Kg's",IF(ISNUMBER(SEARCH("Alu",J:J)),"Kg's",IF(ISNUMBER(SEARCH("Gasket",J:J)),"Rmt",IF(ISNUMBER(SEARCH("Cleats",J:J)),"No's",IF(ISNUMBER(SEARCH("Tube",J:J)),"No's",IF(ISNUMBER(SEARCH("Bracket",J:J)),"No's",IF(ISNUMBER(SEARCH("Corner",J:J)),"No's",IF(ISNUMBER(SEARCH("MS",J:J)),"Kg's",IF(ISNUMBER(SEARCH("Bucket",J:J)),"Kg's",IF(ISNUMBER(SEARCH("stretch",J:J)),"Kg's",IF(ISNUMBER(SEARCH("Bubble",J:J)),"Roll",IF(ISNUMBER(SEARCH("JTR",J:J)),"Rmt",IF(ISNUMBER(SEARCH("Rod",J:J)),"Kg's",IF(ISNUMBER(SEARCH("Handle",J:J)),"No's",IF(ISNUMBER(SEARCH("Gear",J:J)),"No's",IF(ISNUMBER(SEARCH("Bush",J:J)),"No's","")))))))))))))))))))) -> Kg's | L89: 6210 | M89: 78.5 | N89: =L89*M89 -> 487485 | O89: =(N89+R89)*9% -> 44260.65 | P89: =(N89+R89)*9% -> 44260.65 | R89: 4300 | S89: =IF(R89="","",R89/(L89+90)) -> 0.68253968 | T89: =IF(N89="","",SUM(N89,O89,P89,Q89,R89)) -> 580306.3
A90: =IF(C90="","",COUNT($C$3:C90)) -> 88 | B90: =IF(C90="","",TEXT(C90,"mmmm")) -> September | C90: 44823 | D90: 925 | E90: 44814 | F90: JR & Co | G90: JSW | H90: 41541 | I90: 045/22-23 | J90: 120gsm 22G | K90: =IF(ISNUMBER(SEARCH("gsm",J:J)),"Kg's",IF(ISNUMBER(SEARCH("Tape",J:J)),"Roll",IF(ISNUMBER(SEARCH("Thermal",J:J)),"Sqmt",IF(ISNUMBER(SEARCH("Acou",J:J)),"Sqmt",IF(ISNUMBER(SEARCH("ss",J:J)),"Kg's",IF(ISNUMBER(SEARCH("Alu",J:J)),"Kg's",IF(ISNUMBER(SEARCH("Gasket",J:J)),"Rmt",IF(ISNUMBER(SEARCH("Cleats",J:J)),"No's",IF(ISNUMBER(SEARCH("Tube",J:J)),"No's",IF(ISNUMBER(SEARCH("Bracket",J:J)),"No's",IF(ISNUMBER(SEARCH("Corner",J:J)),"No's",IF(ISNUMBER(SEARCH("MS",J:J)),"Kg's",IF(ISNUMBER(SEARCH("Bucket",J:J)),"Kg's",IF(ISNUMBER(SEARCH("stretch",J:J)),"Kg's",IF(ISNUMBER(SEARCH("Bubble",J:J)),"Roll",IF(ISNUMBER(SEARCH("JTR",J:J)),"Rmt",IF(ISNUMBER(SEARCH("Rod",J:J)),"Kg's",IF(ISNUMBER(SEARCH("Handle",J:J)),"No's",IF(ISNUMBER(SEARCH("Gear",J:J)),"No's",IF(ISNUMBER(SEARCH("Bush",J:J)),"No's","")))))))))))))))))))) -> Kg's | L90: 15850 | M90: 77 | N90: =L90*M90 -> 1220450 | O90: =(N90+R90)*9% -> 110839.5 | P90: =(N90+R90)*9% -> 110839.5 | R90: 11100 | S90: =IF(R90="","",R90/(L90+L91)) -> 0.53135472 | T90: =IF(N90="","",SUM(N90,O90,P90,Q90,R90)) -> 1453229
A91: =IF(C91="","",COUNT($C$3:C91)) -> 89 | B91: =IF(C91="","",TEXT(C91,"mmmm")) -> September | C91: 44826 | D91: 925 | E91: 44814 | F91: JR & Co | G91: JSW | H91: 41565 | I91: 046/22-23 | J91: 120gsm 20G | K91: =IF(ISNUMBER(SEARCH("gsm",J:J)),"Kg's",IF(ISNUMBER(SEARCH("Tape",J:J)),"Roll",IF(ISNUMBER(SEARCH("Thermal",J:J)),"Sqmt",IF(ISNUMBER(SEARCH("Acou",J:J)),"Sqmt",IF(ISNUMBER(SEARCH("ss",J:J)),"Kg's",IF(ISNUMBER(SEARCH("Alu",J:J)),"Kg's",IF(ISNUMBER(SEARCH("Gasket",J:J)),"Rmt",IF(ISNUMBER(SEARCH("Cleats",J:J)),"No's",IF(ISNUMBER(SEARCH("Tube",J:J)),"No's",IF(ISNUMBER(SEARCH("Bracket",J:J)),"No's",IF(ISNUMBER(SEARCH("Corner",J:J)),"No's",IF(ISNUMBER(SEARCH("MS",J:J)),"Kg's",IF(ISNUMBER(SEARCH("Bucket",J:J)),"Kg's",IF(ISNUMBER(SEARCH("stretch",J:J)),"Kg's",IF(ISNUMBER(SEARCH("Bubble",J:J)),"Roll",IF(ISNUMBER(SEARCH("JTR",J:J)),"Rmt",IF(ISNUMBER(SEARCH("Rod",J:J)),"Kg's",IF(ISNUMBER(SEARCH("Handle",J:J)),"No's",IF(ISNUMBER(SEARCH("Gear",J:J)),"No's",IF(ISNUMBER(SEARCH("Bush",J:J)),"No's","")))))))))))))))))))) -> Kg's | L91: 5040 | M91: 77 | N91: =L91*M91 -> 388080 | O91: =(N91+R91)*9% -> 35584.2 | P91: =(N91+R91)*9% -> 35584.2 | R91: 7300 | S91: =IF(R91="","",R91/(L91+L92)) -> 0.70361446 | T91: =IF(N91="","",SUM(N91,O91,P91,Q91,R91)) -> 466548.4
A92: =IF(C92="","",COUNT($C$3:C92)) -> 90 | B92: =IF(C92="","",TEXT(C92,"mmmm")) -> September | C92: 44826 | D92: 925 | E92: 44814 | F92: JR & Co | G92: JSW | H92: 41565 | I92: 046/22-23 | J92: 120gsm 26G | K92: =IF(ISNUMBER(SEARCH("gsm",J:J)),"Kg's",IF(ISNUMBER(SEARCH("Tape",J:J)),"Roll",IF(ISNUMBER(SEARCH("Thermal",J:J)),"Sqmt",IF(ISNUMBER(SEARCH("Acou",J:J)),"Sqmt",IF(ISNUMBER(SEARCH("ss",J:J)),"Kg's",IF(ISNUMBER(SEARCH("Alu",J:J)),"Kg's",IF(ISNUMBER(SEARCH("Gasket",J:J)),"Rmt",IF(ISNUMBER(SEARCH("Cleats",J:J)),"No's",IF(ISNUMBER(SEARCH("Tube",J:J)),"No's",IF(ISNUMBER(SEARCH("Bracket",J:J)),"No's",IF(ISNUMBER(SEARCH("Corner",J:J)),"No's",IF(ISNUMBER(SEARCH("MS",J:J)),"Kg's",IF(ISNUMBER(SEARCH("Bucket",J:J)),"Kg's",IF(ISNUMBER(SEARCH("stretch",J:J)),"Kg's",IF(ISNUMBER(SEARCH("Bubble",J:J)),"Roll",IF(ISNUMBER(SEARCH("JTR",J:J)),"Rmt",IF(ISNUMBER(SEARCH("Rod",J:J)),"Kg's",IF(ISNUMBER(SEARCH("Handle",J:J)),"No's",IF(ISNUMBER(SEARCH("Gear",J:J)),"No's",IF(ISNUMBER(SEARCH("Bush",J:J)),"No's","")))))))))))))))))))) -> Kg's | L92: 5335 | M92: 80 | N92: =L92*M92 -> 426800 | O92: =(N92+R92)*9% -> 38412 | P92: =(N92+R92)*9% -> 38412 | T92: =IF(N92="","",SUM(N92,O92,P92,Q92,R92)) -> 503624
A93: =IF(C93="","",COUNT($C$3:C93)) -> 91 | B93: =IF(C93="","",TEXT(C93,"mmmm")) -> September | C93: 44827 | D93: 925 | E93: 44814 | F93: JR & Co | G93: JSW | H93: 41582 | I93: 047/22-23 | J93: 120gsm 24G | K93: =IF(ISNUMBER(SEARCH("gsm",J:J)),"Kg's",IF(ISNUMBER(SEARCH("Tape",J:J)),"Roll",IF(ISNUMBER(SEARCH("Thermal",J:J)),"Sqmt",IF(ISNUMBER(SEARCH("Acou",J:J)),"Sqmt",IF(ISNUMBER(SEARCH("ss",J:J)),"Kg's",IF(ISNUMBER(SEARCH("Alu",J:J)),"Kg's",IF(ISNUMBER(SEARCH("Gasket",J:J)),"Rmt",IF(ISNUMBER(SEARCH("Cleats",J:J)),"No's",IF(ISNUMBER(SEARCH("Tube",J:J)),"No's",IF(ISNUMBER(SEARCH("Bracket",J:J)),"No's",IF(ISNUMBER(SEARCH("Corner",J:J)),"No's",IF(ISNUMBER(SEARCH("MS",J:J)),"Kg's",IF(ISNUMBER(SEARCH("Bucket",J:J)),"Kg's",IF(ISNUMBER(SEARCH("stretch",J:J)),"Kg's",IF(ISNUMBER(SEARCH("Bubble",J:J)),"Roll",IF(ISNUMBER(SEARCH("JTR",J:J)),"Rmt",IF(ISNUMBER(SEARCH("Rod",J:J)),"Kg's",IF(ISNUMBER(SEARCH("Handle",J:J)),"No's",IF(ISNUMBER(SEARCH("Gear",J:J)),"No's",IF(ISNUMBER(SEARCH("Bush",J:J)),"No's","")))))))))))))))))))) -> Kg's | L93: 17530 | M93: 78.5 | N93: =L93*M93 -> 1376105 | O93: =(N93+R93)*9% -> 124956.45 | P93: =(N93+R93)*9% -> 124956.45 | R93: 12300 | S93: =IF(R93="","",R93/(L93+L94)) -> 0.67843354 | T93: =IF(N93="","",SUM(N93,O93,P93,Q93,R93)) -> 1638317.9
A94: =IF(C94="","",COUNT($C$3:C94)) -> 92 | B94: =IF(C94="","",TEXT(C94,"mmmm")) -> September | C94: 44834 | D94: 931 | E94: 44833 | F94: Izzy Agencies | H94: 379 | I94: 049/22-23 | J94: 8 mm JTR | K94: =IF(ISNUMBER(SEARCH("gsm",J:J)),"Kg's",IF(ISNUMBER(SEARCH("Tape",J:J)),"Roll",IF(ISNUMBER(SEARCH("Thermal",J:J)),"Sqmt",IF(ISNUMBER(SEARCH("Acou",J:J)),"Sqmt",IF(ISNUMBER(SEARCH("ss",J:J)),"Kg's",IF(ISNUMBER(SEARCH("Alu",J:J)),"Kg's",IF(ISNUMBER(SEARCH("Gasket",J:J)),"Rmt",IF(ISNUMBER(SEARCH("Cleats",J:J)),"No's",IF(ISNUMBER(SEARCH("Tube",J:J)),"No's",IF(ISNUMBER(SEARCH("Bracket",J:J)),"No's",IF(ISNUMBER(SEARCH("Corner",J:J)),"No's",IF(ISNUMBER(SEARCH("MS",J:J)),"Kg's",IF(ISNUMBER(SEARCH("Bucket",J:J)),"Kg's",IF(ISNUMBER(SEARCH("stretch",J:J)),"Kg's",IF(ISNUMBER(SEARCH("Bubble",J:J)),"Roll",IF(ISNUMBER(SEARCH("JTR",J:J)),"Rmt",IF(ISNUMBER(SEARCH("Rod",J:J)),"Kg's",IF(ISNUMBER(SEARCH("Handle",J:J)),"No's",IF(ISNUMBER(SEARCH("Gear",J:J)),"No's",IF(ISNUMBER(SEARCH("Bush",J:J)),"No's","")))))))))))))))))))) -> Rmt | L94: 600 | M94: 27 | N94: =L94*M94 -> 16200 | O94: =(N94+R94)*9% -> 1458 | P94: =(N94+R94)*9% -> 1458 | T94: =IF(N94="","",SUM(N94,O94,P94,Q94,R94)) -> 19116
A95: =IF(C95="","",COUNT($C$3:C95)) -> 93 | B95: =IF(C95="","",TEXT(C95,"mmmm")) -> September | C95: 44834 | D95: 931 | E95: 44833 | F95: Izzy Agencies | H95: 379 | I95: 049/22-23 | J95: 10 mm JTR | K95: =IF(ISNUMBER(SEARCH("gsm",J:J)),"Kg's",IF(ISNUMBER(SEARCH("Tape",J:J)),"Roll",IF(ISNUMBER(SEARCH("Thermal",J:J)),"Sqmt",IF(ISNUMBER(SEARCH("Acou",J:J)),"Sqmt",IF(ISNUMBER(SEARCH("ss",J:J)),"Kg's",IF(ISNUMBER(SEARCH("Alu",J:J)),"Kg's",IF(ISNUMBER(SEARCH("Gasket",J:J)),"Rmt",IF(ISNUMBER(SEARCH("Cleats",J:J)),"No's",IF(ISNUMBER(SEARCH("Tube",J:J)),"No's",IF(ISNUMBER(SEARCH("Bracket",J:J)),"No's",IF(ISNUMBER(SEARCH("Corner",J:J)),"No's",IF(ISNUMBER(SEARCH("MS",J:J)),"Kg's",IF(ISNUMBER(SEARCH("Bucket",J:J)),"Kg's",IF(ISNUMBER(SEARCH("stretch",J:J)),"Kg's",IF(ISNUMBER(SEARCH("Bubble",J:J)),"Roll",IF(ISNUMBER(SEARCH("JTR",J:J)),"Rmt",IF(ISNUMBER(SEARCH("Rod",J:J)),"Kg's",IF(ISNUMBER(SEARCH("Handle",J:J)),"No's",IF(ISNUMBER(SEARCH("Gear",J:J)),"No's",IF(ISNUMBER(SEARCH("Bush",J:J)),"No's","")))))))))))))))))))) -> Rmt | L95: 400 | M95: 42 | N95: =L95*M95 -> 16800 | O95: =(N95+R95)*9% -> 1512 | P95: =(N95+R95)*9% -> 1512 | T95: =IF(N95="","",SUM(N95,O95,P95,Q95,R95)) -> 19824
A96: =IF(C96="","",COUNT($C$3:C96)) -> 94 | B96: =IF(C96="","",TEXT(C96,"mmmm")) -> October | C96: 44845 | D96: 935 | E96: 44844 | F96: LR Multi Speciality Products | H96: LRM/0665/22-23 | I96: 054/22-23 | J96: Stretch Film | K96: =IF(ISNUMBER(SEARCH("gsm",J:J)),"Kg's",IF(ISNUMBER(SEARCH("Tape",J:J)),"Roll",IF(ISNUMBER(SEARCH("Thermal",J:J)),"Sqmt",IF(ISNUMBER(SEARCH("Acou",J:J)),"Sqmt",IF(ISNUMBER(SEARCH("ss",J:J)),"Kg's",IF(ISNUMBER(SEARCH("Alu",J:J)),"Kg's",IF(ISNUMBER(SEARCH("Gasket",J:J)),"Rmt",IF(ISNUMBER(SEARCH("Cleats",J:J)),"No's",IF(ISNUMBER(SEARCH("Tube",J:J)),"No's",IF(ISNUMBER(SEARCH("Bracket",J:J)),"No's",IF(ISNUMBER(SEARCH("Corner",J:J)),"No's",IF(ISNUMBER(SEARCH("MS",J:J)),"Kg's",IF(ISNUMBER(SEARCH("Bucket",J:J)),"Kg's",IF(ISNUMBER(SEARCH("stretch",J:J)),"Kg's",IF(ISNUMBER(SEARCH("Bubble",J:J)),"Roll",IF(ISNUMBER(SEARCH("JTR",J:J)),"Rmt",IF(ISNUMBER(SEARCH("Rod",J:J)),"Kg's",IF(ISNUMBER(SEARCH("Handle",J:J)),"No's",IF(ISNUMBER(SEARCH("Gear",J:J)),"No's",IF(ISNUMBER(SEARCH("Bush",J:J)),"No's","")))))))))))))))))))) -> Kg's | L96: 323.2 | M96: 145 | N96: =L96*M96 -> 46864 | O96: =(N96+R96)*9% -> 4217.76 | P96: =(N96+R96)*9% -> 4217.76 | T96: =IF(N96="","",SUM(N96,O96,P96,Q96,R96)) -> 55299.52
A97: =IF(C97="","",COUNT($C$3:C97)) -> 95 | B97: =IF(C97="","",TEXT(C97,"mmmm")) -> October | C97: 44848 | D97: 936 | E97: 44847 | F97: Mandot Steel | G97: JSW | H97: MS/22-23/IN/6421 | I97: 058/22-23 | J97: 120gsm 22G | K97: =IF(ISNUMBER(SEARCH("gsm",J:J)),"Kg's",IF(ISNUMBER(SEARCH("Tape",J:J)),"Roll",IF(ISNUMBER(SEARCH("Thermal",J:J)),"Sqmt",IF(ISNUMBER(SEARCH("Acou",J:J)),"Sqmt",IF(ISNUMBER(SEARCH("ss",J:J)),"Kg's",IF(ISNUMBER(SEARCH("Alu",J:J)),"Kg's",IF(ISNUMBER(SEARCH("Gasket",J:J)),"Rmt",IF(ISNUMBER(SEARCH("Cleats",J:J)),"No's",IF(ISNUMBER(SEARCH("Tube",J:J)),"No's",IF(ISNUMBER(SEARCH("Bracket",J:J)),"No's",IF(ISNUMBER(SEARCH("Corner",J:J)),"No's",IF(ISNUMBER(SEARCH("MS",J:J)),"Kg's",IF(ISNUMBER(SEARCH("Bucket",J:J)),"Kg's",IF(ISNUMBER(SEARCH("stretch",J:J)),"Kg's",IF(ISNUMBER(SEARCH("Bubble",J:J)),"Roll",IF(ISNUMBER(SEARCH("JTR",J:J)),"Rmt",IF(ISNUMBER(SEARCH("Rod",J:J)),"Kg's",IF(ISNUMBER(SEARCH("Handle",J:J)),"No's",IF(ISNUMBER(SEARCH("Gear",J:J)),"No's",IF(ISNUMBER(SEARCH("Bush",J:J)),"No's","")))))))))))))))))))) -> Kg's | L97: 9935 | M97: 75 | N97: =L97*M97 -> 745125 | O97: =(N97+R97)*9% -> 67511.25 | P97: =(N97+R97)*9% -> 67511.25 | R97: 5000 | S97: =IF(R97="","",R97/(L97+L98)) -> 0.32268474 | T97: =IF(N97="","",SUM(N97,O97,P97,Q97,R97)) -> 885147.5
A98: =IF(C98="","",COUNT($C$3:C98)) -> 96 | B98: =IF(C98="","",TEXT(C98,"mmmm")) -> October | C98: 44848 | D98: 936 | E98: 44847 | F98: Mandot Steel | G98: JSW | H98: MS/22-23/IN/6422 | I98: 059/22-23 | J98: 120gsm 24G | K98: =IF(ISNUMBER(SEARCH("gsm",J:J)),"Kg's",IF(ISNUMBER(SEARCH("Tape",J:J)),"Roll",IF(ISNUMBER(SEARCH("Thermal",J:J)),"Sqmt",IF(ISNUMBER(SEARCH("Acou",J:J)),"Sqmt",IF(ISNUMBER(SEARCH("ss",J:J)),"Kg's",IF(ISNUMBER(SEARCH("Alu",J:J)),"Kg's",IF(ISNUMBER(SEARCH("Gasket",J:J)),"Rmt",IF(ISNUMBER(SEARCH("Cleats",J:J)),"No's",IF(ISNUMBER(SEARCH("Tube",J:J)),"No's",IF(ISNUMBER(SEARCH("Bracket",J:J)),"No's",IF(ISNUMBER(SEARCH("Corner",J:J)),"No's",IF(ISNUMBER(SEARCH("MS",J:J)),"Kg's",IF(ISNUMBER(SEARCH("Bucket",J:J)),"Kg's",IF(ISNUMBER(SEARCH("stretch",J:J)),"Kg's",IF(ISNUMBER(SEARCH("Bubble",J:J)),"Roll",IF(ISNUMBER(SEARCH("JTR",J:J)),"Rmt",IF(ISNUMBER(SEARCH("Rod",J:J)),"Kg's",IF(ISNUMBER(SEARCH("Handle",J:J)),"No's",IF(ISNUMBER(SEARCH("Gear",J:J)),"No's",IF(ISNUMBER(SEARCH("Bush",J:J)),"No's","")))))))))))))))))))) -> Kg's | L98: 5560 | M98: 76.5 | N98: =L98*M98 -> 425340 | O98: =(N98+R98)*9% -> 38528.1 | P98: =(N98+R98)*9% -> 38528.1 | R98: 2750 | S98: =IF(R98="","",R98/(L98+L99)) -> 0.18345564 | T98: =IF(N98="","",SUM(N98,O98,P98,Q98,R98)) -> 505146.2
A99: =IF(C99="","",COUNT($C$3:C99)) -> 97 | B99: =IF(C99="","",TEXT(C99,"mmmm")) -> October | C99: 44852 | D99: 936 | E99: 44847 | F99: Mandot Steel | G99: JSW | H99: MS/22-23/IN/6495 | I99: 063/22-23 | J99: 120gsm 24G | K99: =IF(ISNUMBER(SEARCH("gsm",J:J)),"Kg's",IF(ISNUMBER(SEARCH("Tape",J:J)),"Roll",IF(ISNUMBER(SEARCH("Thermal",J:J)),"Sqmt",IF(ISNUMBER(SEARCH("Acou",J:J)),"Sqmt",IF(ISNUMBER(SEARCH("ss",J:J)),"Kg's",IF(ISNUMBER(SEARCH("Alu",J:J)),"Kg's",IF(ISNUMBER(SEARCH("Gasket",J:J)),"Rmt",IF(ISNUMBER(SEARCH("Cleats",J:J)),"No's",IF(ISNUMBER(SEARCH("Tube",J:J)),"No's",IF(ISNUMBER(SEARCH("Bracket",J:J)),"No's",IF(ISNUMBER(SEARCH("Corner",J:J)),"No's",IF(ISNUMBER(SEARCH("MS",J:J)),"Kg's",IF(ISNUMBER(SEARCH("Bucket",J:J)),"Kg's",IF(ISNUMBER(SEARCH("stretch",J:J)),"Kg's",IF(ISNUMBER(SEARCH("Bubble",J:J)),"Roll",IF(ISNUMBER(SEARCH("JTR",J:J)),"Rmt",IF(ISNUMBER(SEARCH("Rod",J:J)),"Kg's",IF(ISNUMBER(SEARCH("Handle",J:J)),"No's",IF(ISNUMBER(SEARCH("Gear",J:J)),"No's",IF(ISNUMBER(SEARCH("Bush",J:J)),"No's","")))))))))))))))))))) -> Kg's | L99: 9430 | M99: 76.5 | N99: =L99*M99 -> 721395 | O99: =(N99+R99)*9% -> 65353.05 | P99: =(N99+R99)*9% -> 65353.05 | R99: 4750 | S99: =IF(R99="","",R99/(L99+L100)) -> 0.21709324 | T99: =IF(N99="","",SUM(N99,O99,P99,Q99,R99)) -> 856851.1
A100: =IF(C100="","",COUNT($C$3:C100)) -> 98 | B100: =IF(C100="","",TEXT(C100,"mmmm")) -> October | C100: 44852 | D100: 936 | E100: 44847 | F100: Mandot Steel | G100: JSW | H100: MS/22-23/IN/6496 | I100: 064/22-23 | J100: 120gsm 24G | K100: =IF(ISNUMBER(SEARCH("gsm",J:J)),"Kg's",IF(ISNUMBER(SEARCH("Tape",J:J)),"Roll",IF(ISNUMBER(SEARCH("Thermal",J:J)),"Sqmt",IF(ISNUMBER(SEARCH("Acou",J:J)),"Sqmt",IF(ISNUMBER(SEARCH("ss",J:J)),"Kg's",IF(ISNUMBER(SEARCH("Alu",J:J)),"Kg's",IF(ISNUMBER(SEARCH("Gasket",J:J)),"Rmt",IF(ISNUMBER(SEARCH("Cleats",J:J)),"No's",IF(ISNUMBER(SEARCH("Tube",J:J)),"No's",IF(ISNUMBER(SEARCH("Bracket",J:J)),"No's",IF(ISNUMBER(SEARCH("Corner",J:J)),"No's",IF(ISNUMBER(SEARCH("MS",J:J)),"Kg's",IF(ISNUMBER(SEARCH("Bucket",J:J)),"Kg's",IF(ISNUMBER(SEARCH("stretch",J:J)),"Kg's",IF(ISNUMBER(SEARCH("Bubble",J:J)),"Roll",IF(ISNUMBER(SEARCH("JTR",J:J)),"Rmt",IF(ISNUMBER(SEARCH("Rod",J:J)),"Kg's",IF(ISNUMBER(SEARCH("Handle",J:J)),"No's",IF(ISNUMBER(SEARCH("Gear",J:J)),"No's",IF(ISNUMBER(SEARCH("Bush",J:J)),"No's","")))))))))))))))))))) -> Kg's | L100: 12450 | M100: 76.5 | N100: =L100*M100 -> 952425 | O100: =(N100+R100)*9% -> 86280.75 | P100: =(N100+R100)*9% -> 86280.75 | R100: 6250 | S100: =IF(R100="","",R100/(L100+L101)) -> 0.48262548 | T100: =IF(N100="","",SUM(N100,O100,P100,Q100,R100)) -> 1131236.5
...

Sheet Consumption
N1: SUM | O1: =SUM(O3:O1048576) -> 449468.27 | P1: =SUM(P3:P1048576) -> 70163.15 | Q1: =SUM(Q3:Q1048576) -> 64018.7 | R1: =AVERAGE(R3:R2087) -> 22.157623 | S1: =AVERAGE(S3:S2321) -> 77.625641 | T1: =SUM(T3:T1048576) -> 6251.2702 | U1: =SUM(U3:U1048576) -> 6110.55 | W1: =SUM(W3:W1048576) -> 32508.948 | X1: =SUM(X3:X1048576) -> 34376.953 | Y1: =AVERAGE(Y3:Y1048576) -> 14.886479 | Z1: =AVERAGE(Z3:Z1048576) -> 16.637762 | AA1: =SUM(AA3:AA1048576) -> 0 | AB1: =SUM(AB3:AB1048576) -> 34376.953
A2: SI NO | B2: MONTH | C2: DATE | D2: CUST. PO NO. | E2: KNND JOB NO | F2: PO DATE | G2: CUSTOMER NAME | H2: PROJECT NAME | I2: PRODUCT | J2: RAW MATERIAL | K2: UNITS | L2: PLANNING(Sqmt) | M2: S.LINE (Rmt) | N2: VULCAN (Rmt) | O2: FEED QTY | P2: BILL Qty Sqmt | Q2: Area+Fold | R2: Fitting (Straight) | S2: Ratio (Fitting) | T2: SCRAP Sqmt | U2: FOLD Sqmt | V2: CONSUMPTION | W2: FOLD Kg | X2: SCRAP Kg | Y2: SCRAP % | Z2: FOLD % | AA2: USED SCR Kg | AB2: Act SCRAP Kg | AC2: Remarks | AD2: Coil Number
A3: =IF(C3="","",COUNTA($C$3:C3)) -> 1 | B3: =IF(C3="","",TEXT(C3,"mmmm")) -> April | C3: 44655 | D3: 2302-64005 | F3: 44616 | G3: Knnd Associates Pvt Ltd | H3: Google Kyoto West Second Floor Oval Duct | I3: Spiral Oval Duct with Paint | J3: 120gsm Slit 24G | K3: =IF(ISNUMBER(SEARCH("gsm",J:J)),"Sqmt",IF(ISNUMBER(SEARCH("Tape",J:J)),"Roll",IF(ISNUMBER(SEARCH("Thermal",J:J)),"Sqmt",IF(ISNUMBER(SEARCH("Acou",J:J)),"Sqmt",IF(ISNUMBER(SEARCH("ss",J:J)),"Sqmt",IF(ISNUMBER(SEARCH("Alu",J:J)),"Sqmt",IF(ISNUMBER(SEARCH("Gasket",J:J)),"Rmt",IF(ISNUMBER(SEARCH("Cleats",J:J)),"No's",IF(ISNUMBER(SEARCH("Tube",J:J)),"No's",IF(ISNUMBER(SEARCH("Bracket",J:J)),"No's",IF(ISNUMBER(SEARCH("Corner",J:J)),"No's",IF(ISNUMBER(SEARCH("MS",J:J)),"Kg's",IF(ISNUMBER(SEARCH("Bucket",J:J)),"Kg's",IF(ISNUMBER(SEARCH("stretch",J:J)),"Kg's",IF(ISNUMBER(SEARCH("Bubble",J:J)),"Roll",IF(ISNUMBER(SEARCH("JTR",J:J)),"Rmt",IF(ISNUMBER(SEARCH("Clamp",J:J)),"No's",IF(ISNUMBER(SEARCH("PIR",J:J)),"sqmt","")))))))))))))))))) -> Sqmt | L3: 21.8 | M3: 17.868852 | O3: =IF(ISNUMBER(SEARCH("gsm",J:J)),(M3+N3)*1.22,IF(ISNUMBER(SEARCH("Tape",J:J)),L3,IF(ISNUMBER(SEARCH("Thermal",J:J)),L3,IF(ISNUMBER(SEARCH("Acou",J:J)),L3,IF(ISNUMBER(SEARCH("ss",J:J)),L3,IF(ISNUMBER(SEARCH("Alu",J:J)),L3,IF(ISNUMBER(SEARCH("Gasket",J:J)),L3,IF(ISNUMBER(SEARCH("Cleats",J:J)),L3,IF(ISNUMBER(SEARCH("Tube",J:J)),L3,IF(ISNUMBER(SEARCH("Bracket",J:J)),L3,IF(ISNUMBER(SEARCH("Corner",J:J)),L3,IF(ISNUMBER(SEARCH("MS",J:J)),L3,IF(ISNUMBER(SEARCH("Bucket",J:J)),L3,IF(ISNUMBER(SEARCH("stretch",J:J)),L3,IF(ISNUMBER(SEARCH("Bubble",J:J)),L3,IF(ISNUMBER(SEARCH("JTR",J:J)),L3,IF(ISNUMBER(SEARCH("Clamp",J:J)),"No's",IF(ISNUMBER(SEARCH("PIR",J:J)),"sqmt","")))))))))))))))))) -> 21.8 | P3: 13.1 | Q3: 13.5 | R3: 37 | S3: 63 | T3: =(IF(K3="Sqmt",(O3-Q3),"")) -> 8.3 | U3: =(IF(K3="Sqmt",(O3-P3)-T3,IF(K3="Rmt","",IF(K3="Kg's","",IF(K3="No's","",IF(K3="Roll","","")))))) -> 0.4 | V3: =IF(ISNUMBER(SEARCH("26",J:J)),O3*3.925,IF(ISNUMBER(SEARCH("24",J:J)),O3*4.71,IF(ISNUMBER(SEARCH("22",J:J)),O3*6.28,IF(ISNUMBER(SEARCH("20",J:J)),O3*7.85,IF(ISNUMBER(SEARCH("18G",J:J)),O3*9.42,IF(ISNUMBER(SEARCH("16G",J:J)),O3*11.775,IF(ISNUMBER(SEARCH("Thermal",J:J)),O3,IF(ISNUMBER(SEARCH("Acou",J:J)),O3,IF(ISNUMBER(SEARCH("ss",J:J)),O3,IF(ISNUMBER(SEARCH("0.8mm",J:J)),O3*2.2,IF(ISNUMBER(SEARCH("1mm",J:J)),O3*2.75,IF(ISNUMBER(SEARCH("1.2mm",J:J)),O3*3.3,IF(ISNUMBER(SEARCH("Gasket",J:J)),O3,IF(ISNUMBER(SEARCH("Cleats",J:J)),O3,IF(ISNUMBER(SEARCH("Sealant",J:J)),O3,IF(ISNUMBER(SEARCH("Bracket",J:J)),O3,IF(ISNUMBER(SEARCH("Corner",J:J)),O3,IF(ISNUMBER(SEARCH("Bubble",J:J)),O3,"")))))))))))))))))) -> 102.678 | W3: =IF(ISNUMBER(SEARCH("26",J:J)),U3*3.925,IF(ISNUMBER(SEARCH("24",J:J)),U3*4.71,IF(ISNUMBER(SEARCH("22",J:J)),U3*6.28,IF(ISNUMBER(SEARCH("20",J:J)),U3*7.85,IF(ISNUMBER(SEARCH("18G",J:J)),U3*9.42,IF(ISNUMBER(SEARCH("16G",J:J)),U3*11.775,IF(ISNUMBER(SEARCH("Thermal",J:J)),U3,IF(ISNUMBER(SEARCH("Acou",J:J)),U3,IF(ISNUMBER(SEARCH("ss",J:J)),U3,IF(ISNUMBER(SEARCH("0.8mm",J:J)),U3*2.2,IF(ISNUMBER(SEARCH("1mm",J:J)),U3*2.75,IF(ISNUMBER(SEARCH("1.2mm",J:J)),U3*3.3,IF(ISNUMBER(SEARCH("Gasket",J:J)),U3,IF(ISNUMBER(SEARCH("Cleats",J:J)),U3,IF(ISNUMBER(SEARCH("Sealant",J:J)),U3,IF(ISNUMBER(SEARCH("Bracket",J:J)),U3,IF(ISNUMBER(SEARCH("Corner",J:J)),U3,IF(ISNUMBER(SEARCH("Bubble",J:J)),U3,"")))))))))))))))))) -> 1.884 | X3: =IF(ISNUMBER(SEARCH("26",J:J)),T3*3.925,IF(ISNUMBER(SEARCH("24",J:J)),T3*4.71,IF(ISNUMBER(SEARCH("22",J:J)),T3*6.28,IF(ISNUMBER(SEARCH("20",J:J)),T3*7.85,IF(ISNUMBER(SEARCH("18",J:J)),T3*9.42,IF(ISNUMBER(SEARCH("16",J:J)),T3*11.775,IF(ISNUMBER(SEARCH("Thermal",J:J)),"",IF(ISNUMBER(SEARCH("Acou",J:J)),"",IF(ISNUMBER(SEARCH("ss",J:J)),"",IF(ISNUMBER(SEARCH("0.8mm",J:J)),T3*2.2,IF(ISNUMBER(SEARCH("1mm",J:J)),T3*2.75,IF(ISNUMBER(SEARCH("1.2mm",J:J)),T3*3.3,IF(ISNUMBER(SEARCH("Gasket",J:J)),"",IF(ISNUMBER(SEARCH("Cleats",J:J)),"",IF(ISNUMBER(SEARCH("Sealant",J:J)),"",IF(ISNUMBER(SEARCH("Bracket",J:J)),"",IF(ISNUMBER(SEARCH("Corner",J:J)),"",IF(ISNUMBER(SEARCH("Bubble",J:J)),"","")))))))))))))))))) -> 39.093 | Y3: =IF(K3="Sqmt",(T3/O3)*100,IF(K3="Kg's","",IF(K3="No's","",IF(K3="Rmt","",IF(K3="Roll","",IF(K3="","")))))) -> 38.073394 | Z3: =IF(K3="Sqmt",(U3/O3)*100,IF(K3="Kg's","",IF(K3="No's","",IF(K3="Rmt","",IF(K3="Roll","",IF(K3="","")))))) -> 1.8348624 | AB3: =IFERROR((X3-AA3),"") -> 39.093
A4: =IF(C4="","",COUNTA($C$3:C4)) -> 2 | B4: =IF(C4="","",TEXT(C4,"mmmm")) -> April | C4: 44655 | D4: 2302-64005 | F4: 44616 | G4: Knnd Associates Pvt Ltd | H4: Google Kyoto West Second Floor Oval Duct | I4: Spiral Oval Duct with Paint | J4: 120gsm 24G | K4: =IF(ISNUMBER(SEARCH("gsm",J:J)),"Sqmt",IF(ISNUMBER(SEARCH("Tape",J:J)),"Roll",IF(ISNUMBER(SEARCH("Thermal",J:J)),"Sqmt",IF(ISNUMBER(SEARCH("Acou",J:J)),"Sqmt",IF(ISNUMBER(SEARCH("ss",J:J)),"Sqmt",IF(ISNUMBER(SEARCH("Alu",J:J)),"Sqmt",IF(ISNUMBER(SEARCH("Gasket",J:J)),"Rmt",IF(ISNUMBER(SEARCH("Cleats",J:J)),"No's",IF(ISNUMBER(SEARCH("Tube",J:J)),"No's",IF(ISNUMBER(SEARCH("Bracket",J:J)),"No's",IF(ISNUMBER(SEARCH("Corner",J:J)),"No's",IF(ISNUMBER(SEARCH("MS",J:J)),"Kg's",IF(ISNUMBER(SEARCH("Bucket",J:J)),"Kg's",IF(ISNUMBER(SEARCH("stretch",J:J)),"Kg's",IF(ISNUMBER(SEARCH("Bubble",J:J)),"Roll",IF(ISNUMBER(SEARCH("JTR",J:J)),"Rmt",IF(ISNUMBER(SEARCH("Clamp",J:J)),"No's",IF(ISNUMBER(SEARCH("PIR",J:J)),"sqmt","")))))))))))))))))) -> Sqmt | L4: 48.7 | N4: 39.918033 | O4: =IF(ISNUMBER(SEARCH("gsm",J:J)),(M4+N4)*1.22,IF(ISNUMBER(SEARCH("Tape",J:J)),L4,IF(ISNUMBER(SEARCH("Thermal",J:J)),L4,IF(ISNUMBER(SEARCH("Acou",J:J)),L4,IF(ISNUMBER(SEARCH("ss",J:J)),L4,IF(ISNUMBER(SEARCH("Alu",J:J)),L4,IF(ISNUMBER(SEARCH("Gasket",J:J)),L4,IF(ISNUMBER(SEARCH("Cleats",J:J)),L4,IF(ISNUMBER(SEARCH("Tube",J:J)),L4,IF(ISNUMBER(SEARCH("Bracket",J:J)),L4,IF(ISNUMBER(SEARCH("Corner",J:J)),L4,IF(ISNUMBER(SEARCH("MS",J:J)),L4,IF(ISNUMBER(SEARCH("Bucket",J:J)),L4,IF(ISNUMBER(SEARCH("stretch",J:J)),L4,IF(ISNUMBER(SEARCH("Bubble",J:J)),L4,IF(ISNUMBER(SEARCH("JTR",J:J)),L4,IF(ISNUMBER(SEARCH("Clamp",J:J)),"No's",IF(ISNUMBER(SEARCH("PIR",J:J)),"sqmt","")))))))))))))))))) -> 48.7 | P4: 37.1 | Q4: 43.8 | T4: =(IF(K4="Sqmt",(O4-Q4),"")) -> 4.9 | U4: =(IF(K4="Sqmt",(O4-P4)-T4,IF(K4="Rmt","",IF(K4="Kg's","",IF(K4="No's","",IF(K4="Roll","","")))))) -> 6.7 | V4: =IF(ISNUMBER(SEARCH("26",J:J)),O4*3.925,IF(ISNUMBER(SEARCH("24",J:J)),O4*4.71,IF(ISNUMBER(SEARCH("22",J:J)),O4*6.28,IF(ISNUMBER(SEARCH("20",J:J)),O4*7.85,IF(ISNUMBER(SEARCH("18G",J:J)),O4*9.42,IF(ISNUMBER(SEARCH("16G",J:J)),O4*11.775,IF(ISNUMBER(SEARCH("Thermal",J:J)),O4,IF(ISNUMBER(SEARCH("Acou",J:J)),O4,IF(ISNUMBER(SEARCH("ss",J:J)),O4,IF(ISNUMBER(SEARCH("0.8mm",J:J)),O4*2.2,IF(ISNUMBER(SEARCH("1mm",J:J)),O4*2.75,IF(ISNUMBER(SEARCH("1.2mm",J:J)),O4*3.3,IF(ISNUMBER(SEARCH("Gasket",J:J)),O4,IF(ISNUMBER(SEARCH("Cleats",J:J)),O4,IF(ISNUMBER(SEARCH("Sealant",J:J)),O4,IF(ISNUMBER(SEARCH("Bracket",J:J)),O4,IF(ISNUMBER(SEARCH("Corner",J:J)),O4,IF(ISNUMBER(SEARCH("Bubble",J:J)),O4,"")))))))))))))))))) -> 229.377 | W4: =IF(ISNUMBER(SEARCH("26",J:J)),U4*3.925,IF(ISNUMBER(SEARCH("24",J:J)),U4*4.71,IF(ISNUMBER(SEARCH("22",J:J)),U4*6.28,IF(ISNUMBER(SEARCH("20",J:J)),U4*7.85,IF(ISNUMBER(SEARCH("18G",J:J)),U4*9.42,IF(ISNUMBER(SEARCH("16G",J:J)),U4*11.775,IF(ISNUMBER(SEARCH("Thermal",J:J)),U4,IF(ISNUMBER(SEARCH("Acou",J:J)),U4,IF(ISNUMBER(SEARCH("ss",J:J)),U4,IF(ISNUMBER(SEARCH("0.8mm",J:J)),U4*2.2,IF(ISNUMBER(SEARCH("1mm",J:J)),U4*2.75,IF(ISNUMBER(SEARCH("1.2mm",J:J)),U4*3.3,IF(ISNUMBER(SEARCH("Gasket",J:J)),U4,IF(ISNUMBER(SEARCH("Cleats",J:J)),U4,IF(ISNUMBER(SEARCH("Sealant",J:J)),U4,IF(ISNUMBER(SEARCH("Bracket",J:J)),U4,IF(ISNUMBER(SEARCH("Corner",J:J)),U4,IF(ISNUMBER(SEARCH("Bubble",J:J)),U4,"")))))))))))))))))) -> 31.557 | X4: =IF(ISNUMBER(SEARCH("26",J:J)),T4*3.925,IF(ISNUMBER(SEARCH("24",J:J)),T4*4.71,IF(ISNUMBER(SEARCH("22",J:J)),T4*6.28,IF(ISNUMBER(SEARCH("20",J:J)),T4*7.85,IF(ISNUMBER(SEARCH("18",J:J)),T4*9.42,IF(ISNUMBER(SEARCH("16",J:J)),T4*11.775,IF(ISNUMBER(SEARCH("Thermal",J:J)),"",IF(ISNUMBER(SEARCH("Acou",J:J)),"",IF(ISNUMBER(SEARCH("ss",J:J)),"",IF(ISNUMBER(SEARCH("0.8mm",J:J)),T4*2.2,IF(ISNUMBER(SEARCH("1mm",J:J)),T4*2.75,IF(ISNUMBER(SEARCH("1.2mm",J:J)),T4*3.3,IF(ISNUMBER(SEARCH("Gasket",J:J)),"",IF(ISNUMBER(SEARCH("Cleats",J:J)),"",IF(ISNUMBER(SEARCH("Sealant",J:J)),"",IF(ISNUMBER(SEARCH("Bracket",J:J)),"",IF(ISNUMBER(SEARCH("Corner",J:J)),"",IF(ISNUMBER(SEARCH("Bubble",J:J)),"","")))))))))))))))))) -> 23.079 | Y4: =IF(K4="Sqmt",(T4/O4)*100,IF(K4="Kg's","",IF(K4="No's","",IF(K4="Rmt","",IF(K4="Roll","",IF(K4="","")))))) -> 10.061602 | Z4: =IF(K4="Sqmt",(U4/O4)*100,IF(K4="Kg's","",IF(K4="No's","",IF(K4="Rmt","",IF(K4="Roll","",IF(K4="","")))))) -> 13.7577 | AB4: =IFERROR((X4-AA4),"") -> 23.079
A5: =IF(C5="","",COUNTA($C$3:C5)) -> 3 | B5: =IF(C5="","",TEXT(C5,"mmmm")) -> April | C5: 44655 | D5: 2302-64005 | F5: 44616 | G5: Knnd Associates Pvt Ltd | H5: Google Kyoto West Second Floor Oval Duct | I5: Spiral Oval Duct with Paint | J5: 120gsm Slit 22G | K5: =IF(ISNUMBER(SEARCH("gsm",J:J)),"Sqmt",IF(ISNUMBER(SEARCH("Tape",J:J)),"Roll",IF(ISNUMBER(SEARCH("Thermal",J:J)),"Sqmt",IF(ISNUMBER(SEARCH("Acou",J:J)),"Sqmt",IF(ISNUMBER(SEARCH("ss",J:J)),"Sqmt",IF(ISNUMBER(SEARCH("Alu",J:J)),"Sqmt",IF(ISNUMBER(SEARCH("Gasket",J:J)),"Rmt",IF(ISNUMBER(SEARCH("Cleats",J:J)),"No's",IF(ISNUMBER(SEARCH("Tube",J:J)),"No's",IF(ISNUMBER(SEARCH("Bracket",J:J)),"No's",IF(ISNUMBER(SEARCH("Corner",J:J)),"No's",IF(ISNUMBER(SEARCH("MS",J:J)),"Kg's",IF(ISNUMBER(SEARCH("Bucket",J:J)),"Kg's",IF(ISNUMBER(SEARCH("stretch",J:J)),"Kg's",IF(ISNUMBER(SEARCH("Bubble",J:J)),"Roll",IF(ISNUMBER(SEARCH("JTR",J:J)),"Rmt",IF(ISNUMBER(SEARCH("Clamp",J:J)),"No's",IF(ISNUMBER(SEARCH("PIR",J:J)),"sqmt","")))))))))))))))))) -> Sqmt | L5: 32.8 | M5: 26.885246 | O5: =IF(ISNUMBER(SEARCH("gsm",J:J)),(M5+N5)*1.22,IF(ISNUMBER(SEARCH("Tape",J:J)),L5,IF(ISNUMBER(SEARCH("Thermal",J:J)),L5,IF(ISNUMBER(SEARCH("Acou",J:J)),L5,IF(ISNUMBER(SEARCH("ss",J:J)),L5,IF(ISNUMBER(SEARCH("Alu",J:J)),L5,IF(ISNUMBER(SEARCH("Gasket",J:J)),L5,IF(ISNUMBER(SEARCH("Cleats",J:J)),L5,IF(ISNUMBER(SEARCH("Tube",J:J)),L5,IF(ISNUMBER(SEARCH("Bracket",J:J)),L5,IF(ISNUMBER(SEARCH("Corner",J:J)),L5,IF(ISNUMBER(SEARCH("MS",J:J)),L5,IF(ISNUMBER(SEARCH("Bucket",J:J)),L5,IF(ISNUMBER(SEARCH("stretch",J:J)),L5,IF(ISNUMBER(SEARCH("Bubble",J:J)),L5,IF(ISNUMBER(SEARCH("JTR",J:J)),L5,IF(ISNUMBER(SEARCH("Clamp",J:J)),"No's",IF(ISNUMBER(SEARCH("PIR",J:J)),"sqmt","")))))))))))))))))) -> 32.8 | P5: 25.5 | Q5: 26.1 | T5: =(IF(K5="Sqmt",(O5-Q5),"")) -> 6.7 | U5: =(IF(K5="Sqmt",(O5-P5)-T5,IF(K5="Rmt","",IF(K5="Kg's","",IF(K5="No's","",IF(K5="Roll","","")))))) -> 0.6 | V5: =IF(ISNUMBER(SEARCH("26",J:J)),O5*3.925,IF(ISNUMBER(SEARCH("24",J:J)),O5*4.71,IF(ISNUMBER(SEARCH("22",J:J)),O5*6.28,IF(ISNUMBER(SEARCH("20",J:J)),O5*7.85,IF(ISNUMBER(SEARCH("18G",J:J)),O5*9.42,IF(ISNUMBER(SEARCH("16G",J:J)),O5*11.775,IF(ISNUMBER(SEARCH("Thermal",J:J)),O5,IF(ISNUMBER(SEARCH("Acou",J:J)),O5,IF(ISNUMBER(SEARCH("ss",J:J)),O5,IF(ISNUMBER(SEARCH("0.8mm",J:J)),O5*2.2,IF(ISNUMBER(SEARCH("1mm",J:J)),O5*2.75,IF(ISNUMBER(SEARCH("1.2mm",J:J)),O5*3.3,IF(ISNUMBER(SEARCH("Gasket",J:J)),O5,IF(ISNUMBER(SEARCH("Cleats",J:J)),O5,IF(ISNUMBER(SEARCH("Sealant",J:J)),O5,IF(ISNUMBER(SEARCH("Bracket",J:J)),O5,IF(ISNUMBER(SEARCH("Corner",J:J)),O5,IF(ISNUMBER(SEARCH("Bubble",J:J)),O5,"")))))))))))))))))) -> 205.984 | W5: =IF(ISNUMBER(SEARCH("26",J:J)),U5*3.925,IF(ISNUMBER(SEARCH("24",J:J)),U5*4.71,IF(ISNUMBER(SEARCH("22",J:J)),U5*6.28,IF(ISNUMBER(SEARCH("20",J:J)),U5*7.85,IF(ISNUMBER(SEARCH("18G",J:J)),U5*9.42,IF(ISNUMBER(SEARCH("16G",J:J)),U5*11.775,IF(ISNUMBER(SEARCH("Thermal",J:J)),U5,IF(ISNUMBER(SEARCH("Acou",J:J)),U5,IF(ISNUMBER(SEARCH("ss",J:J)),U5,IF(ISNUMBER(SEARCH("0.8mm",J:J)),U5*2.2,IF(ISNUMBER(SEARCH("1mm",J:J)),U5*2.75,IF(ISNUMBER(SEARCH("1.2mm",J:J)),U5*3.3,IF(ISNUMBER(SEARCH("Gasket",J:J)),U5,IF(ISNUMBER(SEARCH("Cleats",J:J)),U5,IF(ISNUMBER(SEARCH("Sealant",J:J)),U5,IF(ISNUMBER(SEARCH("Bracket",J:J)),U5,IF(ISNUMBER(SEARCH("Corner",J:J)),U5,IF(ISNUMBER(SEARCH("Bubble",J:J)),U5,"")))))))))))))))))) -> 3.768 | X5: =IF(ISNUMBER(SEARCH("26",J:J)),T5*3.925,IF(ISNUMBER(SEARCH("24",J:J)),T5*4.71,IF(ISNUMBER(SEARCH("22",J:J)),T5*6.28,IF(ISNUMBER(SEARCH("20",J:J)),T5*7.85,IF(ISNUMBER(SEARCH("18",J:J)),T5*9.42,IF(ISNUMBER(SEARCH("16",J:J)),T5*11.775,IF(ISNUMBER(SEARCH("Thermal",J:J)),"",IF(ISNUMBER(SEARCH("Acou",J:J)),"",IF(ISNUMBER(SEARCH("ss",J:J)),"",IF(ISNUMBER(SEARCH("0.8mm",J:J)),T5*2.2,IF(ISNUMBER(SEARCH("1mm",J:J)),T5*2.75,IF(ISNUMBER(SEARCH("1.2mm",J:J)),T5*3.3,IF(ISNUMBER(SEARCH("Gasket",J:J)),"",IF(ISNUMBER(SEARCH("Cleats",J:J)),"",IF(ISNUMBER(SEARCH("Sealant",J:J)),"",IF(ISNUMBER(SEARCH("Bracket",J:J)),"",IF(ISNUMBER(SEARCH("Corner",J:J)),"",IF(ISNUMBER(SEARCH("Bubble",J:J)),"","")))))))))))))))))) -> 42.076 | Y5: =IF(K5="Sqmt",(T5/O5)*100,IF(K5="Kg's","",IF(K5="No's","",IF(K5="Rmt","",IF(K5="Roll","",IF(K5="","")))))) -> 20.426829 | Z5: =IF(K5="Sqmt",(U5/O5)*100,IF(K5="Kg's","",IF(K5="No's","",IF(K5="Rmt","",IF(K5="Roll","",IF(K5="","")))))) -> 1.8292683 | AB5: =IFERROR((X5-AA5),"") -> 42.076
A6: =IF(C6="","",COUNTA($C$3:C6)) -> 4 | B6: =IF(C6="","",TEXT(C6,"mmmm")) -> April | C6: 44655 | D6: 2302-64005 | F6: 44616 | G6: Knnd Associates Pvt Ltd | H6: Google Kyoto West Second Floor Oval Duct | I6: Spiral Oval Duct with Paint | J6: 120gsm 22G | K6: =IF(ISNUMBER(SEARCH("gsm",J:J)),"Sqmt",IF(ISNUMBER(SEARCH("Tape",J:J)),"Roll",IF(ISNUMBER(SEARCH("Thermal",J:J)),"Sqmt",IF(ISNUMBER(SEARCH("Acou",J:J)),"Sqmt",IF(ISNUMBER(SEARCH("ss",J:J)),"Sqmt",IF(ISNUMBER(SEARCH("Alu",J:J)),"Sqmt",IF(ISNUMBER(SEARCH("Gasket",J:J)),"Rmt",IF(ISNUMBER(SEARCH("Cleats",J:J)),"No's",IF(ISNUMBER(SEARCH("Tube",J:J)),"No's",IF(ISNUMBER(SEARCH("Bracket",J:J)),"No's",IF(ISNUMBER(SEARCH("Corner",J:J)),"No's",IF(ISNUMBER(SEARCH("MS",J:J)),"Kg's",IF(ISNUMBER(SEARCH("Bucket",J:J)),"Kg's",IF(ISNUMBER(SEARCH("stretch",J:J)),"Kg's",IF(ISNUMBER(SEARCH("Bubble",J:J)),"Roll",IF(ISNUMBER(SEARCH("JTR",J:J)),"Rmt",IF(ISNUMBER(SEARCH("Clamp",J:J)),"No's",IF(ISNUMBER(SEARCH("PIR",J:J)),"sqmt","")))))))))))))))))) -> Sqmt | L6: 45.7 | N6: 37.459016 | O6: =IF(ISNUMBER(SEARCH("gsm",J:J)),(M6+N6)*1.22,IF(ISNUMBER(SEARCH("Tape",J:J)),L6,IF(ISNUMBER(SEARCH("Thermal",J:J)),L6,IF(ISNUMBER(SEARCH("Acou",J:J)),L6,IF(ISNUMBER(SEARCH("ss",J:J)),L6,IF(ISNUMBER(SEARCH("Alu",J:J)),L6,IF(ISNUMBER(SEARCH("Gasket",J:J)),L6,IF(ISNUMBER(SEARCH("Cleats",J:J)),L6,IF(ISNUMBER(SEARCH("Tube",J:J)),L6,IF(ISNUMBER(SEARCH("Bracket",J:J)),L6,IF(ISNUMBER(SEARCH("Corner",J:J)),L6,IF(ISNUMBER(SEARCH("MS",J:J)),L6,IF(ISNUMBER(SEARCH("Bucket",J:J)),L6,IF(ISNUMBER(SEARCH("stretch",J:J)),L6,IF(ISNUMBER(SEARCH("Bubble",J:J)),L6,IF(ISNUMBER(SEARCH("JTR",J:J)),L6,IF(ISNUMBER(SEARCH("Clamp",J:J)),"No's",IF(ISNUMBER(SEARCH("PIR",J:J)),"sqmt","")))))))))))))))))) -> 45.7 | P6: 30.5 | Q6: 34.6 | T6: =(IF(K6="Sqmt",(O6-Q6),"")) -> 11.1 | U6: =(IF(K6="Sqmt",(O6-P6)-T6,IF(K6="Rmt","",IF(K6="Kg's","",IF(K6="No's","",IF(K6="Roll","","")))))) -> 4.1 | V6: =IF(ISNUMBER(SEARCH("26",J:J)),O6*3.925,IF(ISNUMBER(SEARCH("24",J:J)),O6*4.71,IF(ISNUMBER(SEARCH("22",J:J)),O6*6.28,IF(ISNUMBER(SEARCH("20",J:J)),O6*7.85,IF(ISNUMBER(SEARCH("18G",J:J)),O6*9.42,IF(ISNUMBER(SEARCH("16G",J:J)),O6*11.775,IF(ISNUMBER(SEARCH("Thermal",J:J)),O6,IF(ISNUMBER(SEARCH("Acou",J:J)),O6,IF(ISNUMBER(SEARCH("ss",J:J)),O6,IF(ISNUMBER(SEARCH("0.8mm",J:J)),O6*2.2,IF(ISNUMBER(SEARCH("1mm",J:J)),O6*2.75,IF(ISNUMBER(SEARCH("1.2mm",J:J)),O6*3.3,IF(ISNUMBER(SEARCH("Gasket",J:J)),O6,IF(ISNUMBER(SEARCH("Cleats",J:J)),O6,IF(ISNUMBER(SEARCH("Sealant",J:J)),O6,IF(ISNUMBER(SEARCH("Bracket",J:J)),O6,IF(ISNUMBER(SEARCH("Corner",J:J)),O6,IF(ISNUMBER(SEARCH("Bubble",J:J)),O6,"")))))))))))))))))) -> 286.996 | W6: =IF(ISNUMBER(SEARCH("26",J:J)),U6*3.925,IF(ISNUMBER(SEARCH("24",J:J)),U6*4.71,IF(ISNUMBER(SEARCH("22",J:J)),U6*6.28,IF(ISNUMBER(SEARCH("20",J:J)),U6*7.85,IF(ISNUMBER(SEARCH("18G",J:J)),U6*9.42,IF(ISNUMBER(SEARCH("16G",J:J)),U6*11.775,IF(ISNUMBER(SEARCH("Thermal",J:J)),U6,IF(ISNUMBER(SEARCH("Acou",J:J)),U6,IF(ISNUMBER(SEARCH("ss",J:J)),U6,IF(ISNUMBER(SEARCH("0.8mm",J:J)),U6*2.2,IF(ISNUMBER(SEARCH("1mm",J:J)),U6*2.75,IF(ISNUMBER(SEARCH("1.2mm",J:J)),U6*3.3,IF(ISNUMBER(SEARCH("Gasket",J:J)),U6,IF(ISNUMBER(SEARCH("Cleats",J:J)),U6,IF(ISNUMBER(SEARCH("Sealant",J:J)),U6,IF(ISNUMBER(SEARCH("Bracket",J:J)),U6,IF(ISNUMBER(SEARCH("Corner",J:J)),U6,IF(ISNUMBER(SEARCH("Bubble",J:J)),U6,"")))))))))))))))))) -> 25.748 | X6: =IF(ISNUMBER(SEARCH("26",J:J)),T6*3.925,IF(ISNUMBER(SEARCH("24",J:J)),T6*4.71,IF(ISNUMBER(SEARCH("22",J:J)),T6*6.28,IF(ISNUMBER(SEARCH("20",J:J)),T6*7.85,IF(ISNUMBER(SEARCH("18",J:J)),T6*9.42,IF(ISNUMBER(SEARCH("16",J:J)),T6*11.775,IF(ISNUMBER(SEARCH("Thermal",J:J)),"",IF(ISNUMBER(SEARCH("Acou",J:J)),"",IF(ISNUMBER(SEARCH("ss",J:J)),"",IF(ISNUMBER(SEARCH("0.8mm",J:J)),T6*2.2,IF(ISNUMBER(SEARCH("1mm",J:J)),T6*2.75,IF(ISNUMBER(SEARCH("1.2mm",J:J)),T6*3.3,IF(ISNUMBER(SEARCH("Gasket",J:J)),"",IF(ISNUMBER(SEARCH("Cleats",J:J)),"",IF(ISNUMBER(SEARCH("Sealant",J:J)),"",IF(ISNUMBER(SEARCH("Bracket",J:J)),"",IF(ISNUMBER(SEARCH("Corner",J:J)),"",IF(ISNUMBER(SEARCH("Bubble",J:J)),"","")))))))))))))))))) -> 69.708 | Y6: =IF(K6="Sqmt",(T6/O6)*100,IF(K6="Kg's","",IF(K6="No's","",IF(K6="Rmt","",IF(K6="Roll","",IF(K6="","")))))) -> 24.28884 | Z6: =IF(K6="Sqmt",(U6/O6)*100,IF(K6="Kg's","",IF(K6="No's","",IF(K6="Rmt","",IF(K6="Roll","",IF(K6="","")))))) -> 8.9715536 | AB6: =IFERROR((X6-AA6),"") -> 69.708
A7: =IF(C7="","",COUNTA($C$3:C7)) -> 5 | B7: =IF(C7="","",TEXT(C7,"mmmm")) -> April | C7: 44655 | D7: 2302-64005 | F7: 44616 | G7: Knnd Associates Pvt Ltd | H7: Google Kyoto West Second Floor Oval Duct | I7: Spiral Oval Duct with Paint | J7: 120gsm Slit 20G | K7: =IF(ISNUMBER(SEARCH("gsm",J:J)),"Sqmt",IF(ISNUMBER(SEARCH("Tape",J:J)),"Roll",IF(ISNUMBER(SEARCH("Thermal",J:J)),"Sqmt",IF(ISNUMBER(SEARCH("Acou",J:J)),"Sqmt",IF(ISNUMBER(SEARCH("ss",J:J)),"Sqmt",IF(ISNUMBER(SEARCH("Alu",J:J)),"Sqmt",IF(ISNUMBER(SEARCH("Gasket",J:J)),"Rmt",IF(ISNUMBER(SEARCH("Cleats",J:J)),"No's",IF(ISNUMBER(SEARCH("Tube",J:J)),"No's",IF(ISNUMBER(SEARCH("Bracket",J:J)),"No's",IF(ISNUMBER(SEARCH("Corner",J:J)),"No's",IF(ISNUMBER(SEARCH("MS",J:J)),"Kg's",IF(ISNUMBER(SEARCH("Bucket",J:J)),"Kg's",IF(ISNUMBER(SEARCH("stretch",J:J)),"Kg's",IF(ISNUMBER(SEARCH("Bubble",J:J)),"Roll",IF(ISNUMBER(SEARCH("JTR",J:J)),"Rmt",IF(ISNUMBER(SEARCH("Clamp",J:J)),"No's",IF(ISNUMBER(SEARCH("PIR",J:J)),"sqmt","")))))))))))))))))) -> Sqmt | L7: 169.2 | M7: 138.68852 | O7: =IF(ISNUMBER(SEARCH("gsm",J:J)),(M7+N7)*1.22,IF(ISNUMBER(SEARCH("Tape",J:J)),L7,IF(ISNUMBER(SEARCH("Thermal",J:J)),L7,IF(ISNUMBER(SEARCH("Acou",J:J)),L7,IF(ISNUMBER(SEARCH("ss",J:J)),L7,IF(ISNUMBER(SEARCH("Alu",J:J)),L7,IF(ISNUMBER(SEARCH("Gasket",J:J)),L7,IF(ISNUMBER(SEARCH("Cleats",J:J)),L7,IF(ISNUMBER(SEARCH("Tube",J:J)),L7,IF(ISNUMBER(SEARCH("Bracket",J:J)),L7,IF(ISNUMBER(SEARCH("Corner",J:J)),L7,IF(ISNUMBER(SEARCH("MS",J:J)),L7,IF(ISNUMBER(SEARCH("Bucket",J:J)),L7,IF(ISNUMBER(SEARCH("stretch",J:J)),L7,IF(ISNUMBER(SEARCH("Bubble",J:J)),L7,IF(ISNUMBER(SEARCH("JTR",J:J)),L7,IF(ISNUMBER(SEARCH("Clamp",J:J)),"No's",IF(ISNUMBER(SEARCH("PIR",J:J)),"sqmt","")))))))))))))))))) -> 169.2 | P7: 158.5 | Q7: 162.8 | T7: =(IF(K7="Sqmt",(O7-Q7),"")) -> 6.4 | U7: =(IF(K7="Sqmt",(O7-P7)-T7,IF(K7="Rmt","",IF(K7="Kg's","",IF(K7="No's","",IF(K7="Roll","","")))))) -> 4.3 | V7: =IF(ISNUMBER(SEARCH("26",J:J)),O7*3.925,IF(ISNUMBER(SEARCH("24",J:J)),O7*4.71,IF(ISNUMBER(SEARCH("22",J:J)),O7*6.28,IF(ISNUMBER(SEARCH("20",J:J)),O7*7.85,IF(ISNUMBER(SEARCH("18G",J:J)),O7*9.42,IF(ISNUMBER(SEARCH("16G",J:J)),O7*11.775,IF(ISNUMBER(SEARCH("Thermal",J:J)),O7,IF(ISNUMBER(SEARCH("Acou",J:J)),O7,IF(ISNUMBER(SEARCH("ss",J:J)),O7,IF(ISNUMBER(SEARCH("0.8mm",J:J)),O7*2.2,IF(ISNUMBER(SEARCH("1mm",J:J)),O7*2.75,IF(ISNUMBER(SEARCH("1.2mm",J:J)),O7*3.3,IF(ISNUMBER(SEARCH("Gasket",J:J)),O7,IF(ISNUMBER(SEARCH("Cleats",J:J)),O7,IF(ISNUMBER(SEARCH("Sealant",J:J)),O7,IF(ISNUMBER(SEARCH("Bracket",J:J)),O7,IF(ISNUMBER(SEARCH("Corner",J:J)),O7,IF(ISNUMBER(SEARCH("Bubble",J:J)),O7,"")))))))))))))))))) -> 1328.22 | W7: =IF(ISNUMBER(SEARCH("26",J:J)),U7*3.925,IF(ISNUMBER(SEARCH("24",J:J)),U7*4.71,IF(ISNUMBER(SEARCH("22",J:J)),U7*6.28,IF(ISNUMBER(SEARCH("20",J:J)),U7*7.85,IF(ISNUMBER(SEARCH("18G",J:J)),U7*9.42,IF(ISNUMBER(SEARCH("16G",J:J)),U7*11.775,IF(ISNUMBER(SEARCH("Thermal",J:J)),U7,IF(ISNUMBER(SEARCH("Acou",J:J)),U7,IF(ISNUMBER(SEARCH("ss",J:J)),U7,IF(ISNUMBER(SEARCH("0.8mm",J:J)),U7*2.2,IF(ISNUMBER(SEARCH("1mm",J:J)),U7*2.75,IF(ISNUMBER(SEARCH("1.2mm",J:J)),U7*3.3,IF(ISNUMBER(SEARCH("Gasket",J:J)),U7,IF(ISNUMBER(SEARCH("Cleats",J:J)),U7,IF(ISNUMBER(SEARCH("Sealant",J:J)),U7,IF(ISNUMBER(SEARCH("Bracket",J:J)),U7,IF(ISNUMBER(SEARCH("Corner",J:J)),U7,IF(ISNUMBER(SEARCH("Bubble",J:J)),U7,"")))))))))))))))))) -> 33.755 | X7: =IF(ISNUMBER(SEARCH("26",J:J)),T7*3.925,IF(ISNUMBER(SEARCH("24",J:J)),T7*4.71,IF(ISNUMBER(SEARCH("22",J:J)),T7*6.28,IF(ISNUMBER(SEARCH("20",J:J)),T7*7.85,IF(ISNUMBER(SEARCH("18",J:J)),T7*9.42,IF(ISNUMBER(SEARCH("16",J:J)),T7*11.775,IF(ISNUMBER(SEARCH("Thermal",J:J)),"",IF(ISNUMBER(SEARCH("Acou",J:J)),"",IF(ISNUMBER(SEARCH("ss",J:J)),"",IF(ISNUMBER(SEARCH("0.8mm",J:J)),T7*2.2,IF(ISNUMBER(SEARCH("1mm",J:J)),T7*2.75,IF(ISNUMBER(SEARCH("1.2mm",J:J)),T7*3.3,IF(ISNUMBER(SEARCH("Gasket",J:J)),"",IF(ISNUMBER(SEARCH("Cleats",J:J)),"",IF(ISNUMBER(SEARCH("Sealant",J:J)),"",IF(ISNUMBER(SEARCH("Bracket",J:J)),"",IF(ISNUMBER(SEARCH("Corner",J:J)),"",IF(ISNUMBER(SEARCH("Bubble",J:J)),"","")))))))))))))))))) -> 50.24 | Y7: =IF(K7="Sqmt",(T7/O7)*100,IF(K7="Kg's","",IF(K7="No's","",IF(K7="Rmt","",IF(K7="Roll","",IF(K7="","")))))) -> 3.7825059 | Z7: =IF(K7="Sqmt",(U7/O7)*100,IF(K7="Kg's","",IF(K7="No's","",IF(K7="Rmt","",IF(K7="Roll","",IF(K7="","")))))) -> 2.5413712 | AB7: =IFERROR((X7-AA7),"") -> 50.24
A8: =IF(C8="","",COUNTA($C$3:C8)) -> 6 | B8: =IF(C8="","",TEXT(C8,"mmmm")) -> April | C8: 44655 | D8: 2302-64005 | F8: 44616 | G8: Knnd Associates Pvt Ltd | H8: Google Kyoto West Second Floor Oval Duct | I8: Spiral Oval Duct with Paint | J8: 120gsm 20G | K8: =IF(ISNUMBER(SEARCH("gsm",J:J)),"Sqmt",IF(ISNUMBER(SEARCH("Tape",J:J)),"Roll",IF(ISNUMBER(SEARCH("Thermal",J:J)),"Sqmt",IF(ISNUMBER(SEARCH("Acou",J:J)),"Sqmt",IF(ISNUMBER(SEARCH("ss",J:J)),"Sqmt",IF(ISNUMBER(SEARCH("Alu",J:J)),"Sqmt",IF(ISNUMBER(SEARCH("Gasket",J:J)),"Rmt",IF(ISNUMBER(SEARCH("Cleats",J:J)),"No's",IF(ISNUMBER(SEARCH("Tube",J:J)),"No's",IF(ISNUMBER(SEARCH("Bracket",J:J)),"No's",IF(ISNUMBER(SEARCH("Corner",J:J)),"No's",IF(ISNUMBER(SEARCH("MS",J:J)),"Kg's",IF(ISNUMBER(SEARCH("Bucket",J:J)),"Kg's",IF(ISNUMBER(SEARCH("stretch",J:J)),"Kg's",IF(ISNUMBER(SEARCH("Bubble",J:J)),"Roll",IF(ISNUMBER(SEARCH("JTR",J:J)),"Rmt",IF(ISNUMBER(SEARCH("Clamp",J:J)),"No's",IF(ISNUMBER(SEARCH("PIR",J:J)),"sqmt","")))))))))))))))))) -> Sqmt | L8: 54 | N8: 44.262295 | O8: =IF(ISNUMBER(SEARCH("gsm",J:J)),(M8+N8)*1.22,IF(ISNUMBER(SEARCH("Tape",J:J)),L8,IF(ISNUMBER(SEARCH("Thermal",J:J)),L8,IF(ISNUMBER(SEARCH("Acou",J:J)),L8,IF(ISNUMBER(SEARCH("ss",J:J)),L8,IF(ISNUMBER(SEARCH("Alu",J:J)),L8,IF(ISNUMBER(SEARCH("Gasket",J:J)),L8,IF(ISNUMBER(SEARCH("Cleats",J:J)),L8,IF(ISNUMBER(SEARCH("Tube",J:J)),L8,IF(ISNUMBER(SEARCH("Bracket",J:J)),L8,IF(ISNUMBER(SEARCH("Corner",J:J)),L8,IF(ISNUMBER(SEARCH("MS",J:J)),L8,IF(ISNUMBER(SEARCH("Bucket",J:J)),L8,IF(ISNUMBER(SEARCH("stretch",J:J)),L8,IF(ISNUMBER(SEARCH("Bubble",J:J)),L8,IF(ISNUMBER(SEARCH("JTR",J:J)),L8,IF(ISNUMBER(SEARCH("Clamp",J:J)),"No's",IF(ISNUMBER(SEARCH("PIR",J:J)),"sqmt","")))))))))))))))))) -> 54 | P8: 34.7 | Q8: 36.1 | T8: =(IF(K8="Sqmt",(O8-Q8),"")) -> 17.9 | U8: =(IF(K8="Sqmt",(O8-P8)-T8,IF(K8="Rmt","",IF(K8="Kg's","",IF(K8="No's","",IF(K8="Roll","","")))))) -> 1.4 | V8: =IF(ISNUMBER(SEARCH("26",J:J)),O8*3.925,IF(ISNUMBER(SEARCH("24",J:J)),O8*4.71,IF(ISNUMBER(SEARCH("22",J:J)),O8*6.28,IF(ISNUMBER(SEARCH("20",J:J)),O8*7.85,IF(ISNUMBER(SEARCH("18G",J:J)),O8*9.42,IF(ISNUMBER(SEARCH("16G",J:J)),O8*11.775,IF(ISNUMBER(SEARCH("Thermal",J:J)),O8,IF(ISNUMBER(SEARCH("Acou",J:J)),O8,IF(ISNUMBER(SEARCH("ss",J:J)),O8,IF(ISNUMBER(SEARCH("0.8mm",J:J)),O8*2.2,IF(ISNUMBER(SEARCH("1mm",J:J)),O8*2.75,IF(ISNUMBER(SEARCH("1.2mm",J:J)),O8*3.3,IF(ISNUMBER(SEARCH("Gasket",J:J)),O8,IF(ISNUMBER(SEARCH("Cleats",J:J)),O8,IF(ISNUMBER(SEARCH("Sealant",J:J)),O8,IF(ISNUMBER(SEARCH("Bracket",J:J)),O8,IF(ISNUMBER(SEARCH("Corner",J:J)),O8,IF(ISNUMBER(SEARCH("Bubble",J:J)),O8,"")))))))))))))))))) -> 423.9 | W8: =IF(ISNUMBER(SEARCH("26",J:J)),U8*3.925,IF(ISNUMBER(SEARCH("24",J:J)),U8*4.71,IF(ISNUMBER(SEARCH("22",J:J)),U8*6.28,IF(ISNUMBER(SEARCH("20",J:J)),U8*7.85,IF(ISNUMBER(SEARCH("18G",J:J)),U8*9.42,IF(ISNUMBER(SEARCH("16G",J:J)),U8*11.775,IF(ISNUMBER(SEARCH("Thermal",J:J)),U8,IF(ISNUMBER(SEARCH("Acou",J:J)),U8,IF(ISNUMBER(SEARCH("ss",J:J)),U8,IF(ISNUMBER(SEARCH("0.8mm",J:J)),U8*2.2,IF(ISNUMBER(SEARCH("1mm",J:J)),U8*2.75,IF(ISNUMBER(SEARCH("1.2mm",J:J)),U8*3.3,IF(ISNUMBER(SEARCH("Gasket",J:J)),U8,IF(ISNUMBER(SEARCH("Cleats",J:J)),U8,IF(ISNUMBER(SEARCH("Sealant",J:J)),U8,IF(ISNUMBER(SEARCH("Bracket",J:J)),U8,IF(ISNUMBER(SEARCH("Corner",J:J)),U8,IF(ISNUMBER(SEARCH("Bubble",J:J)),U8,"")))))))))))))))))) -> 10.99 | X8: =IF(ISNUMBER(SEARCH("26",J:J)),T8*3.925,IF(ISNUMBER(SEARCH("24",J:J)),T8*4.71,IF(ISNUMBER(SEARCH("22",J:J)),T8*6.28,IF(ISNUMBER(SEARCH("20",J:J)),T8*7.85,IF(ISNUMBER(SEARCH("18",J:J)),T8*9.42,IF(ISNUMBER(SEARCH("16",J:J)),T8*11.775,IF(ISNUMBER(SEARCH("Thermal",J:J)),"",IF(ISNUMBER(SEARCH("Acou",J:J)),"",IF(ISNUMBER(SEARCH("ss",J:J)),"",IF(ISNUMBER(SEARCH("0.8mm",J:J)),T8*2.2,IF(ISNUMBER(SEARCH("1mm",J:J)),T8*2.75,IF(ISNUMBER(SEARCH("1.2mm",J:J)),T8*3.3,IF(ISNUMBER(SEARCH("Gasket",J:J)),"",IF(ISNUMBER(SEARCH("Cleats",J:J)),"",IF(ISNUMBER(SEARCH("Sealant",J:J)),"",IF(ISNUMBER(SEARCH("Bracket",J:J)),"",IF(ISNUMBER(SEARCH("Corner",J:J)),"",IF(ISNUMBER(SEARCH("Bubble",J:J)),"","")))))))))))))))))) -> 140.515 | Y8: =IF(K8="Sqmt",(T8/O8)*100,IF(K8="Kg's","",IF(K8="No's","",IF(K8="Rmt","",IF(K8="Roll","",IF(K8="","")))))) -> 33.148148 | Z8: =IF(K8="Sqmt",(U8/O8)*100,IF(K8="Kg's","",IF(K8="No's","",IF(K8="Rmt","",IF(K8="Roll","",IF(K8="","")))))) -> 2.5925926 | AB8: =IFERROR((X8-AA8),"") -> 140.515
A9: =IF(C9="","",COUNTA($C$3:C9)) -> 7 | B9: =IF(C9="","",TEXT(C9,"mmmm")) -> April | C9: 44655 | D9: 2302-64005 | F9: 44616 | G9: Knnd Associates Pvt Ltd | H9: Google Kyoto West Second Floor Oval Duct | I9: H Bracket | J9: H Bracket | K9: =IF(ISNUMBER(SEARCH("gsm",J:J)),"Sqmt",IF(ISNUMBER(SEARCH("Tape",J:J)),"Roll",IF(ISNUMBER(SEARCH("Thermal",J:J)),"Sqmt",IF(ISNUMBER(SEARCH("Acou",J:J)),"Sqmt",IF(ISNUMBER(SEARCH("ss",J:J)),"Sqmt",IF(ISNUMBER(SEARCH("Alu",J:J)),"Sqmt",IF(ISNUMBER(SEARCH("Gasket",J:J)),"Rmt",IF(ISNUMBER(SEARCH("Cleats",J:J)),"No's",IF(ISNUMBER(SEARCH("Tube",J:J)),"No's",IF(ISNUMBER(SEARCH("Bracket",J:J)),"No's",IF(ISNUMBER(SEARCH("Corner",J:J)),"No's",IF(ISNUMBER(SEARCH("MS",J:J)),"Kg's",IF(ISNUMBER(SEARCH("Bucket",J:J)),"Kg's",IF(ISNUMBER(SEARCH("stretch",J:J)),"Kg's",IF(ISNUMBER(SEARCH("Bubble",J:J)),"Roll",IF(ISNUMBER(SEARCH("JTR",J:J)),"Rmt",IF(ISNUMBER(SEARCH("Clamp",J:J)),"No's",IF(ISNUMBER(SEARCH("PIR",J:J)),"sqmt","")))))))))))))))))) -> No's | L9: 78 | O9: =IF(ISNUMBER(SEARCH("gsm",J:J)),(M9+N9)*1.22,IF(ISNUMBER(SEARCH("Tape",J:J)),L9,IF(ISNUMBER(SEARCH("Thermal",J:J)),L9,IF(ISNUMBER(SEARCH("Acou",J:J)),L9,IF(ISNUMBER(SEARCH("ss",J:J)),L9,IF(ISNUMBER(SEARCH("Alu",J:J)),L9,IF(ISNUMBER(SEARCH("Gasket",J:J)),L9,IF(ISNUMBER(SEARCH("Cleats",J:J)),L9,IF(ISNUMBER(SEARCH("Tube",J:J)),L9,IF(ISNUMBER(SEARCH("Bracket",J:J)),L9,IF(ISNUMBER(SEARCH("Corner",J:J)),L9,IF(ISNUMBER(SEARCH("MS",J:J)),L9,IF(ISNUMBER(SEARCH("Bucket",J:J)),L9,IF(ISNUMBER(SEARCH("stretch",J:J)),L9,IF(ISNUMBER(SEARCH("Bubble",J:J)),L9,IF(ISNUMBER(SEARCH("JTR",J:J)),L9,IF(ISNUMBER(SEARCH("Clamp",J:J)),"No's",IF(ISNUMBER(SEARCH("PIR",J:J)),"sqmt","")))))))))))))))))) -> 78 | P9: 78 | T9: =(IF(K9="Sqmt",(O9-Q9),"")) | U9: =(IF(K9="Sqmt",(O9-P9)-T9,IF(K9="Rmt","",IF(K9="Kg's","",IF(K9="No's","",IF(K9="Roll","","")))))) | V9: =IF(ISNUMBER(SEARCH("26",J:J)),O9*3.925,IF(ISNUMBER(SEARCH("24",J:J)),O9*4.71,IF(ISNUMBER(SEARCH("22",J:J)),O9*6.28,IF(ISNUMBER(SEARCH("20",J:J)),O9*7.85,IF(ISNUMBER(SEARCH("18G",J:J)),O9*9.42,IF(ISNUMBER(SEARCH("16G",J:J)),O9*11.775,IF(ISNUMBER(SEARCH("Thermal",J:J)),O9,IF(ISNUMBER(SEARCH("Acou",J:J)),O9,IF(ISNUMBER(SEARCH("ss",J:J)),O9,IF(ISNUMBER(SEARCH("0.8mm",J:J)),O9*2.2,IF(ISNUMBER(SEARCH("1mm",J:J)),O9*2.75,IF(ISNUMBER(SEARCH("1.2mm",J:J)),O9*3.3,IF(ISNUMBER(SEARCH("Gasket",J:J)),O9,IF(ISNUMBER(SEARCH("Cleats",J:J)),O9,IF(ISNUMBER(SEARCH("Sealant",J:J)),O9,IF(ISNUMBER(SEARCH("Bracket",J:J)),O9,IF(ISNUMBER(SEARCH("Corner",J:J)),O9,IF(ISNUMBER(SEARCH("Bubble",J:J)),O9,"")))))))))))))))))) -> 78 | W9: =IF(ISNUMBER(SEARCH("26",J:J)),U9*3.925,IF(ISNUMBER(SEARCH("24",J:J)),U9*4.71,IF(ISNUMBER(SEARCH("22",J:J)),U9*6.28,IF(ISNUMBER(SEARCH("20",J:J)),U9*7.85,IF(ISNUMBER(SEARCH("18G",J:J)),U9*9.42,IF(ISNUMBER(SEARCH("16G",J:J)),U9*11.775,IF(ISNUMBER(SEARCH("Thermal",J:J)),U9,IF(ISNUMBER(SEARCH("Acou",J:J)),U9,IF(ISNUMBER(SEARCH("ss",J:J)),U9,IF(ISNUMBER(SEARCH("0.8mm",J:J)),U9*2.2,IF(ISNUMBER(SEARCH("1mm",J:J)),U9*2.75,IF(ISNUMBER(SEARCH("1.2mm",J:J)),U9*3.3,IF(ISNUMBER(SEARCH("Gasket",J:J)),U9,IF(ISNUMBER(SEARCH("Cleats",J:J)),U9,IF(ISNUMBER(SEARCH("Sealant",J:J)),U9,IF(ISNUMBER(SEARCH("Bracket",J:J)),U9,IF(ISNUMBER(SEARCH("Corner",J:J)),U9,IF(ISNUMBER(SEARCH("Bubble",J:J)),U9,"")))))))))))))))))) | X9: =IF(ISNUMBER(SEARCH("26",J:J)),T9*3.925,IF(ISNUMBER(SEARCH("24",J:J)),T9*4.71,IF(ISNUMBER(SEARCH("22",J:J)),T9*6.28,IF(ISNUMBER(SEARCH("20",J:J)),T9*7.85,IF(ISNUMBER(SEARCH("18",J:J)),T9*9.42,IF(ISNUMBER(SEARCH("16",J:J)),T9*11.775,IF(ISNUMBER(SEARCH("Thermal",J:J)),"",IF(ISNUMBER(SEARCH("Acou",J:J)),"",IF(ISNUMBER(SEARCH("ss",J:J)),"",IF(ISNUMBER(SEARCH("0.8mm",J:J)),T9*2.2,IF(ISNUMBER(SEARCH("1mm",J:J)),T9*2.75,IF(ISNUMBER(SEARCH("1.2mm",J:J)),T9*3.3,IF(ISNUMBER(SEARCH("Gasket",J:J)),"",IF(ISNUMBER(SEARCH("Cleats",J:J)),"",IF(ISNUMBER(SEARCH("Sealant",J:J)),"",IF(ISNUMBER(SEARCH("Bracket",J:J)),"",IF(ISNUMBER(SEARCH("Corner",J:J)),"",IF(ISNUMBER(SEARCH("Bubble",J:J)),"","")))))))))))))))))) | Y9: =IF(K9="Sqmt",(T9/O9)*100,IF(K9="Kg's","",IF(K9="No's","",IF(K9="Rmt","",IF(K9="Roll","",IF(K9="","")))))) | Z9: =IF(K9="Sqmt",(U9/O9)*100,IF(K9="Kg's","",IF(K9="No's","",IF(K9="Rmt","",IF(K9="Roll","",IF(K9="","")))))) | AB9: =IFERROR((X9-AA9),"")
A10: =IF(C10="","",COUNTA($C$3:C10)) -> 8 | B10: =IF(C10="","",TEXT(C10,"mmmm")) -> April | C10: 44655 | D10: 2302-64005 | F10: 44616 | G10: Knnd Associates Pvt Ltd | H10: Google Kyoto West Second Floor Oval Duct | I10: Corners | J10: Corner 32mm | K10: =IF(ISNUMBER(SEARCH("gsm",J:J)),"Sqmt",IF(ISNUMBER(SEARCH("Tape",J:J)),"Roll",IF(ISNUMBER(SEARCH("Thermal",J:J)),"Sqmt",IF(ISNUMBER(SEARCH("Acou",J:J)),"Sqmt",IF(ISNUMBER(SEARCH("ss",J:J)),"Sqmt",IF(ISNUMBER(SEARCH("Alu",J:J)),"Sqmt",IF(ISNUMBER(SEARCH("Gasket",J:J)),"Rmt",IF(ISNUMBER(SEARCH("Cleats",J:J)),"No's",IF(ISNUMBER(SEARCH("Tube",J:J)),"No's",IF(ISNUMBER(SEARCH("Bracket",J:J)),"No's",IF(ISNUMBER(SEARCH("Corner",J:J)),"No's",IF(ISNUMBER(SEARCH("MS",J:J)),"Kg's",IF(ISNUMBER(SEARCH("Bucket",J:J)),"Kg's",IF(ISNUMBER(SEARCH("stretch",J:J)),"Kg's",IF(ISNUMBER(SEARCH("Bubble",J:J)),"Roll",IF(ISNUMBER(SEARCH("JTR",J:J)),"Rmt",IF(ISNUMBER(SEARCH("Clamp",J:J)),"No's",IF(ISNUMBER(SEARCH("PIR",J:J)),"sqmt","")))))))))))))))))) -> No's | L10: 60 | O10: =IF(ISNUMBER(SEARCH("gsm",J:J)),(M10+N10)*1.22,IF(ISNUMBER(SEARCH("Tape",J:J)),L10,IF(ISNUMBER(SEARCH("Thermal",J:J)),L10,IF(ISNUMBER(SEARCH("Acou",J:J)),L10,IF(ISNUMBER(SEARCH("ss",J:J)),L10,IF(ISNUMBER(SEARCH("Alu",J:J)),L10,IF(ISNUMBER(SEARCH("Gasket",J:J)),L10,IF(ISNUMBER(SEARCH("Cleats",J:J)),L10,IF(ISNUMBER(SEARCH("Tube",J:J)),L10,IF(ISNUMBER(SEARCH("Bracket",J:J)),L10,IF(ISNUMBER(SEARCH("Corner",J:J)),L10,IF(ISNUMBER(SEARCH("MS",J:J)),L10,IF(ISNUMBER(SEARCH("Bucket",J:J)),L10,IF(ISNUMBER(SEARCH("stretch",J:J)),L10,IF(ISNUMBER(SEARCH("Bubble",J:J)),L10,IF(ISNUMBER(SEARCH("JTR",J:J)),L10,IF(ISNUMBER(SEARCH("Clamp",J:J)),"No's",IF(ISNUMBER(SEARCH("PIR",J:J)),"sqmt","")))))))))))))))))) -> 60 | T10: =(IF(K10="Sqmt",(O10-Q10),"")) | U10: =(IF(K10="Sqmt",(O10-P10)-T10,IF(K10="Rmt","",IF(K10="Kg's","",IF(K10="No's","",IF(K10="Roll","","")))))) | V10: =IF(ISNUMBER(SEARCH("26",J:J)),O10*3.925,IF(ISNUMBER(SEARCH("24",J:J)),O10*4.71,IF(ISNUMBER(SEARCH("22",J:J)),O10*6.28,IF(ISNUMBER(SEARCH("20",J:J)),O10*7.85,IF(ISNUMBER(SEARCH("18G",J:J)),O10*9.42,IF(ISNUMBER(SEARCH("16G",J:J)),O10*11.775,IF(ISNUMBER(SEARCH("Thermal",J:J)),O10,IF(ISNUMBER(SEARCH("Acou",J:J)),O10,IF(ISNUMBER(SEARCH("ss",J:J)),O10,IF(ISNUMBER(SEARCH("0.8mm",J:J)),O10*2.2,IF(ISNUMBER(SEARCH("1mm",J:J)),O10*2.75,IF(ISNUMBER(SEARCH("1.2mm",J:J)),O10*3.3,IF(ISNUMBER(SEARCH("Gasket",J:J)),O10,IF(ISNUMBER(SEARCH("Cleats",J:J)),O10,IF(ISNUMBER(SEARCH("Sealant",J:J)),O10,IF(ISNUMBER(SEARCH("Bracket",J:J)),O10,IF(ISNUMBER(SEARCH("Corner",J:J)),O10,IF(ISNUMBER(SEARCH("Bubble",J:J)),O10,"")))))))))))))))))) -> 60 | W10: =IF(ISNUMBER(SEARCH("26",J:J)),U10*3.925,IF(ISNUMBER(SEARCH("24",J:J)),U10*4.71,IF(ISNUMBER(SEARCH("22",J:J)),U10*6.28,IF(ISNUMBER(SEARCH("20",J:J)),U10*7.85,IF(ISNUMBER(SEARCH("18G",J:J)),U10*9.42,IF(ISNUMBER(SEARCH("16G",J:J)),U10*11.775,IF(ISNUMBER(SEARCH("Thermal",J:J)),U10,IF(ISNUMBER(SEARCH("Acou",J:J)),U10,IF(ISNUMBER(SEARCH("ss",J:J)),U10,IF(ISNUMBER(SEARCH("0.8mm",J:J)),U10*2.2,IF(ISNUMBER(SEARCH("1mm",J:J)),U10*2.75,IF(ISNUMBER(SEARCH("1.2mm",J:J)),U10*3.3,IF(ISNUMBER(SEARCH("Gasket",J:J)),U10,IF(ISNUMBER(SEARCH("Cleats",J:J)),U10,IF(ISNUMBER(SEARCH("Sealant",J:J)),U10,IF(ISNUMBER(SEARCH("Bracket",J:J)),U10,IF(ISNUMBER(SEARCH("Corner",J:J)),U10,IF(ISNUMBER(SEARCH("Bubble",J:J)),U10,"")))))))))))))))))) | X10: =IF(ISNUMBER(SEARCH("26",J:J)),T10*3.925,IF(ISNUMBER(SEARCH("24",J:J)),T10*4.71,IF(ISNUMBER(SEARCH("22",J:J)),T10*6.28,IF(ISNUMBER(SEARCH("20",J:J)),T10*7.85,IF(ISNUMBER(SEARCH("18",J:J)),T10*9.42,IF(ISNUMBER(SEARCH("16",J:J)),T10*11.775,IF(ISNUMBER(SEARCH("Thermal",J:J)),"",IF(ISNUMBER(SEARCH("Acou",J:J)),"",IF(ISNUMBER(SEARCH("ss",J:J)),"",IF(ISNUMBER(SEARCH("0.8mm",J:J)),T10*2.2,IF(ISNUMBER(SEARCH("1mm",J:J)),T10*2.75,IF(ISNUMBER(SEARCH("1.2mm",J:J)),T10*3.3,IF(ISNUMBER(SEARCH("Gasket",J:J)),"",IF(ISNUMBER(SEARCH("Cleats",J:J)),"",IF(ISNUMBER(SEARCH("Sealant",J:J)),"",IF(ISNUMBER(SEARCH("Bracket",J:J)),"",IF(ISNUMBER(SEARCH("Corner",J:J)),"",IF(ISNUMBER(SEARCH("Bubble",J:J)),"","")))))))))))))))))) | Y10: =IF(K10="Sqmt",(T10/O10)*100,IF(K10="Kg's","",IF(K10="No's","",IF(K10="Rmt","",IF(K10="Roll","",IF(K10="","")))))) | Z10: =IF(K10="Sqmt",(U10/O10)*100,IF(K10="Kg's","",IF(K10="No's","",IF(K10="Rmt","",IF(K10="Roll","",IF(K10="","")))))) | AB10: =IFERROR((X10-AA10),"")
A11: =IF(C11="","",COUNTA($C$3:C11)) -> 9 | B11: =IF(C11="","",TEXT(C11,"mmmm")) -> April | C11: 44656 | D11: 0103-64003 | F11: 44302 | G11: Knnd Associates Pvt Ltd | H11: Prestige Rex Walk Extra Duct ( 275 Gsm ) 24.03.2022 | I11: Box Duct with TDF | J11: 275gsm 22G | K11: =IF(ISNUMBER(SEARCH("gsm",J:J)),"Sqmt",IF(ISNUMBER(SEARCH("Tape",J:J)),"Roll",IF(ISNUMBER(SEARCH("Thermal",J:J)),"Sqmt",IF(ISNUMBER(SEARCH("Acou",J:J)),"Sqmt",IF(ISNUMBER(SEARCH("ss",J:J)),"Sqmt",IF(ISNUMBER(SEARCH("Alu",J:J)),"Sqmt",IF(ISNUMBER(SEARCH("Gasket",J:J)),"Rmt",IF(ISNUMBER(SEARCH("Cleats",J:J)),"No's",IF(ISNUMBER(SEARCH("Tube",J:J)),"No's",IF(ISNUMBER(SEARCH("Bracket",J:J)),"No's",IF(ISNUMBER(SEARCH("Corner",J:J)),"No's",IF(ISNUMBER(SEARCH("MS",J:J)),"Kg's",IF(ISNUMBER(SEARCH("Bucket",J:J)),"Kg's",IF(ISNUMBER(SEARCH("stretch",J:J)),"Kg's",IF(ISNUMBER(SEARCH("Bubble",J:J)),"Roll",IF(ISNUMBER(SEARCH("JTR",J:J)),"Rmt",IF(ISNUMBER(SEARCH("Clamp",J:J)),"No's",IF(ISNUMBER(SEARCH("PIR",J:J)),"sqmt","")))))))))))))))))) -> Sqmt | L11: 217.7 | M11: 74.56 | N11: 105.74 | O11: =IF(ISNUMBER(SEARCH("gsm",J:J)),(M11+N11)*1.22,IF(ISNUMBER(SEARCH("Tape",J:J)),L11,IF(ISNUMBER(SEARCH("Thermal",J:J)),L11,IF(ISNUMBER(SEARCH("Acou",J:J)),L11,IF(ISNUMBER(SEARCH("ss",J:J)),L11,IF(ISNUMBER(SEARCH("Alu",J:J)),L11,IF(ISNUMBER(SEARCH("Gasket",J:J)),L11,IF(ISNUMBER(SEARCH("Cleats",J:J)),L11,IF(ISNUMBER(SEARCH("Tube",J:J)),L11,IF(ISNUMBER(SEARCH("Bracket",J:J)),L11,IF(ISNUMBER(SEARCH("Corner",J:J)),L11,IF(ISNUMBER(SEARCH("MS",J:J)),L11,IF(ISNUMBER(SEARCH("Bucket",J:J)),L11,IF(ISNUMBER(SEARCH("stretch",J:J)),L11,IF(ISNUMBER(SEARCH("Bubble",J:J)),L11,IF(ISNUMBER(SEARCH("JTR",J:J)),L11,IF(ISNUMBER(SEARCH("Clamp",J:J)),"No's",IF(ISNUMBER(SEARCH("PIR",J:J)),"sqmt","")))))))))))))))))) -> 219.966 | P11: 166.9 | Q11: 190.3 | R11: 35 | S11: 65 | T11: =(IF(K11="Sqmt",(O11-Q11),"")) -> 29.666 | U11: =(IF(K11="Sqmt",(O11-P11)-T11,IF(K11="Rmt","",IF(K11="Kg's","",IF(K11="No's","",IF(K11="Roll","","")))))) -> 23.4 | V11: =IF(ISNUMBER(SEARCH("26",J:J)),O11*3.925,IF(ISNUMBER(SEARCH("24",J:J)),O11*4.71,IF(ISNUMBER(SEARCH("22",J:J)),O11*6.28,IF(ISNUMBER(SEARCH("20",J:J)),O11*7.85,IF(ISNUMBER(SEARCH("18G",J:J)),O11*9.42,IF(ISNUMBER(SEARCH("16G",J:J)),O11*11.775,IF(ISNUMBER(SEARCH("Thermal",J:J)),O11,IF(ISNUMBER(SEARCH("Acou",J:J)),O11,IF(ISNUMBER(SEARCH("ss",J:J)),O11,IF(ISNUMBER(SEARCH("0.8mm",J:J)),O11*2.2,IF(ISNUMBER(SEARCH("1mm",J:J)),O11*2.75,IF(ISNUMBER(SEARCH("1.2mm",J:J)),O11*3.3,IF(ISNUMBER(SEARCH("Gasket",J:J)),O11,IF(ISNUMBER(SEARCH("Cleats",J:J)),O11,IF(ISNUMBER(SEARCH("Sealant",J:J)),O11,IF(ISNUMBER(SEARCH("Bracket",J:J)),O11,IF(ISNUMBER(SEARCH("Corner",J:J)),O11,IF(ISNUMBER(SEARCH("Bubble",J:J)),O11,"")))))))))))))))))) -> 1381.3865 | W11: =IF(ISNUMBER(SEARCH("26",J:J)),U11*3.925,IF(ISNUMBER(SEARCH("24",J:J)),U11*4.71,IF(ISNUMBER(SEARCH("22",J:J)),U11*6.28,IF(ISNUMBER(SEARCH("20",J:J)),U11*7.85,IF(ISNUMBER(SEARCH("18G",J:J)),U11*9.42,IF(ISNUMBER(SEARCH("16G",J:J)),U11*11.775,IF(ISNUMBER(SEARCH("Thermal",J:J)),U11,IF(ISNUMBER(SEARCH("Acou",J:J)),U11,IF(ISNUMBER(SEARCH("ss",J:J)),U11,IF(ISNUMBER(SEARCH("0.8mm",J:J)),U11*2.2,IF(ISNUMBER(SEARCH("1mm",J:J)),U11*2.75,IF(ISNUMBER(SEARCH("1.2mm",J:J)),U11*3.3,IF(ISNUMBER(SEARCH("Gasket",J:J)),U11,IF(ISNUMBER(SEARCH("Cleats",J:J)),U11,IF(ISNUMBER(SEARCH("Sealant",J:J)),U11,IF(ISNUMBER(SEARCH("Bracket",J:J)),U11,IF(ISNUMBER(SEARCH("Corner",J:J)),U11,IF(ISNUMBER(SEARCH("Bubble",J:J)),U11,"")))))))))))))))))) -> 146.952 | X11: =IF(ISNUMBER(SEARCH("26",J:J)),T11*3.925,IF(ISNUMBER(SEARCH("24",J:J)),T11*4.71,IF(ISNUMBER(SEARCH("22",J:J)),T11*6.28,IF(ISNUMBER(SEARCH("20",J:J)),T11*7.85,IF(ISNUMBER(SEARCH("18",J:J)),T11*9.42,IF(ISNUMBER(SEARCH("16",J:J)),T11*11.775,IF(ISNUMBER(SEARCH("Thermal",J:J)),"",IF(ISNUMBER(SEARCH("Acou",J:J)),"",IF(ISNUMBER(SEARCH("ss",J:J)),"",IF(ISNUMBER(SEARCH("0.8mm",J:J)),T11*2.2,IF(ISNUMBER(SEARCH("1mm",J:J)),T11*2.75,IF(ISNUMBER(SEARCH("1.2mm",J:J)),T11*3.3,IF(ISNUMBER(SEARCH("Gasket",J:J)),"",IF(ISNUMBER(SEARCH("Cleats",J:J)),"",IF(ISNUMBER(SEARCH("Sealant",J:J)),"",IF(ISNUMBER(SEARCH("Bracket",J:J)),"",IF(ISNUMBER(SEARCH("Corner",J:J)),"",IF(ISNUMBER(SEARCH("Bubble",J:J)),"","")))))))))))))))))) -> 186.30248 | Y11: =IF(K11="Sqmt",(T11/O11)*100,IF(K11="Kg's","",IF(K11="No's","",IF(K11="Rmt","",IF(K11="Roll","",IF(K11="","")))))) -> 13.48663 | Z11: =IF(K11="Sqmt",(U11/O11)*100,IF(K11="Kg's","",IF(K11="No's","",IF(K11="Rmt","",IF(K11="Roll","",IF(K11="","")))))) -> 10.638008 | AB11: =IFERROR((X11-AA11),"") -> 186.30248 | AC11: Site Measurement
A12: =IF(C12="","",COUNTA($C$3:C12)) -> 10 | B12: =IF(C12="","",TEXT(C12,"mmmm")) -> April | C12: 44656 | D12: 0103-64003 | F12: 44302 | G12: Knnd Associates Pvt Ltd | H12: Prestige Rex Walk Extra Duct ( 275 Gsm ) 24.03.2022 | I12: Corners | J12: Corner 32mm | K12: =IF(ISNUMBER(SEARCH("gsm",J:J)),"Sqmt",IF(ISNUMBER(SEARCH("Tape",J:J)),"Roll",IF(ISNUMBER(SEARCH("Thermal",J:J)),"Sqmt",IF(ISNUMBER(SEARCH("Acou",J:J)),"Sqmt",IF(ISNUMBER(SEARCH("ss",J:J)),"Sqmt",IF(ISNUMBER(SEARCH("Alu",J:J)),"Sqmt",IF(ISNUMBER(SEARCH("Gasket",J:J)),"Rmt",IF(ISNUMBER(SEARCH("Cleats",J:J)),"No's",IF(ISNUMBER(SEARCH("Tube",J:J)),"No's",IF(ISNUMBER(SEARCH("Bracket",J:J)),"No's",IF(ISNUMBER(SEARCH("Corner",J:J)),"No's",IF(ISNUMBER(SEARCH("MS",J:J)),"Kg's",IF(ISNUMBER(SEARCH("Bucket",J:J)),"Kg's",IF(ISNUMBER(SEARCH("stretch",J:J)),"Kg's",IF(ISNUMBER(SEARCH("Bubble",J:J)),"Roll",IF(ISNUMBER(SEARCH("JTR",J:J)),"Rmt",IF(ISNUMBER(SEARCH("Clamp",J:J)),"No's",IF(ISNUMBER(SEARCH("PIR",J:J)),"sqmt","")))))))))))))))))) -> No's | L12: 416 | O12: =IF(ISNUMBER(SEARCH("gsm",J:J)),(M12+N12)*1.22,IF(ISNUMBER(SEARCH("Tape",J:J)),L12,IF(ISNUMBER(SEARCH("Thermal",J:J)),L12,IF(ISNUMBER(SEARCH("Acou",J:J)),L12,IF(ISNUMBER(SEARCH("ss",J:J)),L12,IF(ISNUMBER(SEARCH("Alu",J:J)),L12,IF(ISNUMBER(SEARCH("Gasket",J:J)),L12,IF(ISNUMBER(SEARCH("Cleats",J:J)),L12,IF(ISNUMBER(SEARCH("Tube",J:J)),L12,IF(ISNUMBER(SEARCH("Bracket",J:J)),L12,IF(ISNUMBER(SEARCH("Corner",J:J)),L12,IF(ISNUMBER(SEARCH("MS",J:J)),L12,IF(ISNUMBER(SEARCH("Bucket",J:J)),L12,IF(ISNUMBER(SEARCH("stretch",J:J)),L12,IF(ISNUMBER(SEARCH("Bubble",J:J)),L12,IF(ISNUMBER(SEARCH("JTR",J:J)),L12,IF(ISNUMBER(SEARCH("Clamp",J:J)),"No's",IF(ISNUMBER(SEARCH("PIR",J:J)),"sqmt","")))))))))))))))))) -> 416 | T12: =(IF(K12="Sqmt",(O12-Q12),"")) | U12: =(IF(K12="Sqmt",(O12-P12)-T12,IF(K12="Rmt","",IF(K12="Kg's","",IF(K12="No's","",IF(K12="Roll","","")))))) | V12: =IF(ISNUMBER(SEARCH("26",J:J)),O12*3.925,IF(ISNUMBER(SEARCH("24",J:J)),O12*4.71,IF(ISNUMBER(SEARCH("22",J:J)),O12*6.28,IF(ISNUMBER(SEARCH("20",J:J)),O12*7.85,IF(ISNUMBER(SEARCH("18G",J:J)),O12*9.42,IF(ISNUMBER(SEARCH("16G",J:J)),O12*11.775,IF(ISNUMBER(SEARCH("Thermal",J:J)),O12,IF(ISNUMBER(SEARCH("Acou",J:J)),O12,IF(ISNUMBER(SEARCH("ss",J:J)),O12,IF(ISNUMBER(SEARCH("0.8mm",J:J)),O12*2.2,IF(ISNUMBER(SEARCH("1mm",J:J)),O12*2.75,IF(ISNUMBER(SEARCH("1.2mm",J:J)),O12*3.3,IF(ISNUMBER(SEARCH("Gasket",J:J)),O12,IF(ISNUMBER(SEARCH("Cleats",J:J)),O12,IF(ISNUMBER(SEARCH("Sealant",J:J)),O12,IF(ISNUMBER(SEARCH("Bracket",J:J)),O12,IF(ISNUMBER(SEARCH("Corner",J:J)),O12,IF(ISNUMBER(SEARCH("Bubble",J:J)),O12,"")))))))))))))))))) -> 416 | W12: =IF(ISNUMBER(SEARCH("26",J:J)),U12*3.925,IF(ISNUMBER(SEARCH("24",J:J)),U12*4.71,IF(ISNUMBER(SEARCH("22",J:J)),U12*6.28,IF(ISNUMBER(SEARCH("20",J:J)),U12*7.85,IF(ISNUMBER(SEARCH("18G",J:J)),U12*9.42,IF(ISNUMBER(SEARCH("16G",J:J)),U12*11.775,IF(ISNUMBER(SEARCH("Thermal",J:J)),U12,IF(ISNUMBER(SEARCH("Acou",J:J)),U12,IF(ISNUMBER(SEARCH("ss",J:J)),U12,IF(ISNUMBER(SEARCH("0.8mm",J:J)),U12*2.2,IF(ISNUMBER(SEARCH("1mm",J:J)),U12*2.75,IF(ISNUMBER(SEARCH("1.2mm",J:J)),U12*3.3,IF(ISNUMBER(SEARCH("Gasket",J:J)),U12,IF(ISNUMBER(SEARCH("Cleats",J:J)),U12,IF(ISNUMBER(SEARCH("Sealant",J:J)),U12,IF(ISNUMBER(SEARCH("Bracket",J:J)),U12,IF(ISNUMBER(SEARCH("Corner",J:J)),U12,IF(ISNUMBER(SEARCH("Bubble",J:J)),U12,"")))))))))))))))))) | X12: =IF(ISNUMBER(SEARCH("26",J:J)),T12*3.925,IF(ISNUMBER(SEARCH("24",J:J)),T12*4.71,IF(ISNUMBER(SEARCH("22",J:J)),T12*6.28,IF(ISNUMBER(SEARCH("20",J:J)),T12*7.85,IF(ISNUMBER(SEARCH("18",J:J)),T12*9.42,IF(ISNUMBER(SEARCH("16",J:J)),T12*11.775,IF(ISNUMBER(SEARCH("Thermal",J:J)),"",IF(ISNUMBER(SEARCH("Acou",J:J)),"",IF(ISNUMBER(SEARCH("ss",J:J)),"",IF(ISNUMBER(SEARCH("0.8mm",J:J)),T12*2.2,IF(ISNUMBER(SEARCH("1mm",J:J)),T12*2.75,IF(ISNUMBER(SEARCH("1.2mm",J:J)),T12*3.3,IF(ISNUMBER(SEARCH("Gasket",J:J)),"",IF(ISNUMBER(SEARCH("Cleats",J:J)),"",IF(ISNUMBER(SEARCH("Sealant",J:J)),"",IF(ISNUMBER(SEARCH("Bracket",J:J)),"",IF(ISNUMBER(SEARCH("Corner",J:J)),"",IF(ISNUMBER(SEARCH("Bubble",J:J)),"","")))))))))))))))))) | Y12: =IF(K12="Sqmt",(T12/O12)*100,IF(K12="Kg's","",IF(K12="No's","",IF(K12="Rmt","",IF(K12="Roll","",IF(K12="","")))))) | Z12: =IF(K12="Sqmt",(U12/O12)*100,IF(K12="Kg's","",IF(K12="No's","",IF(K12="Rmt","",IF(K12="Roll","",IF(K12="","")))))) | AB12: =IFERROR((X12-AA12),"")
A13: =IF(C13="","",COUNTA($C$3:C13)) -> 11 | B13: =IF(C13="","",TEXT(C13,"mmmm")) -> April | C13: 44656 | D13: 0103-64003 | F13: 44302 | G13: Knnd Associates Pvt Ltd | H13: Prestige Rex Walk Extra Duct ( 275 Gsm ) 24.03.2022 | I13: Gasket | J13: XLPE Gasket | K13: =IF(ISNUMBER(SEARCH("gsm",J:J)),"Sqmt",IF(ISNUMBER(SEARCH("Tape",J:J)),"Roll",IF(ISNUMBER(SEARCH("Thermal",J:J)),"Sqmt",IF(ISNUMBER(SEARCH("Acou",J:J)),"Sqmt",IF(ISNUMBER(SEARCH("ss",J:J)),"Sqmt",IF(ISNUMBER(SEARCH("Alu",J:J)),"Sqmt",IF(ISNUMBER(SEARCH("Gasket",J:J)),"Rmt",IF(ISNUMBER(SEARCH("Cleats",J:J)),"No's",IF(ISNUMBER(SEARCH("Tube",J:J)),"No's",IF(ISNUMBER(SEARCH("Bracket",J:J)),"No's",IF(ISNUMBER(SEARCH("Corner",J:J)),"No's",IF(ISNUMBER(SEARCH("MS",J:J)),"Kg's",IF(ISNUMBER(SEARCH("Bucket",J:J)),"Kg's",IF(ISNUMBER(SEARCH("stretch",J:J)),"Kg's",IF(ISNUMBER(SEARCH("Bubble",J:J)),"Roll",IF(ISNUMBER(SEARCH("JTR",J:J)),"Rmt",IF(ISNUMBER(SEARCH("Clamp",J:J)),"No's",IF(ISNUMBER(SEARCH("PIR",J:J)),"sqmt","")))))))))))))))))) -> Rmt | L13: 180 | O13: =IF(ISNUMBER(SEARCH("gsm",J:J)),(M13+N13)*1.22,IF(ISNUMBER(SEARCH("Tape",J:J)),L13,IF(ISNUMBER(SEARCH("Thermal",J:J)),L13,IF(ISNUMBER(SEARCH("Acou",J:J)),L13,IF(ISNUMBER(SEARCH("ss",J:J)),L13,IF(ISNUMBER(SEARCH("Alu",J:J)),L13,IF(ISNUMBER(SEARCH("Gasket",J:J)),L13,IF(ISNUMBER(SEARCH("Cleats",J:J)),L13,IF(ISNUMBER(SEARCH("Tube",J:J)),L13,IF(ISNUMBER(SEARCH("Bracket",J:J)),L13,IF(ISNUMBER(SEARCH("Corner",J:J)),L13,IF(ISNUMBER(SEARCH("MS",J:J)),L13,IF(ISNUMBER(SEARCH("Bucket",J:J)),L13,IF(ISNUMBER(SEARCH("stretch",J:J)),L13,IF(ISNUMBER(SEARCH("Bubble",J:J)),L13,IF(ISNUMBER(SEARCH("JTR",J:J)),L13,IF(ISNUMBER(SEARCH("Clamp",J:J)),"No's",IF(ISNUMBER(SEARCH("PIR",J:J)),"sqmt","")))))))))))))))))) -> 180 | T13: =(IF(K13="Sqmt",(O13-Q13),"")) | U13: =(IF(K13="Sqmt",(O13-P13)-T13,IF(K13="Rmt","",IF(K13="Kg's","",IF(K13="No's","",IF(K13="Roll","","")))))) | V13: =IF(ISNUMBER(SEARCH("26",J:J)),O13*3.925,IF(ISNUMBER(SEARCH("24",J:J)),O13*4.71,IF(ISNUMBER(SEARCH("22",J:J)),O13*6.28,IF(ISNUMBER(SEARCH("20",J:J)),O13*7.85,IF(ISNUMBER(SEARCH("18G",J:J)),O13*9.42,IF(ISNUMBER(SEARCH("16G",J:J)),O13*11.775,IF(ISNUMBER(SEARCH("Thermal",J:J)),O13,IF(ISNUMBER(SEARCH("Acou",J:J)),O13,IF(ISNUMBER(SEARCH("ss",J:J)),O13,IF(ISNUMBER(SEARCH("0.8mm",J:J)),O13*2.2,IF(ISNUMBER(SEARCH("1mm",J:J)),O13*2.75,IF(ISNUMBER(SEARCH("1.2mm",J:J)),O13*3.3,IF(ISNUMBER(SEARCH("Gasket",J:J)),O13,IF(ISNUMBER(SEARCH("Cleats",J:J)),O13,IF(ISNUMBER(SEARCH("Sealant",J:J)),O13,IF(ISNUMBER(SEARCH("Bracket",J:J)),O13,IF(ISNUMBER(SEARCH("Corner",J:J)),O13,IF(ISNUMBER(SEARCH("Bubble",J:J)),O13,"")))))))))))))))))) -> 180 | W13: =IF(ISNUMBER(SEARCH("26",J:J)),U13*3.925,IF(ISNUMBER(SEARCH("24",J:J)),U13*4.71,IF(ISNUMBER(SEARCH("22",J:J)),U13*6.28,IF(ISNUMBER(SEARCH("20",J:J)),U13*7.85,IF(ISNUMBER(SEARCH("18G",J:J)),U13*9.42,IF(ISNUMBER(SEARCH("16G",J:J)),U13*11.775,IF(ISNUMBER(SEARCH("Thermal",J:J)),U13,IF(ISNUMBER(SEARCH("Acou",J:J)),U13,IF(ISNUMBER(SEARCH("ss",J:J)),U13,IF(ISNUMBER(SEARCH("0.8mm",J:J)),U13*2.2,IF(ISNUMBER(SEARCH("1mm",J:J)),U13*2.75,IF(ISNUMBER(SEARCH("1.2mm",J:J)),U13*3.3,IF(ISNUMBER(SEARCH("Gasket",J:J)),U13,IF(ISNUMBER(SEARCH("Cleats",J:J)),U13,IF(ISNUMBER(SEARCH("Sealant",J:J)),U13,IF(ISNUMBER(SEARCH("Bracket",J:J)),U13,IF(ISNUMBER(SEARCH("Corner",J:J)),U13,IF(ISNUMBER(SEARCH("Bubble",J:J)),U13,"")))))))))))))))))) | X13: =IF(ISNUMBER(SEARCH("26",J:J)),T13*3.925,IF(ISNUMBER(SEARCH("24",J:J)),T13*4.71,IF(ISNUMBER(SEARCH("22",J:J)),T13*6.28,IF(ISNUMBER(SEARCH("20",J:J)),T13*7.85,IF(ISNUMBER(SEARCH("18",J:J)),T13*9.42,IF(ISNUMBER(SEARCH("16",J:J)),T13*11.775,IF(ISNUMBER(SEARCH("Thermal",J:J)),"",IF(ISNUMBER(SEARCH("Acou",J:J)),"",IF(ISNUMBER(SEARCH("ss",J:J)),"",IF(ISNUMBER(SEARCH("0.8mm",J:J)),T13*2.2,IF(ISNUMBER(SEARCH("1mm",J:J)),T13*2.75,IF(ISNUMBER(SEARCH("1.2mm",J:J)),T13*3.3,IF(ISNUMBER(SEARCH("Gasket",J:J)),"",IF(ISNUMBER(SEARCH("Cleats",J:J)),"",IF(ISNUMBER(SEARCH("Sealant",J:J)),"",IF(ISNUMBER(SEARCH("Bracket",J:J)),"",IF(ISNUMBER(SEARCH("Corner",J:J)),"",IF(ISNUMBER(SEARCH("Bubble",J:J)),"","")))))))))))))))))) | Y13: =IF(K13="Sqmt",(T13/O13)*100,IF(K13="Kg's","",IF(K13="No's","",IF(K13="Rmt","",IF(K13="Roll","",IF(K13="","")))))) | Z13: =IF(K13="Sqmt",(U13/O13)*100,IF(K13="Kg's","",IF(K13="No's","",IF(K13="Rmt","",IF(K13="Roll","",IF(K13="","")))))) | AB13: =IFERROR((X13-AA13),"")
A14: =IF(C14="","",COUNTA($C$3:C14)) -> 12 | B14: =IF(C14="","",TEXT(C14,"mmmm")) -> April | C14: 44656 | D14: 0103-64003 | F14: 44302 | G14: Knnd Associates Pvt Ltd | H14: Prestige Rex Walk Extra Duct ( 275 Gsm ) 24.03.2022 | I14: Cleats | J14: Cleats | K14: =IF(ISNUMBER(SEARCH("gsm",J:J)),"Sqmt",IF(ISNUMBER(SEARCH("Tape",J:J)),"Roll",IF(ISNUMBER(SEARCH("Thermal",J:J)),"Sqmt",IF(ISNUMBER(SEARCH("Acou",J:J)),"Sqmt",IF(ISNUMBER(SEARCH("ss",J:J)),"Sqmt",IF(ISNUMBER(SEARCH("Alu",J:J)),"Sqmt",IF(ISNUMBER(SEARCH("Gasket",J:J)),"Rmt",IF(ISNUMBER(SEARCH("Cleats",J:J)),"No's",IF(ISNUMBER(SEARCH("Tube",J:J)),"No's",IF(ISNUMBER(SEARCH("Bracket",J:J)),"No's",IF(ISNUMBER(SEARCH("Corner",J:J)),"No's",IF(ISNUMBER(SEARCH("MS",J:J)),"Kg's",IF(ISNUMBER(SEARCH("Bucket",J:J)),"Kg's",IF(ISNUMBER(SEARCH("stretch",J:J)),"Kg's",IF(ISNUMBER(SEARCH("Bubble",J:J)),"Roll",IF(ISNUMBER(SEARCH("JTR",J:J)),"Rmt",IF(ISNUMBER(SEARCH("Clamp",J:J)),"No's",IF(ISNUMBER(SEARCH("PIR",J:J)),"sqmt","")))))))))))))))))) -> No's | L14: 700 | O14: =IF(ISNUMBER(SEARCH("gsm",J:J)),(M14+N14)*1.22,IF(ISNUMBER(SEARCH("Tape",J:J)),L14,IF(ISNUMBER(SEARCH("Thermal",J:J)),L14,IF(ISNUMBER(SEARCH("Acou",J:J)),L14,IF(ISNUMBER(SEARCH("ss",J:J)),L14,IF(ISNUMBER(SEARCH("Alu",J:J)),L14,IF(ISNUMBER(SEARCH("Gasket",J:J)),L14,IF(ISNUMBER(SEARCH("Cleats",J:J)),L14,IF(ISNUMBER(SEARCH("Tube",J:J)),L14,IF(ISNUMBER(SEARCH("Bracket",J:J)),L14,IF(ISNUMBER(SEARCH("Corner",J:J)),L14,IF(ISNUMBER(SEARCH("MS",J:J)),L14,IF(ISNUMBER(SEARCH("Bucket",J:J)),L14,IF(ISNUMBER(SEARCH("stretch",J:J)),L14,IF(ISNUMBER(SEARCH("Bubble",J:J)),L14,IF(ISNUMBER(SEARCH("JTR",J:J)),L14,IF(ISNUMBER(SEARCH("Clamp",J:J)),"No's",IF(ISNUMBER(SEARCH("PIR",J:J)),"sqmt","")))))))))))))))))) -> 700 | T14: =(IF(K14="Sqmt",(O14-Q14),"")) | U14: =(IF(K14="Sqmt",(O14-P14)-T14,IF(K14="Rmt","",IF(K14="Kg's","",IF(K14="No's","",IF(K14="Roll","","")))))) | V14: =IF(ISNUMBER(SEARCH("26",J:J)),O14*3.925,IF(ISNUMBER(SEARCH("24",J:J)),O14*4.71,IF(ISNUMBER(SEARCH("22",J:J)),O14*6.28,IF(ISNUMBER(SEARCH("20",J:J)),O14*7.85,IF(ISNUMBER(SEARCH("18G",J:J)),O14*9.42,IF(ISNUMBER(SEARCH("16G",J:J)),O14*11.775,IF(ISNUMBER(SEARCH("Thermal",J:J)),O14,IF(ISNUMBER(SEARCH("Acou",J:J)),O14,IF(ISNUMBER(SEARCH("ss",J:J)),O14,IF(ISNUMBER(SEARCH("0.8mm",J:J)),O14*2.2,IF(ISNUMBER(SEARCH("1mm",J:J)),O14*2.75,IF(ISNUMBER(SEARCH("1.2mm",J:J)),O14*3.3,IF(ISNUMBER(SEARCH("Gasket",J:J)),O14,IF(ISNUMBER(SEARCH("Cleats",J:J)),O14,IF(ISNUMBER(SEARCH("Sealant",J:J)),O14,IF(ISNUMBER(SEARCH("Bracket",J:J)),O14,IF(ISNUMBER(SEARCH("Corner",J:J)),O14,IF(ISNUMBER(SEARCH("Bubble",J:J)),O14,"")))))))))))))))))) -> 700 | W14: =IF(ISNUMBER(SEARCH("26",J:J)),U14*3.925,IF(ISNUMBER(SEARCH("24",J:J)),U14*4.71,IF(ISNUMBER(SEARCH("22",J:J)),U14*6.28,IF(ISNUMBER(SEARCH("20",J:J)),U14*7.85,IF(ISNUMBER(SEARCH("18G",J:J)),U14*9.42,IF(ISNUMBER(SEARCH("16G",J:J)),U14*11.775,IF(ISNUMBER(SEARCH("Thermal",J:J)),U14,IF(ISNUMBER(SEARCH("Acou",J:J)),U14,IF(ISNUMBER(SEARCH("ss",J:J)),U14,IF(ISNUMBER(SEARCH("0.8mm",J:J)),U14*2.2,IF(ISNUMBER(SEARCH("1mm",J:J)),U14*2.75,IF(ISNUMBER(SEARCH("1.2mm",J:J)),U14*3.3,IF(ISNUMBER(SEARCH("Gasket",J:J)),U14,IF(ISNUMBER(SEARCH("Cleats",J:J)),U14,IF(ISNUMBER(SEARCH("Sealant",J:J)),U14,IF(ISNUMBER(SEARCH("Bracket",J:J)),U14,IF(ISNUMBER(SEARCH("Corner",J:J)),U14,IF(ISNUMBER(SEARCH("Bubble",J:J)),U14,"")))))))))))))))))) | X14: =IF(ISNUMBER(SEARCH("26",J:J)),T14*3.925,IF(ISNUMBER(SEARCH("24",J:J)),T14*4.71,IF(ISNUMBER(SEARCH("22",J:J)),T14*6.28,IF(ISNUMBER(SEARCH("20",J:J)),T14*7.85,IF(ISNUMBER(SEARCH("18",J:J)),T14*9.42,IF(ISNUMBER(SEARCH("16",J:J)),T14*11.775,IF(ISNUMBER(SEARCH("Thermal",J:J)),"",IF(ISNUMBER(SEARCH("Acou",J:J)),"",IF(ISNUMBER(SEARCH("ss",J:J)),"",IF(ISNUMBER(SEARCH("0.8mm",J:J)),T14*2.2,IF(ISNUMBER(SEARCH("1mm",J:J)),T14*2.75,IF(ISNUMBER(SEARCH("1.2mm",J:J)),T14*3.3,IF(ISNUMBER(SEARCH("Gasket",J:J)),"",IF(ISNUMBER(SEARCH("Cleats",J:J)),"",IF(ISNUMBER(SEARCH("Sealant",J:J)),"",IF(ISNUMBER(SEARCH("Bracket",J:J)),"",IF(ISNUMBER(SEARCH("Corner",J:J)),"",IF(ISNUMBER(SEARCH("Bubble",J:J)),"","")))))))))))))))))) | Y14: =IF(K14="Sqmt",(T14/O14)*100,IF(K14="Kg's","",IF(K14="No's","",IF(K14="Rmt","",IF(K14="Roll","",IF(K14="","")))))) | Z14: =IF(K14="Sqmt",(U14/O14)*100,IF(K14="Kg's","",IF(K14="No's","",IF(K14="Rmt","",IF(K14="Roll","",IF(K14="","")))))) | AB14: =IFERROR((X14-AA14),"")
A15: =IF(C15="","",COUNTA($C$3:C15)) -> 13 | B15: =IF(C15="","",TEXT(C15,"mmmm")) -> April | C15: 44656 | D15: 0103-64003 | F15: 44302 | G15: Knnd Associates Pvt Ltd | H15: Prestige Rex Walk Extra Duct ( 275 Gsm ) 24.03.2022 | I15: Sealant | J15: Sealant Bucket | K15: =IF(ISNUMBER(SEARCH("gsm",J:J)),"Sqmt",IF(ISNUMBER(SEARCH("Tape",J:J)),"Roll",IF(ISNUMBER(SEARCH("Thermal",J:J)),"Sqmt",IF(ISNUMBER(SEARCH("Acou",J:J)),"Sqmt",IF(ISNUMBER(SEARCH("ss",J:J)),"Sqmt",IF(ISNUMBER(SEARCH("Alu",J:J)),"Sqmt",IF(ISNUMBER(SEARCH("Gasket",J:J)),"Rmt",IF(ISNUMBER(SEARCH("Cleats",J:J)),"No's",IF(ISNUMBER(SEARCH("Tube",J:J)),"No's",IF(ISNUMBER(SEARCH("Bracket",J:J)),"No's",IF(ISNUMBER(SEARCH("Corner",J:J)),"No's",IF(ISNUMBER(SEARCH("MS",J:J)),"Kg's",IF(ISNUMBER(SEARCH("Bucket",J:J)),"Kg's",IF(ISNUMBER(SEARCH("stretch",J:J)),"Kg's",IF(ISNUMBER(SEARCH("Bubble",J:J)),"Roll",IF(ISNUMBER(SEARCH("JTR",J:J)),"Rmt",IF(ISNUMBER(SEARCH("Clamp",J:J)),"No's",IF(ISNUMBER(SEARCH("PIR",J:J)),"sqmt","")))))))))))))))))) -> Kg's | L15: 0.9 | O15: =IF(ISNUMBER(SEARCH("gsm",J:J)),(M15+N15)*1.22,IF(ISNUMBER(SEARCH("Tape",J:J)),L15,IF(ISNUMBER(SEARCH("Thermal",J:J)),L15,IF(ISNUMBER(SEARCH("Acou",J:J)),L15,IF(ISNUMBER(SEARCH("ss",J:J)),L15,IF(ISNUMBER(SEARCH("Alu",J:J)),L15,IF(ISNUMBER(SEARCH("Gasket",J:J)),L15,IF(ISNUMBER(SEARCH("Cleats",J:J)),L15,IF(ISNUMBER(SEARCH("Tube",J:J)),L15,IF(ISNUMBER(SEARCH("Bracket",J:J)),L15,IF(ISNUMBER(SEARCH("Corner",J:J)),L15,IF(ISNUMBER(SEARCH("MS",J:J)),L15,IF(ISNUMBER(SEARCH("Bucket",J:J)),L15,IF(ISNUMBER(SEARCH("stretch",J:J)),L15,IF(ISNUMBER(SEARCH("Bubble",J:J)),L15,IF(ISNUMBER(SEARCH("JTR",J:J)),L15,IF(ISNUMBER(SEARCH("Clamp",J:J)),"No's",IF(ISNUMBER(SEARCH("PIR",J:J)),"sqmt","")))))))))))))))))) -> 0.9 | T15: =(IF(K15="Sqmt",(O15-Q15),"")) | U15: =(IF(K15="Sqmt",(O15-P15)-T15,IF(K15="Rmt","",IF(K15="Kg's","",IF(K15="No's","",IF(K15="Roll","","")))))) | V15: =IF(ISNUMBER(SEARCH("26",J:J)),O15*3.925,IF(ISNUMBER(SEARCH("24",J:J)),O15*4.71,IF(ISNUMBER(SEARCH("22",J:J)),O15*6.28,IF(ISNUMBER(SEARCH("20",J:J)),O15*7.85,IF(ISNUMBER(SEARCH("18G",J:J)),O15*9.42,IF(ISNUMBER(SEARCH("16G",J:J)),O15*11.775,IF(ISNUMBER(SEARCH("Thermal",J:J)),O15,IF(ISNUMBER(SEARCH("Acou",J:J)),O15,IF(ISNUMBER(SEARCH("ss",J:J)),O15,IF(ISNUMBER(SEARCH("0.8mm",J:J)),O15*2.2,IF(ISNUMBER(SEARCH("1mm",J:J)),O15*2.75,IF(ISNUMBER(SEARCH("1.2mm",J:J)),O15*3.3,IF(ISNUMBER(SEARCH("Gasket",J:J)),O15,IF(ISNUMBER(SEARCH("Cleats",J:J)),O15,IF(ISNUMBER(SEARCH("Sealant",J:J)),O15,IF(ISNUMBER(SEARCH("Bracket",J:J)),O15,IF(ISNUMBER(SEARCH("Corner",J:J)),O15,IF(ISNUMBER(SEARCH("Bubble",J:J)),O15,"")))))))))))))))))) -> 0.9 | W15: =IF(ISNUMBER(SEARCH("26",J:J)),U15*3.925,IF(ISNUMBER(SEARCH("24",J:J)),U15*4.71,IF(ISNUMBER(SEARCH("22",J:J)),U15*6.28,IF(ISNUMBER(SEARCH("20",J:J)),U15*7.85,IF(ISNUMBER(SEARCH("18G",J:J)),U15*9.42,IF(ISNUMBER(SEARCH("16G",J:J)),U15*11.775,IF(ISNUMBER(SEARCH("Thermal",J:J)),U15,IF(ISNUMBER(SEARCH("Acou",J:J)),U15,IF(ISNUMBER(SEARCH("ss",J:J)),U15,IF(ISNUMBER(SEARCH("0.8mm",J:J)),U15*2.2,IF(ISNUMBER(SEARCH("1mm",J:J)),U15*2.75,IF(ISNUMBER(SEARCH("1.2mm",J:J)),U15*3.3,IF(ISNUMBER(SEARCH("Gasket",J:J)),U15,IF(ISNUMBER(SEARCH("Cleats",J:J)),U15,IF(ISNUMBER(SEARCH("Sealant",J:J)),U15,IF(ISNUMBER(SEARCH("Bracket",J:J)),U15,IF(ISNUMBER(SEARCH("Corner",J:J)),U15,IF(ISNUMBER(SEARCH("Bubble",J:J)),U15,"")))))))))))))))))) | X15: =IF(ISNUMBER(SEARCH("26",J:J)),T15*3.925,IF(ISNUMBER(SEARCH("24",J:J)),T15*4.71,IF(ISNUMBER(SEARCH("22",J:J)),T15*6.28,IF(ISNUMBER(SEARCH("20",J:J)),T15*7.85,IF(ISNUMBER(SEARCH("18",J:J)),T15*9.42,IF(ISNUMBER(SEARCH("16",J:J)),T15*11.775,IF(ISNUMBER(SEARCH("Thermal",J:J)),"",IF(ISNUMBER(SEARCH("Acou",J:J)),"",IF(ISNUMBER(SEARCH("ss",J:J)),"",IF(ISNUMBER(SEARCH("0.8mm",J:J)),T15*2.2,IF(ISNUMBER(SEARCH("1mm",J:J)),T15*2.75,IF(ISNUMBER(SEARCH("1.2mm",J:J)),T15*3.3,IF(ISNUMBER(SEARCH("Gasket",J:J)),"",IF(ISNUMBER(SEARCH("Cleats",J:J)),"",IF(ISNUMBER(SEARCH("Sealant",J:J)),"",IF(ISNUMBER(SEARCH("Bracket",J:J)),"",IF(ISNUMBER(SEARCH("Corner",J:J)),"",IF(ISNUMBER(SEARCH("Bubble",J:J)),"","")))))))))))))))))) | Y15: =IF(K15="Sqmt",(T15/O15)*100,IF(K15="Kg's","",IF(K15="No's","",IF(K15="Rmt","",IF(K15="Roll","",IF(K15="","")))))) | Z15: =IF(K15="Sqmt",(U15/O15)*100,IF(K15="Kg's","",IF(K15="No's","",IF(K15="Rmt","",IF(K15="Roll","",IF(K15="","")))))) | AB15: =IFERROR((X15-AA15),"")
A16: =IF(C16="","",COUNTA($C$3:C16)) -> 14 | B16: =IF(C16="","",TEXT(C16,"mmmm")) -> April | C16: 44656 | D16: 0103-64003 | F16: 44302 | G16: Knnd Associates Pvt Ltd | H16: Prestige Rex Walk Extra Duct ( 275 Gsm ) 24.03.2022 | I16: Sealant | J16: Sealant Tube | K16: =IF(ISNUMBER(SEARCH("gsm",J:J)),"Sqmt",IF(ISNUMBER(SEARCH("Tape",J:J)),"Roll",IF(ISNUMBER(SEARCH("Thermal",J:J)),"Sqmt",IF(ISNUMBER(SEARCH("Acou",J:J)),"Sqmt",IF(ISNUMBER(SEARCH("ss",J:J)),"Sqmt",IF(ISNUMBER(SEARCH("Alu",J:J)),"Sqmt",IF(ISNUMBER(SEARCH("Gasket",J:J)),"Rmt",IF(ISNUMBER(SEARCH("Cleats",J:J)),"No's",IF(ISNUMBER(SEARCH("Tube",J:J)),"No's",IF(ISNUMBER(SEARCH("Bracket",J:J)),"No's",IF(ISNUMBER(SEARCH("Corner",J:J)),"No's",IF(ISNUMBER(SEARCH("MS",J:J)),"Kg's",IF(ISNUMBER(SEARCH("Bucket",J:J)),"Kg's",IF(ISNUMBER(SEARCH("stretch",J:J)),"Kg's",IF(ISNUMBER(SEARCH("Bubble",J:J)),"Roll",IF(ISNUMBER(SEARCH("JTR",J:J)),"Rmt",IF(ISNUMBER(SEARCH("Clamp",J:J)),"No's",IF(ISNUMBER(SEARCH("PIR",J:J)),"sqmt","")))))))))))))))))) -> No's | L16: 1 | O16: =IF(ISNUMBER(SEARCH("gsm",J:J)),(M16+N16)*1.22,IF(ISNUMBER(SEARCH("Tape",J:J)),L16,IF(ISNUMBER(SEARCH("Thermal",J:J)),L16,IF(ISNUMBER(SEARCH("Acou",J:J)),L16,IF(ISNUMBER(SEARCH("ss",J:J)),L16,IF(ISNUMBER(SEARCH("Alu",J:J)),L16,IF(ISNUMBER(SEARCH("Gasket",J:J)),L16,IF(ISNUMBER(SEARCH("Cleats",J:J)),L16,IF(ISNUMBER(SEARCH("Tube",J:J)),L16,IF(ISNUMBER(SEARCH("Bracket",J:J)),L16,IF(ISNUMBER(SEARCH("Corner",J:J)),L16,IF(ISNUMBER(SEARCH("MS",J:J)),L16,IF(ISNUMBER(SEARCH("Bucket",J:J)),L16,IF(ISNUMBER(SEARCH("stretch",J:J)),L16,IF(ISNUMBER(SEARCH("Bubble",J:J)),L16,IF(ISNUMBER(SEARCH("JTR",J:J)),L16,IF(ISNUMBER(SEARCH("Clamp",J:J)),"No's",IF(ISNUMBER(SEARCH("PIR",J:J)),"sqmt","")))))))))))))))))) -> 1 | T16: =(IF(K16="Sqmt",(O16-Q16),"")) | U16: =(IF(K16="Sqmt",(O16-P16)-T16,IF(K16="Rmt","",IF(K16="Kg's","",IF(K16="No's","",IF(K16="Roll","","")))))) | V16: =IF(ISNUMBER(SEARCH("26",J:J)),O16*3.925,IF(ISNUMBER(SEARCH("24",J:J)),O16*4.71,IF(ISNUMBER(SEARCH("22",J:J)),O16*6.28,IF(ISNUMBER(SEARCH("20",J:J)),O16*7.85,IF(ISNUMBER(SEARCH("18G",J:J)),O16*9.42,IF(ISNUMBER(SEARCH("16G",J:J)),O16*11.775,IF(ISNUMBER(SEARCH("Thermal",J:J)),O16,IF(ISNUMBER(SEARCH("Acou",J:J)),O16,IF(ISNUMBER(SEARCH("ss",J:J)),O16,IF(ISNUMBER(SEARCH("0.8mm",J:J)),O16*2.2,IF(ISNUMBER(SEARCH("1mm",J:J)),O16*2.75,IF(ISNUMBER(SEARCH("1.2mm",J:J)),O16*3.3,IF(ISNUMBER(SEARCH("Gasket",J:J)),O16,IF(ISNUMBER(SEARCH("Cleats",J:J)),O16,IF(ISNUMBER(SEARCH("Sealant",J:J)),O16,IF(ISNUMBER(SEARCH("Bracket",J:J)),O16,IF(ISNUMBER(SEARCH("Corner",J:J)),O16,IF(ISNUMBER(SEARCH("Bubble",J:J)),O16,"")))))))))))))))))) -> 1 | W16: =IF(ISNUMBER(SEARCH("26",J:J)),U16*3.925,IF(ISNUMBER(SEARCH("24",J:J)),U16*4.71,IF(ISNUMBER(SEARCH("22",J:J)),U16*6.28,IF(ISNUMBER(SEARCH("20",J:J)),U16*7.85,IF(ISNUMBER(SEARCH("18G",J:J)),U16*9.42,IF(ISNUMBER(SEARCH("16G",J:J)),U16*11.775,IF(ISNUMBER(SEARCH("Thermal",J:J)),U16,IF(ISNUMBER(SEARCH("Acou",J:J)),U16,IF(ISNUMBER(SEARCH("ss",J:J)),U16,IF(ISNUMBER(SEARCH("0.8mm",J:J)),U16*2.2,IF(ISNUMBER(SEARCH("1mm",J:J)),U16*2.75,IF(ISNUMBER(SEARCH("1.2mm",J:J)),U16*3.3,IF(ISNUMBER(SEARCH("Gasket",J:J)),U16,IF(ISNUMBER(SEARCH("Cleats",J:J)),U16,IF(ISNUMBER(SEARCH("Sealant",J:J)),U16,IF(ISNUMBER(SEARCH("Bracket",J:J)),U16,IF(ISNUMBER(SEARCH("Corner",J:J)),U16,IF(ISNUMBER(SEARCH("Bubble",J:J)),U16,"")))))))))))))))))) | X16: =IF(ISNUMBER(SEARCH("26",J:J)),T16*3.925,IF(ISNUMBER(SEARCH("24",J:J)),T16*4.71,IF(ISNUMBER(SEARCH("22",J:J)),T16*6.28,IF(ISNUMBER(SEARCH("20",J:J)),T16*7.85,IF(ISNUMBER(SEARCH("18",J:J)),T16*9.42,IF(ISNUMBER(SEARCH("16",J:J)),T16*11.775,IF(ISNUMBER(SEARCH("Thermal",J:J)),"",IF(ISNUMBER(SEARCH("Acou",J:J)),"",IF(ISNUMBER(SEARCH("ss",J:J)),"",IF(ISNUMBER(SEARCH("0.8mm",J:J)),T16*2.2,IF(ISNUMBER(SEARCH("1mm",J:J)),T16*2.75,IF(ISNUMBER(SEARCH("1.2mm",J:J)),T16*3.3,IF(ISNUMBER(SEARCH("Gasket",J:J)),"",IF(ISNUMBER(SEARCH("Cleats",J:J)),"",IF(ISNUMBER(SEARCH("Sealant",J:J)),"",IF(ISNUMBER(SEARCH("Bracket",J:J)),"",IF(ISNUMBER(SEARCH("Corner",J:J)),"",IF(ISNUMBER(SEARCH("Bubble",J:J)),"","")))))))))))))))))) | Y16: =IF(K16="Sqmt",(T16/O16)*100,IF(K16="Kg's","",IF(K16="No's","",IF(K16="Rmt","",IF(K16="Roll","",IF(K16="","")))))) | Z16: =IF(K16="Sqmt",(U16/O16)*100,IF(K16="Kg's","",IF(K16="No's","",IF(K16="Rmt","",IF(K16="Roll","",IF(K16="","")))))) | AB16: =IFERROR((X16-AA16),"")
A17: =IF(C17="","",COUNTA($C$3:C17)) -> 15 | B17: =IF(C17="","",TEXT(C17,"mmmm")) -> April | C17: 44658 | D17: 0103-64003 | F17: 44302 | G17: Knnd Associates Pvt Ltd | H17: Prestige Rex Walk Mixing Box & Dummy Pieces ( 275 Gsm ) | I17: Mixing Box | J17: 275gsm 24G | K17: =IF(ISNUMBER(SEARCH("gsm",J:J)),"Sqmt",IF(ISNUMBER(SEARCH("Tape",J:J)),"Roll",IF(ISNUMBER(SEARCH("Thermal",J:J)),"Sqmt",IF(ISNUMBER(SEARCH("Acou",J:J)),"Sqmt",IF(ISNUMBER(SEARCH("ss",J:J)),"Sqmt",IF(ISNUMBER(SEARCH("Alu",J:J)),"Sqmt",IF(ISNUMBER(SEARCH("Gasket",J:J)),"Rmt",IF(ISNUMBER(SEARCH("Cleats",J:J)),"No's",IF(ISNUMBER(SEARCH("Tube",J:J)),"No's",IF(ISNUMBER(SEARCH("Bracket",J:J)),"No's",IF(ISNUMBER(SEARCH("Corner",J:J)),"No's",IF(ISNUMBER(SEARCH("MS",J:J)),"Kg's",IF(ISNUMBER(SEARCH("Bucket",J:J)),"Kg's",IF(ISNUMBER(SEARCH("stretch",J:J)),"Kg's",IF(ISNUMBER(SEARCH("Bubble",J:J)),"Roll",IF(ISNUMBER(SEARCH("JTR",J:J)),"Rmt",IF(ISNUMBER(SEARCH("Clamp",J:J)),"No's",IF(ISNUMBER(SEARCH("PIR",J:J)),"sqmt","")))))))))))))))))) -> Sqmt | L17: 3.9 | N17: 3.209 | O17: =IF(ISNUMBER(SEARCH("gsm",J:J)),(M17+N17)*1.22,IF(ISNUMBER(SEARCH("Tape",J:J)),L17,IF(ISNUMBER(SEARCH("Thermal",J:J)),L17,IF(ISNUMBER(SEARCH("Acou",J:J)),L17,IF(ISNUMBER(SEARCH("ss",J:J)),L17,IF(ISNUMBER(SEARCH("Alu",J:J)),L17,IF(ISNUMBER(SEARCH("Gasket",J:J)),L17,IF(ISNUMBER(SEARCH("Cleats",J:J)),L17,IF(ISNUMBER(SEARCH("Tube",J:J)),L17,IF(ISNUMBER(SEARCH("Bracket",J:J)),L17,IF(ISNUMBER(SEARCH("Corner",J:J)),L17,IF(ISNUMBER(SEARCH("MS",J:J)),L17,IF(ISNUMBER(SEARCH("Bucket",J:J)),L17,IF(ISNUMBER(SEARCH("stretch",J:J)),L17,IF(ISNUMBER(SEARCH("Bubble",J:J)),L17,IF(ISNUMBER(SEARCH("JTR",J:J)),L17,IF(ISNUMBER(SEARCH("Clamp",J:J)),"No's",IF(ISNUMBER(SEARCH("PIR",J:J)),"sqmt","")))))))))))))))))) -> 3.91498 | P17: 2.6 | Q17: 3.5 | R17: 0 | S17: 100 | T17: =(IF(K17="Sqmt",(O17-Q17),"")) -> 0.41498 | U17: =(IF(K17="Sqmt",(O17-P17)-T17,IF(K17="Rmt","",IF(K17="Kg's","",IF(K17="No's","",IF(K17="Roll","","")))))) -> 0.9 | V17: =IF(ISNUMBER(SEARCH("26",J:J)),O17*3.925,IF(ISNUMBER(SEARCH("24",J:J)),O17*4.71,IF(ISNUMBER(SEARCH("22",J:J)),O17*6.28,IF(ISNUMBER(SEARCH("20",J:J)),O17*7.85,IF(ISNUMBER(SEARCH("18G",J:J)),O17*9.42,IF(ISNUMBER(SEARCH("16G",J:J)),O17*11.775,IF(ISNUMBER(SEARCH("Thermal",J:J)),O17,IF(ISNUMBER(SEARCH("Acou",J:J)),O17,IF(ISNUMBER(SEARCH("ss",J:J)),O17,IF(ISNUMBER(SEARCH("0.8mm",J:J)),O17*2.2,IF(ISNUMBER(SEARCH("1mm",J:J)),O17*2.75,IF(ISNUMBER(SEARCH("1.2mm",J:J)),O17*3.3,IF(ISNUMBER(SEARCH("Gasket",J:J)),O17,IF(ISNUMBER(SEARCH("Cleats",J:J)),O17,IF(ISNUMBER(SEARCH("Sealant",J:J)),O17,IF(ISNUMBER(SEARCH("Bracket",J:J)),O17,IF(ISNUMBER(SEARCH("Corner",J:J)),O17,IF(ISNUMBER(SEARCH("Bubble",J:J)),O17,"")))))))))))))))))) -> 18.439556 | W17: =IF(ISNUMBER(SEARCH("26",J:J)),U17*3.925,IF(ISNUMBER(SEARCH("24",J:J)),U17*4.71,IF(ISNUMBER(SEARCH("22",J:J)),U17*6.28,IF(ISNUMBER(SEARCH("20",J:J)),U17*7.85,IF(ISNUMBER(SEARCH("18G",J:J)),U17*9.42,IF(ISNUMBER(SEARCH("16G",J:J)),U17*11.775,IF(ISNUMBER(SEARCH("Thermal",J:J)),U17,IF(ISNUMBER(SEARCH("Acou",J:J)),U17,IF(ISNUMBER(SEARCH("ss",J:J)),U17,IF(ISNUMBER(SEARCH("0.8mm",J:J)),U17*2.2,IF(ISNUMBER(SEARCH("1mm",J:J)),U17*2.75,IF(ISNUMBER(SEARCH("1.2mm",J:J)),U17*3.3,IF(ISNUMBER(SEARCH("Gasket",J:J)),U17,IF(ISNUMBER(SEARCH("Cleats",J:J)),U17,IF(ISNUMBER(SEARCH("Sealant",J:J)),U17,IF(ISNUMBER(SEARCH("Bracket",J:J)),U17,IF(ISNUMBER(SEARCH("Corner",J:J)),U17,IF(ISNUMBER(SEARCH("Bubble",J:J)),U17,"")))))))))))))))))) -> 4.239 | X17: =IF(ISNUMBER(SEARCH("26",J:J)),T17*3.925,IF(ISNUMBER(SEARCH("24",J:J)),T17*4.71,IF(ISNUMBER(SEARCH("22",J:J)),T17*6.28,IF(ISNUMBER(SEARCH("20",J:J)),T17*7.85,IF(ISNUMBER(SEARCH("18",J:J)),T17*9.42,IF(ISNUMBER(SEARCH("16",J:J)),T17*11.775,IF(ISNUMBER(SEARCH("Thermal",J:J)),"",IF(ISNUMBER(SEARCH("Acou",J:J)),"",IF(ISNUMBER(SEARCH("ss",J:J)),"",IF(ISNUMBER(SEARCH("0.8mm",J:J)),T17*2.2,IF(ISNUMBER(SEARCH("1mm",J:J)),T17*2.75,IF(ISNUMBER(SEARCH("1.2mm",J:J)),T17*3.3,IF(ISNUMBER(SEARCH("Gasket",J:J)),"",IF(ISNUMBER(SEARCH("Cleats",J:J)),"",IF(ISNUMBER(SEARCH("Sealant",J:J)),"",IF(ISNUMBER(SEARCH("Bracket",J:J)),"",IF(ISNUMBER(SEARCH("Corner",J:J)),"",IF(ISNUMBER(SEARCH("Bubble",J:J)),"","")))))))))))))))))) -> 1.9545558 | Y17: =IF(K17="Sqmt",(T17/O17)*100,IF(K17="Kg's","",IF(K17="No's","",IF(K17="Rmt","",IF(K17="Roll","",IF(K17="","")))))) -> 10.599799 | Z17: =IF(K17="Sqmt",(U17/O17)*100,IF(K17="Kg's","",IF(K17="No's","",IF(K17="Rmt","",IF(K17="Roll","",IF(K17="","")))))) -> 22.988623 | AB17: =IFERROR((X17-AA17),"") -> 1.9545558 | AC17: Site Measurement
A18: =IF(C18="","",COUNTA($C$3:C18)) -> 16 | B18: =IF(C18="","",TEXT(C18,"mmmm")) -> April | C18: 44658 | D18: 0103-64003 | F18: 44302 | G18: Knnd Associates Pvt Ltd | H18: Prestige Rex Walk Mixing Box & Dummy Pieces ( 275 Gsm ) | I18: Corners | J18: Corner 32mm | K18: =IF(ISNUMBER(SEARCH("gsm",J:J)),"Sqmt",IF(ISNUMBER(SEARCH("Tape",J:J)),"Roll",IF(ISNUMBER(SEARCH("Thermal",J:J)),"Sqmt",IF(ISNUMBER(SEARCH("Acou",J:J)),"Sqmt",IF(ISNUMBER(SEARCH("ss",J:J)),"Sqmt",IF(ISNUMBER(SEARCH("Alu",J:J)),"Sqmt",IF(ISNUMBER(SEARCH("Gasket",J:J)),"Rmt",IF(ISNUMBER(SEARCH("Cleats",J:J)),"No's",IF(ISNUMBER(SEARCH("Tube",J:J)),"No's",IF(ISNUMBER(SEARCH("Bracket",J:J)),"No's",IF(ISNUMBER(SEARCH("Corner",J:J)),"No's",IF(ISNUMBER(SEARCH("MS",J:J)),"Kg's",IF(ISNUMBER(SEARCH("Bucket",J:J)),"Kg's",IF(ISNUMBER(SEARCH("stretch",J:J)),"Kg's",IF(ISNUMBER(SEARCH("Bubble",J:J)),"Roll",IF(ISNUMBER(SEARCH("JTR",J:J)),"Rmt",IF(ISNUMBER(SEARCH("Clamp",J:J)),"No's",IF(ISNUMBER(SEARCH("PIR",J:J)),"sqmt","")))))))))))))))))) -> No's | L18: 16 | O18: =IF(ISNUMBER(SEARCH("gsm",J:J)),(M18+N18)*1.22,IF(ISNUMBER(SEARCH("Tape",J:J)),L18,IF(ISNUMBER(SEARCH("Thermal",J:J)),L18,IF(ISNUMBER(SEARCH("Acou",J:J)),L18,IF(ISNUMBER(SEARCH("ss",J:J)),L18,IF(ISNUMBER(SEARCH("Alu",J:J)),L18,IF(ISNUMBER(SEARCH("Gasket",J:J)),L18,IF(ISNUMBER(SEARCH("Cleats",J:J)),L18,IF(ISNUMBER(SEARCH("Tube",J:J)),L18,IF(ISNUMBER(SEARCH("Bracket",J:J)),L18,IF(ISNUMBER(SEARCH("Corner",J:J)),L18,IF(ISNUMBER(SEARCH("MS",J:J)),L18,IF(ISNUMBER(SEARCH("Bucket",J:J)),L18,IF(ISNUMBER(SEARCH("stretch",J:J)),L18,IF(ISNUMBER(SEARCH("Bubble",J:J)),L18,IF(ISNUMBER(SEARCH("JTR",J:J)),L18,IF(ISNUMBER(SEARCH("Clamp",J:J)),"No's",IF(ISNUMBER(SEARCH("PIR",J:J)),"sqmt","")))))))))))))))))) -> 16 | T18: =(IF(K18="Sqmt",(O18-Q18),"")) | U18: =(IF(K18="Sqmt",(O18-P18)-T18,IF(K18="Rmt","",IF(K18="Kg's","",IF(K18="No's","",IF(K18="Roll","","")))))) | V18: =IF(ISNUMBER(SEARCH("26",J:J)),O18*3.925,IF(ISNUMBER(SEARCH("24",J:J)),O18*4.71,IF(ISNUMBER(SEARCH("22",J:J)),O18*6.28,IF(ISNUMBER(SEARCH("20",J:J)),O18*7.85,IF(ISNUMBER(SEARCH("18G",J:J)),O18*9.42,IF(ISNUMBER(SEARCH("16G",J:J)),O18*11.775,IF(ISNUMBER(SEARCH("Thermal",J:J)),O18,IF(ISNUMBER(SEARCH("Acou",J:J)),O18,IF(ISNUMBER(SEARCH("ss",J:J)),O18,IF(ISNUMBER(SEARCH("0.8mm",J:J)),O18*2.2,IF(ISNUMBER(SEARCH("1mm",J:J)),O18*2.75,IF(ISNUMBER(SEARCH("1.2mm",J:J)),O18*3.3,IF(ISNUMBER(SEARCH("Gasket",J:J)),O18,IF(ISNUMBER(SEARCH("Cleats",J:J)),O18,IF(ISNUMBER(SEARCH("Sealant",J:J)),O18,IF(ISNUMBER(SEARCH("Bracket",J:J)),O18,IF(ISNUMBER(SEARCH("Corner",J:J)),O18,IF(ISNUMBER(SEARCH("Bubble",J:J)),O18,"")))))))))))))))))) -> 16 | W18: =IF(ISNUMBER(SEARCH("26",J:J)),U18*3.925,IF(ISNUMBER(SEARCH("24",J:J)),U18*4.71,IF(ISNUMBER(SEARCH("22",J:J)),U18*6.28,IF(ISNUMBER(SEARCH("20",J:J)),U18*7.85,IF(ISNUMBER(SEARCH("18G",J:J)),U18*9.42,IF(ISNUMBER(SEARCH("16G",J:J)),U18*11.775,IF(ISNUMBER(SEARCH("Thermal",J:J)),U18,IF(ISNUMBER(SEARCH("Acou",J:J)),U18,IF(ISNUMBER(SEARCH("ss",J:J)),U18,IF(ISNUMBER(SEARCH("0.8mm",J:J)),U18*2.2,IF(ISNUMBER(SEARCH("1mm",J:J)),U18*2.75,IF(ISNUMBER(SEARCH("1.2mm",J:J)),U18*3.3,IF(ISNUMBER(SEARCH("Gasket",J:J)),U18,IF(ISNUMBER(SEARCH("Cleats",J:J)),U18,IF(ISNUMBER(SEARCH("Sealant",J:J)),U18,IF(ISNUMBER(SEARCH("Bracket",J:J)),U18,IF(ISNUMBER(SEARCH("Corner",J:J)),U18,IF(ISNUMBER(SEARCH("Bubble",J:J)),U18,"")))))))))))))))))) | X18: =IF(ISNUMBER(SEARCH("26",J:J)),T18*3.925,IF(ISNUMBER(SEARCH("24",J:J)),T18*4.71,IF(ISNUMBER(SEARCH("22",J:J)),T18*6.28,IF(ISNUMBER(SEARCH("20",J:J)),T18*7.85,IF(ISNUMBER(SEARCH("18",J:J)),T18*9.42,IF(ISNUMBER(SEARCH("16",J:J)),T18*11.775,IF(ISNUMBER(SEARCH("Thermal",J:J)),"",IF(ISNUMBER(SEARCH("Acou",J:J)),"",IF(ISNUMBER(SEARCH("ss",J:J)),"",IF(ISNUMBER(SEARCH("0.8mm",J:J)),T18*2.2,IF(ISNUMBER(SEARCH("1mm",J:J)),T18*2.75,IF(ISNUMBER(SEARCH("1.2mm",J:J)),T18*3.3,IF(ISNUMBER(SEARCH("Gasket",J:J)),"",IF(ISNUMBER(SEARCH("Cleats",J:J)),"",IF(ISNUMBER(SEARCH("Sealant",J:J)),"",IF(ISNUMBER(SEARCH("Bracket",J:J)),"",IF(ISNUMBER(SEARCH("Corner",J:J)),"",IF(ISNUMBER(SEARCH("Bubble",J:J)),"","")))))))))))))))))) | Y18: =IF(K18="Sqmt",(T18/O18)*100,IF(K18="Kg's","",IF(K18="No's","",IF(K18="Rmt","",IF(K18="Roll","",IF(K18="","")))))) | Z18: =IF(K18="Sqmt",(U18/O18)*100,IF(K18="Kg's","",IF(K18="No's","",IF(K18="Rmt","",IF(K18="Roll","",IF(K18="","")))))) | AB18: =IFERROR((X18-AA18),"")
A19: =IF(C19="","",COUNTA($C$3:C19)) -> 17 | B19: =IF(C19="","",TEXT(C19,"mmmm")) -> April | C19: 44658 | D19: 2302-64005 | F19: 44616 | G19: Knnd Associates Pvt Ltd | H19: Google Kyoto West 5Th Floor Oval Duct | I19: Spiral Oval Duct with Paint | J19: 120gsm Slit 24G | K19: =IF(ISNUMBER(SEARCH("gsm",J:J)),"Sqmt",IF(ISNUMBER(SEARCH("Tape",J:J)),"Roll",IF(ISNUMBER(SEARCH("Thermal",J:J)),"Sqmt",IF(ISNUMBER(SEARCH("Acou",J:J)),"Sqmt",IF(ISNUMBER(SEARCH("ss",J:J)),"Sqmt",IF(ISNUMBER(SEARCH("Alu",J:J)),"Sqmt",IF(ISNUMBER(SEARCH("Gasket",J:J)),"Rmt",IF(ISNUMBER(SEARCH("Cleats",J:J)),"No's",IF(ISNUMBER(SEARCH("Tube",J:J)),"No's",IF(ISNUMBER(SEARCH("Bracket",J:J)),"No's",IF(ISNUMBER(SEARCH("Corner",J:J)),"No's",IF(ISNUMBER(SEARCH("MS",J:J)),"Kg's",IF(ISNUMBER(SEARCH("Bucket",J:J)),"Kg's",IF(ISNUMBER(SEARCH("stretch",J:J)),"Kg's",IF(ISNUMBER(SEARCH("Bubble",J:J)),"Roll",IF(ISNUMBER(SEARCH("JTR",J:J)),"Rmt",IF(ISNUMBER(SEARCH("Clamp",J:J)),"No's",IF(ISNUMBER(SEARCH("PIR",J:J)),"sqmt","")))))))))))))))))) -> Sqmt | L19: 25.2 | M19: 20.655738 | O19: =IF(ISNUMBER(SEARCH("gsm",J:J)),(M19+N19)*1.22,IF(ISNUMBER(SEARCH("Tape",J:J)),L19,IF(ISNUMBER(SEARCH("Thermal",J:J)),L19,IF(ISNUMBER(SEARCH("Acou",J:J)),L19,IF(ISNUMBER(SEARCH("ss",J:J)),L19,IF(ISNUMBER(SEARCH("Alu",J:J)),L19,IF(ISNUMBER(SEARCH("Gasket",J:J)),L19,IF(ISNUMBER(SEARCH("Cleats",J:J)),L19,IF(ISNUMBER(SEARCH("Tube",J:J)),L19,IF(ISNUMBER(SEARCH("Bracket",J:J)),L19,IF(ISNUMBER(SEARCH("Corner",J:J)),L19,IF(ISNUMBER(SEARCH("MS",J:J)),L19,IF(ISNUMBER(SEARCH("Bucket",J:J)),L19,IF(ISNUMBER(SEARCH("stretch",J:J)),L19,IF(ISNUMBER(SEARCH("Bubble",J:J)),L19,IF(ISNUMBER(SEARCH("JTR",J:J)),L19,IF(ISNUMBER(SEARCH("Clamp",J:J)),"No's",IF(ISNUMBER(SEARCH("PIR",J:J)),"sqmt","")))))))))))))))))) -> 25.2 | P19: 21 | Q19: 21.6 | R19: 35 | S19: 65 | T19: =(IF(K19="Sqmt",(O19-Q19),"")) -> 3.6 | U19: =(IF(K19="Sqmt",(O19-P19)-T19,IF(K19="Rmt","",IF(K19="Kg's","",IF(K19="No's","",IF(K19="Roll","","")))))) -> 0.6 | V19: =IF(ISNUMBER(SEARCH("26",J:J)),O19*3.925,IF(ISNUMBER(SEARCH("24",J:J)),O19*4.71,IF(ISNUMBER(SEARCH("22",J:J)),O19*6.28,IF(ISNUMBER(SEARCH("20",J:J)),O19*7.85,IF(ISNUMBER(SEARCH("18G",J:J)),O19*9.42,IF(ISNUMBER(SEARCH("16G",J:J)),O19*11.775,IF(ISNUMBER(SEARCH("Thermal",J:J)),O19,IF(ISNUMBER(SEARCH("Acou",J:J)),O19,IF(ISNUMBER(SEARCH("ss",J:J)),O19,IF(ISNUMBER(SEARCH("0.8mm",J:J)),O19*2.2,IF(ISNUMBER(SEARCH("1mm",J:J)),O19*2.75,IF(ISNUMBER(SEARCH("1.2mm",J:J)),O19*3.3,IF(ISNUMBER(SEARCH("Gasket",J:J)),O19,IF(ISNUMBER(SEARCH("Cleats",J:J)),O19,IF(ISNUMBER(SEARCH("Sealant",J:J)),O19,IF(ISNUMBER(SEARCH("Bracket",J:J)),O19,IF(ISNUMBER(SEARCH("Corner",J:J)),O19,IF(ISNUMBER(SEARCH("Bubble",J:J)),O19,"")))))))))))))))))) -> 118.692 | W19: =IF(ISNUMBER(SEARCH("26",J:J)),U19*3.925,IF(ISNUMBER(SEARCH("24",J:J)),U19*4.71,IF(ISNUMBER(SEARCH("22",J:J)),U19*6.28,IF(ISNUMBER(SEARCH("20",J:J)),U19*7.85,IF(ISNUMBER(SEARCH("18G",J:J)),U19*9.42,IF(ISNUMBER(SEARCH("16G",J:J)),U19*11.775,IF(ISNUMBER(SEARCH("Thermal",J:J)),U19,IF(ISNUMBER(SEARCH("Acou",J:J)),U19,IF(ISNUMBER(SEARCH("ss",J:J)),U19,IF(ISNUMBER(SEARCH("0.8mm",J:J)),U19*2.2,IF(ISNUMBER(SEARCH("1mm",J:J)),U19*2.75,IF(ISNUMBER(SEARCH("1.2mm",J:J)),U19*3.3,IF(ISNUMBER(SEARCH("Gasket",J:J)),U19,IF(ISNUMBER(SEARCH("Cleats",J:J)),U19,IF(ISNUMBER(SEARCH("Sealant",J:J)),U19,IF(ISNUMBER(SEARCH("Bracket",J:J)),U19,IF(ISNUMBER(SEARCH("Corner",J:J)),U19,IF(ISNUMBER(SEARCH("Bubble",J:J)),U19,"")))))))))))))))))) -> 2.826 | X19: =IF(ISNUMBER(SEARCH("26",J:J)),T19*3.925,IF(ISNUMBER(SEARCH("24",J:J)),T19*4.71,IF(ISNUMBER(SEARCH("22",J:J)),T19*6.28,IF(ISNUMBER(SEARCH("20",J:J)),T19*7.85,IF(ISNUMBER(SEARCH("18",J:J)),T19*9.42,IF(ISNUMBER(SEARCH("16",J:J)),T19*11.775,IF(ISNUMBER(SEARCH("Thermal",J:J)),"",IF(ISNUMBER(SEARCH("Acou",J:J)),"",IF(ISNUMBER(SEARCH("ss",J:J)),"",IF(ISNUMBER(SEARCH("0.8mm",J:J)),T19*2.2,IF(ISNUMBER(SEARCH("1mm",J:J)),T19*2.75,IF(ISNUMBER(SEARCH("1.2mm",J:J)),T19*3.3,IF(ISNUMBER(SEARCH("Gasket",J:J)),"",IF(ISNUMBER(SEARCH("Cleats",J:J)),"",IF(ISNUMBER(SEARCH("Sealant",J:J)),"",IF(ISNUMBER(SEARCH("Bracket",J:J)),"",IF(ISNUMBER(SEARCH("Corner",J:J)),"",IF(ISNUMBER(SEARCH("Bubble",J:J)),"","")))))))))))))))))) -> 16.956 | Y19: =IF(K19="Sqmt",(T19/O19)*100,IF(K19="Kg's","",IF(K19="No's","",IF(K19="Rmt","",IF(K19="Roll","",IF(K19="","")))))) -> 14.285714 | Z19: =IF(K19="Sqmt",(U19/O19)*100,IF(K19="Kg's","",IF(K19="No's","",IF(K19="Rmt","",IF(K19="Roll","",IF(K19="","")))))) -> 2.3809524 | AB19: =IFERROR((X19-AA19),"") -> 16.956
A20: =IF(C20="","",COUNTA($C$3:C20)) -> 18 | B20: =IF(C20="","",TEXT(C20,"mmmm")) -> April | C20: 44658 | D20: 2302-64005 | F20: 44616 | G20: Knnd Associates Pvt Ltd | H20: Google Kyoto West 5Th Floor Oval Duct | I20: Spiral Oval Duct with Paint | J20: 120gsm 24G | K20: =IF(ISNUMBER(SEARCH("gsm",J:J)),"Sqmt",IF(ISNUMBER(SEARCH("Tape",J:J)),"Roll",IF(ISNUMBER(SEARCH("Thermal",J:J)),"Sqmt",IF(ISNUMBER(SEARCH("Acou",J:J)),"Sqmt",IF(ISNUMBER(SEARCH("ss",J:J)),"Sqmt",IF(ISNUMBER(SEARCH("Alu",J:J)),"Sqmt",IF(ISNUMBER(SEARCH("Gasket",J:J)),"Rmt",IF(ISNUMBER(SEARCH("Cleats",J:J)),"No's",IF(ISNUMBER(SEARCH("Tube",J:J)),"No's",IF(ISNUMBER(SEARCH("Bracket",J:J)),"No's",IF(ISNUMBER(SEARCH("Corner",J:J)),"No's",IF(ISNUMBER(SEARCH("MS",J:J)),"Kg's",IF(ISNUMBER(SEARCH("Bucket",J:J)),"Kg's",IF(ISNUMBER(SEARCH("stretch",J:J)),"Kg's",IF(ISNUMBER(SEARCH("Bubble",J:J)),"Roll",IF(ISNUMBER(SEARCH("JTR",J:J)),"Rmt",IF(ISNUMBER(SEARCH("Clamp",J:J)),"No's",IF(ISNUMBER(SEARCH("PIR",J:J)),"sqmt","")))))))))))))))))) -> Sqmt | L20: 64.9 | N20: 53.2 | O20: =IF(ISNUMBER(SEARCH("gsm",J:J)),(M20+N20)*1.22,IF(ISNUMBER(SEARCH("Tape",J:J)),L20,IF(ISNUMBER(SEARCH("Thermal",J:J)),L20,IF(ISNUMBER(SEARCH("Acou",J:J)),L20,IF(ISNUMBER(SEARCH("ss",J:J)),L20,IF(ISNUMBER(SEARCH("Alu",J:J)),L20,IF(ISNUMBER(SEARCH("Gasket",J:J)),L20,IF(ISNUMBER(SEARCH("Cleats",J:J)),L20,IF(ISNUMBER(SEARCH("Tube",J:J)),L20,IF(ISNUMBER(SEARCH("Bracket",J:J)),L20,IF(ISNUMBER(SEARCH("Corner",J:J)),L20,IF(ISNUMBER(SEARCH("MS",J:J)),L20,IF(ISNUMBER(SEARCH("Bucket",J:J)),L20,IF(ISNUMBER(SEARCH("stretch",J:J)),L20,IF(ISNUMBER(SEARCH("Bubble",J:J)),L20,IF(ISNUMBER(SEARCH("JTR",J:J)),L20,IF(ISNUMBER(SEARCH("Clamp",J:J)),"No's",IF(ISNUMBER(SEARCH("PIR",J:J)),"sqmt","")))))))))))))))))) -> 64.904 | P20: 48.8 | Q20: 58.6 | T20: =(IF(K20="Sqmt",(O20-Q20),"")) -> 6.304 | U20: =(IF(K20="Sqmt",(O20-P20)-T20,IF(K20="Rmt","",IF(K20="Kg's","",IF(K20="No's","",IF(K20="Roll","","")))))) -> 9.8 | V20: =IF(ISNUMBER(SEARCH("26",J:J)),O20*3.925,IF(ISNUMBER(SEARCH("24",J:J)),O20*4.71,IF(ISNUMBER(SEARCH("22",J:J)),O20*6.28,IF(ISNUMBER(SEARCH("20",J:J)),O20*7.85,IF(ISNUMBER(SEARCH("18G",J:J)),O20*9.42,IF(ISNUMBER(SEARCH("16G",J:J)),O20*11.775,IF(ISNUMBER(SEARCH("Thermal",J:J)),O20,IF(ISNUMBER(SEARCH("Acou",J:J)),O20,IF(ISNUMBER(SEARCH("ss",J:J)),O20,IF(ISNUMBER(SEARCH("0.8mm",J:J)),O20*2.2,IF(ISNUMBER(SEARCH("1mm",J:J)),O20*2.75,IF(ISNUMBER(SEARCH("1.2mm",J:J)),O20*3.3,IF(ISNUMBER(SEARCH("Gasket",J:J)),O20,IF(ISNUMBER(SEARCH("Cleats",J:J)),O20,IF(ISNUMBER(SEARCH("Sealant",J:J)),O20,IF(ISNUMBER(SEARCH("Bracket",J:J)),O20,IF(ISNUMBER(SEARCH("Corner",J:J)),O20,IF(ISNUMBER(SEARCH("Bubble",J:J)),O20,"")))))))))))))))))) -> 305.69784 | W20: =IF(ISNUMBER(SEARCH("26",J:J)),U20*3.925,IF(ISNUMBER(SEARCH("24",J:J)),U20*4.71,IF(ISNUMBER(SEARCH("22",J:J)),U20*6.28,IF(ISNUMBER(SEARCH("20",J:J)),U20*7.85,IF(ISNUMBER(SEARCH("18G",J:J)),U20*9.42,IF(ISNUMBER(SEARCH("16G",J:J)),U20*11.775,IF(ISNUMBER(SEARCH("Thermal",J:J)),U20,IF(ISNUMBER(SEARCH("Acou",J:J)),U20,IF(ISNUMBER(SEARCH("ss",J:J)),U20,IF(ISNUMBER(SEARCH("0.8mm",J:J)),U20*2.2,IF(ISNUMBER(SEARCH("1mm",J:J)),U20*2.75,IF(ISNUMBER(SEARCH("1.2mm",J:J)),U20*3.3,IF(ISNUMBER(SEARCH("Gasket",J:J)),U20,IF(ISNUMBER(SEARCH("Cleats",J:J)),U20,IF(ISNUMBER(SEARCH("Sealant",J:J)),U20,IF(ISNUMBER(SEARCH("Bracket",J:J)),U20,IF(ISNUMBER(SEARCH("Corner",J:J)),U20,IF(ISNUMBER(SEARCH("Bubble",J:J)),U20,"")))))))))))))))))) -> 46.158 | X20: =IF(ISNUMBER(SEARCH("26",J:J)),T20*3.925,IF(ISNUMBER(SEARCH("24",J:J)),T20*4.71,IF(ISNUMBER(SEARCH("22",J:J)),T20*6.28,IF(ISNUMBER(SEARCH("20",J:J)),T20*7.85,IF(ISNUMBER(SEARCH("18",J:J)),T20*9.42,IF(ISNUMBER(SEARCH("16",J:J)),T20*11.775,IF(ISNUMBER(SEARCH("Thermal",J:J)),"",IF(ISNUMBER(SEARCH("Acou",J:J)),"",IF(ISNUMBER(SEARCH("ss",J:J)),"",IF(ISNUMBER(SEARCH("0.8mm",J:J)),T20*2.2,IF(ISNUMBER(SEARCH("1mm",J:J)),T20*2.75,IF(ISNUMBER(SEARCH("1.2mm",J:J)),T20*3.3,IF(ISNUMBER(SEARCH("Gasket",J:J)),"",IF(ISNUMBER(SEARCH("Cleats",J:J)),"",IF(ISNUMBER(SEARCH("Sealant",J:J)),"",IF(ISNUMBER(SEARCH("Bracket",J:J)),"",IF(ISNUMBER(SEARCH("Corner",J:J)),"",IF(ISNUMBER(SEARCH("Bubble",J:J)),"","")))))))))))))))))) -> 29.69184 | Y20: =IF(K20="Sqmt",(T20/O20)*100,IF(K20="Kg's","",IF(K20="No's","",IF(K20="Rmt","",IF(K20="Roll","",IF(K20="","")))))) -> 9.7128066 | Z20: =IF(K20="Sqmt",(U20/O20)*100,IF(K20="Kg's","",IF(K20="No's","",IF(K20="Rmt","",IF(K20="Roll","",IF(K20="","")))))) -> 15.099223 | AB20: =IFERROR((X20-AA20),"") -> 29.69184
A21: =IF(C21="","",COUNTA($C$3:C21)) -> 19 | B21: =IF(C21="","",TEXT(C21,"mmmm")) -> April | C21: 44658 | D21: 2302-64005 | F21: 44616 | G21: Knnd Associates Pvt Ltd | H21: Google Kyoto West 5Th Floor Oval Duct | I21: Spiral Oval Duct with Paint | J21: 120gsm Slit 22G | K21: =IF(ISNUMBER(SEARCH("gsm",J:J)),"Sqmt",IF(ISNUMBER(SEARCH("Tape",J:J)),"Roll",IF(ISNUMBER(SEARCH("Thermal",J:J)),"Sqmt",IF(ISNUMBER(SEARCH("Acou",J:J)),"Sqmt",IF(ISNUMBER(SEARCH("ss",J:J)),"Sqmt",IF(ISNUMBER(SEARCH("Alu",J:J)),"Sqmt",IF(ISNUMBER(SEARCH("Gasket",J:J)),"Rmt",IF(ISNUMBER(SEARCH("Cleats",J:J)),"No's",IF(ISNUMBER(SEARCH("Tube",J:J)),"No's",IF(ISNUMBER(SEARCH("Bracket",J:J)),"No's",IF(ISNUMBER(SEARCH("Corner",J:J)),"No's",IF(ISNUMBER(SEARCH("MS",J:J)),"Kg's",IF(ISNUMBER(SEARCH("Bucket",J:J)),"Kg's",IF(ISNUMBER(SEARCH("stretch",J:J)),"Kg's",IF(ISNUMBER(SEARCH("Bubble",J:J)),"Roll",IF(ISNUMBER(SEARCH("JTR",J:J)),"Rmt",IF(ISNUMBER(SEARCH("Clamp",J:J)),"No's",IF(ISNUMBER(SEARCH("PIR",J:J)),"sqmt","")))))))))))))))))) -> Sqmt | L21: 105.7 | M21: 86.639344 | O21: =IF(ISNUMBER(SEARCH("gsm",J:J)),(M21+N21)*1.22,IF(ISNUMBER(SEARCH("Tape",J:J)),L21,IF(ISNUMBER(SEARCH("Thermal",J:J)),L21,IF(ISNUMBER(SEARCH("Acou",J:J)),L21,IF(ISNUMBER(SEARCH("ss",J:J)),L21,IF(ISNUMBER(SEARCH("Alu",J:J)),L21,IF(ISNUMBER(SEARCH("Gasket",J:J)),L21,IF(ISNUMBER(SEARCH("Cleats",J:J)),L21,IF(ISNUMBER(SEARCH("Tube",J:J)),L21,IF(ISNUMBER(SEARCH("Bracket",J:J)),L21,IF(ISNUMBER(SEARCH("Corner",J:J)),L21,IF(ISNUMBER(SEARCH("MS",J:J)),L21,IF(ISNUMBER(SEARCH("Bucket",J:J)),L21,IF(ISNUMBER(SEARCH("stretch",J:J)),L21,IF(ISNUMBER(SEARCH("Bubble",J:J)),L21,IF(ISNUMBER(SEARCH("JTR",J:J)),L21,IF(ISNUMBER(SEARCH("Clamp",J:J)),"No's",IF(ISNUMBER(SEARCH("PIR",J:J)),"sqmt","")))))))))))))))))) -> 105.7 | P21: 88.15 | Q21: 90.2 | T21: =(IF(K21="Sqmt",(O21-Q21),"")) -> 15.5 | U21: =(IF(K21="Sqmt",(O21-P21)-T21,IF(K21="Rmt","",IF(K21="Kg's","",IF(K21="No's","",IF(K21="Roll","","")))))) -> 2.05 | V21: =IF(ISNUMBER(SEARCH("26",J:J)),O21*3.925,IF(ISNUMBER(SEARCH("24",J:J)),O21*4.71,IF(ISNUMBER(SEARCH("22",J:J)),O21*6.28,IF(ISNUMBER(SEARCH("20",J:J)),O21*7.85,IF(ISNUMBER(SEARCH("18G",J:J)),O21*9.42,IF(ISNUMBER(SEARCH("16G",J:J)),O21*11.775,IF(ISNUMBER(SEARCH("Thermal",J:J)),O21,IF(ISNUMBER(SEARCH("Acou",J:J)),O21,IF(ISNUMBER(SEARCH("ss",J:J)),O21,IF(ISNUMBER(SEARCH("0.8mm",J:J)),O21*2.2,IF(ISNUMBER(SEARCH("1mm",J:J)),O21*2.75,IF(ISNUMBER(SEARCH("1.2mm",J:J)),O21*3.3,IF(ISNUMBER(SEARCH("Gasket",J:J)),O21,IF(ISNUMBER(SEARCH("Cleats",J:J)),O21,IF(ISNUMBER(SEARCH("Sealant",J:J)),O21,IF(ISNUMBER(SEARCH("Bracket",J:J)),O21,IF(ISNUMBER(SEARCH("Corner",J:J)),O21,IF(ISNUMBER(SEARCH("Bubble",J:J)),O21,"")))))))))))))))))) -> 663.796 | W21: =IF(ISNUMBER(SEARCH("26",J:J)),U21*3.925,IF(ISNUMBER(SEARCH("24",J:J)),U21*4.71,IF(ISNUMBER(SEARCH("22",J:J)),U21*6.28,IF(ISNUMBER(SEARCH("20",J:J)),U21*7.85,IF(ISNUMBER(SEARCH("18G",J:J)),U21*9.42,IF(ISNUMBER(SEARCH("16G",J:J)),U21*11.775,IF(ISNUMBER(SEARCH("Thermal",J:J)),U21,IF(ISNUMBER(SEARCH("Acou",J:J)),U21,IF(ISNUMBER(SEARCH("ss",J:J)),U21,IF(ISNUMBER(SEARCH("0.8mm",J:J)),U21*2.2,IF(ISNUMBER(SEARCH("1mm",J:J)),U21*2.75,IF(ISNUMBER(SEARCH("1.2mm",J:J)),U21*3.3,IF(ISNUMBER(SEARCH("Gasket",J:J)),U21,IF(ISNUMBER(SEARCH("Cleats",J:J)),U21,IF(ISNUMBER(SEARCH("Sealant",J:J)),U21,IF(ISNUMBER(SEARCH("Bracket",J:J)),U21,IF(ISNUMBER(SEARCH("Corner",J:J)),U21,IF(ISNUMBER(SEARCH("Bubble",J:J)),U21,"")))))))))))))))))) -> 12.874 | X21: =IF(ISNUMBER(SEARCH("26",J:J)),T21*3.925,IF(ISNUMBER(SEARCH("24",J:J)),T21*4.71,IF(ISNUMBER(SEARCH("22",J:J)),T21*6.28,IF(ISNUMBER(SEARCH("20",J:J)),T21*7.85,IF(ISNUMBER(SEARCH("18",J:J)),T21*9.42,IF(ISNUMBER(SEARCH("16",J:J)),T21*11.775,IF(ISNUMBER(SEARCH("Thermal",J:J)),"",IF(ISNUMBER(SEARCH("Acou",J:J)),"",IF(ISNUMBER(SEARCH("ss",J:J)),"",IF(ISNUMBER(SEARCH("0.8mm",J:J)),T21*2.2,IF(ISNUMBER(SEARCH("1mm",J:J)),T21*2.75,IF(ISNUMBER(SEARCH("1.2mm",J:J)),T21*3.3,IF(ISNUMBER(SEARCH("Gasket",J:J)),"",IF(ISNUMBER(SEARCH("Cleats",J:J)),"",IF(ISNUMBER(SEARCH("Sealant",J:J)),"",IF(ISNUMBER(SEARCH("Bracket",J:J)),"",IF(ISNUMBER(SEARCH("Corner",J:J)),"",IF(ISNUMBER(SEARCH("Bubble",J:J)),"","")))))))))))))))))) -> 97.34 | Y21: =IF(K21="Sqmt",(T21/O21)*100,IF(K21="Kg's","",IF(K21="No's","",IF(K21="Rmt","",IF(K21="Roll","",IF(K21="","")))))) -> 14.664144 | Z21: =IF(K21="Sqmt",(U21/O21)*100,IF(K21="Kg's","",IF(K21="No's","",IF(K21="Rmt","",IF(K21="Roll","",IF(K21="","")))))) -> 1.9394513 | AB21: =IFERROR((X21-AA21),"") -> 97.34
A22: =IF(C22="","",COUNTA($C$3:C22)) -> 20 | B22: =IF(C22="","",TEXT(C22,"mmmm")) -> April | C22: 44658 | D22: 2302-64005 | F22: 44616 | G22: Knnd Associates Pvt Ltd | H22: Google Kyoto West 5Th Floor Oval Duct | I22: Spiral Oval Duct with Paint | J22: 120gsm 22G | K22: =IF(ISNUMBER(SEARCH("gsm",J:J)),"Sqmt",IF(ISNUMBER(SEARCH("Tape",J:J)),"Roll",IF(ISNUMBER(SEARCH("Thermal",J:J)),"Sqmt",IF(ISNUMBER(SEARCH("Acou",J:J)),"Sqmt",IF(ISNUMBER(SEARCH("ss",J:J)),"Sqmt",IF(ISNUMBER(SEARCH("Alu",J:J)),"Sqmt",IF(ISNUMBER(SEARCH("Gasket",J:J)),"Rmt",IF(ISNUMBER(SEARCH("Cleats",J:J)),"No's",IF(ISNUMBER(SEARCH("Tube",J:J)),"No's",IF(ISNUMBER(SEARCH("Bracket",J:J)),"No's",IF(ISNUMBER(SEARCH("Corner",J:J)),"No's",IF(ISNUMBER(SEARCH("MS",J:J)),"Kg's",IF(ISNUMBER(SEARCH("Bucket",J:J)),"Kg's",IF(ISNUMBER(SEARCH("stretch",J:J)),"Kg's",IF(ISNUMBER(SEARCH("Bubble",J:J)),"Roll",IF(ISNUMBER(SEARCH("JTR",J:J)),"Rmt",IF(ISNUMBER(SEARCH("Clamp",J:J)),"No's",IF(ISNUMBER(SEARCH("PIR",J:J)),"sqmt","")))))))))))))))))) -> Sqmt | L22: 43.2 | N22: 35.41 | O22: =IF(ISNUMBER(SEARCH("gsm",J:J)),(M22+N22)*1.22,IF(ISNUMBER(SEARCH("Tape",J:J)),L22,IF(ISNUMBER(SEARCH("Thermal",J:J)),L22,IF(ISNUMBER(SEARCH("Acou",J:J)),L22,IF(ISNUMBER(SEARCH("ss",J:J)),L22,IF(ISNUMBER(SEARCH("Alu",J:J)),L22,IF(ISNUMBER(SEARCH("Gasket",J:J)),L22,IF(ISNUMBER(SEARCH("Cleats",J:J)),L22,IF(ISNUMBER(SEARCH("Tube",J:J)),L22,IF(ISNUMBER(SEARCH("Bracket",J:J)),L22,IF(ISNUMBER(SEARCH("Corner",J:J)),L22,IF(ISNUMBER(SEARCH("MS",J:J)),L22,IF(ISNUMBER(SEARCH("Bucket",J:J)),L22,IF(ISNUMBER(SEARCH("stretch",J:J)),L22,IF(ISNUMBER(SEARCH("Bubble",J:J)),L22,IF(ISNUMBER(SEARCH("JTR",J:J)),L22,IF(ISNUMBER(SEARCH("Clamp",J:J)),"No's",IF(ISNUMBER(SEARCH("PIR",J:J)),"sqmt","")))))))))))))))))) -> 43.2002 | P22: 30.5 | Q22: 33.6 | T22: =(IF(K22="Sqmt",(O22-Q22),"")) -> 9.6002 | U22: =(IF(K22="Sqmt",(O22-P22)-T22,IF(K22="Rmt","",IF(K22="Kg's","",IF(K22="No's","",IF(K22="Roll","","")))))) -> 3.1 | V22: =IF(ISNUMBER(SEARCH("26",J:J)),O22*3.925,IF(ISNUMBER(SEARCH("24",J:J)),O22*4.71,IF(ISNUMBER(SEARCH("22",J:J)),O22*6.28,IF(ISNUMBER(SEARCH("20",J:J)),O22*7.85,IF(ISNUMBER(SEARCH("18G",J:J)),O22*9.42,IF(ISNUMBER(SEARCH("16G",J:J)),O22*11.775,IF(ISNUMBER(SEARCH("Thermal",J:J)),O22,IF(ISNUMBER(SEARCH("Acou",J:J)),O22,IF(ISNUMBER(SEARCH("ss",J:J)),O22,IF(ISNUMBER(SEARCH("0.8mm",J:J)),O22*2.2,IF(ISNUMBER(SEARCH("1mm",J:J)),O22*2.75,IF(ISNUMBER(SEARCH("1.2mm",J:J)),O22*3.3,IF(ISNUMBER(SEARCH("Gasket",J:J)),O22,IF(ISNUMBER(SEARCH("Cleats",J:J)),O22,IF(ISNUMBER(SEARCH("Sealant",J:J)),O22,IF(ISNUMBER(SEARCH("Bracket",J:J)),O22,IF(ISNUMBER(SEARCH("Corner",J:J)),O22,IF(ISNUMBER(SEARCH("Bubble",J:J)),O22,"")))))))))))))))))) -> 271.29726 | W22: =IF(ISNUMBER(SEARCH("26",J:J)),U22*3.925,IF(ISNUMBER(SEARCH("24",J:J)),U22*4.71,IF(ISNUMBER(SEARCH("22",J:J)),U22*6.28,IF(ISNUMBER(SEARCH("20",J:J)),U22*7.85,IF(ISNUMBER(SEARCH("18G",J:J)),U22*9.42,IF(ISNUMBER(SEARCH("16G",J:J)),U22*11.775,IF(ISNUMBER(SEARCH("Thermal",J:J)),U22,IF(ISNUMBER(SEARCH("Acou",J:J)),U22,IF(ISNUMBER(SEARCH("ss",J:J)),U22,IF(ISNUMBER(SEARCH("0.8mm",J:J)),U22*2.2,IF(ISNUMBER(SEARCH("1mm",J:J)),U22*2.75,IF(ISNUMBER(SEARCH("1.2mm",J:J)),U22*3.3,IF(ISNUMBER(SEARCH("Gasket",J:J)),U22,IF(ISNUMBER(SEARCH("Cleats",J:J)),U22,IF(ISNUMBER(SEARCH("Sealant",J:J)),U22,IF(ISNUMBER(SEARCH("Bracket",J:J)),U22,IF(ISNUMBER(SEARCH("Corner",J:J)),U22,IF(ISNUMBER(SEARCH("Bubble",J:J)),U22,"")))))))))))))))))) -> 19.468 | X22: =IF(ISNUMBER(SEARCH("26",J:J)),T22*3.925,IF(ISNUMBER(SEARCH("24",J:J)),T22*4.71,IF(ISNUMBER(SEARCH("22",J:J)),T22*6.28,IF(ISNUMBER(SEARCH("20",J:J)),T22*7.85,IF(ISNUMBER(SEARCH("18",J:J)),T22*9.42,IF(ISNUMBER(SEARCH("16",J:J)),T22*11.775,IF(ISNUMBER(SEARCH("Thermal",J:J)),"",IF(ISNUMBER(SEARCH("Acou",J:J)),"",IF(ISNUMBER(SEARCH("ss",J:J)),"",IF(ISNUMBER(SEARCH("0.8mm",J:J)),T22*2.2,IF(ISNUMBER(SEARCH("1mm",J:J)),T22*2.75,IF(ISNUMBER(SEARCH("1.2mm",J:J)),T22*3.3,IF(ISNUMBER(SEARCH("Gasket",J:J)),"",IF(ISNUMBER(SEARCH("Cleats",J:J)),"",IF(ISNUMBER(SEARCH("Sealant",J:J)),"",IF(ISNUMBER(SEARCH("Bracket",J:J)),"",IF(ISNUMBER(SEARCH("Corner",J:J)),"",IF(ISNUMBER(SEARCH("Bubble",J:J)),"","")))))))))))))))))) -> 60.289256 | Y22: =IF(K22="Sqmt",(T22/O22)*100,IF(K22="Kg's","",IF(K22="No's","",IF(K22="Rmt","",IF(K22="Roll","",IF(K22="","")))))) -> 22.222582 | Z22: =IF(K22="Sqmt",(U22/O22)*100,IF(K22="Kg's","",IF(K22="No's","",IF(K22="Rmt","",IF(K22="Roll","",IF(K22="","")))))) -> 7.1758927 | AB22: =IFERROR((X22-AA22),"") -> 60.289256
